Workbook
Name PROJECT_YEARS: 'Assumptions'!$C$9
Name FX_VND_PER_USD: 'Assumptions'!$C$41
Name PV_CAPEX: 'Assumptions'!$C$44
Name BESS_CAPEX: 'Assumptions'!$C$45
Name OTHER_CAPEX: 'Assumptions'!$C$46
Name TOTAL_CAPEX: 'Assumptions'!$C$47
Name OM_YEAR1: 'Assumptions'!$C$49
Name ESC_OM: 'Assumptions'!$C$50
Name BESS_CYCLE_LIFE: 'Assumptions'!$C$53
Name ESC_ENERGY: 'Assumptions'!$C$58
Name ESC_CAPACITY: 'Assumptions'!$C$59
Name PV_DEGRADATION: 'Assumptions'!$C$60
Name ESCO_DISCOUNT: 'Assumptions'!$C$64
Name DEMAND_SHARE: 'Assumptions'!$C$65
Name ESC_STRIKE: 'Assumptions'!$C$68
Name ESC_FEE: 'Assumptions'!$C$69
Name DEBT_FRACTION: 'Assumptions'!$C$78
Name DEBT_RATE: 'Assumptions'!$C$79
Name DEBT_TERM_YEARS: 'Assumptions'!$C$80
Name DEBT_PRINCIPAL: 'Assumptions'!$C$81
Name EQUITY_INVESTMENT: 'Assumptions'!$C$82
Name DEBT_PAYMENT: 'Assumptions'!$C$83
Name DISC_RATE: 'Assumptions'!$C$84
Name CIT_RATE: 'Assumptions'!$C$87
Name CIT_PREF_RATE: 'Assumptions'!$C$88
Name CIT_PREF_YEARS: 'Assumptions'!$C$89
Name CIT_HOLIDAY_YEARS: 'Assumptions'!$C$90
Name CIT_REDUCED_YEARS: 'Assumptions'!$C$91
Name CIT_REDUCED_FRACTION: 'Assumptions'!$C$92
Name CIT_LOSS_CF_YEARS: 'Assumptions'!$C$93
Name CIT_CLOCK_CAP_YEAR: 'Assumptions'!$C$94
Name PV_DEP_YEARS: 'Assumptions'!$C$95
Name BESS_DEP_YEARS: 'Assumptions'!$C$96
Name BAU_BILL_Y1: 'Assumptions'!$C$98
Name OPT_BILL_Y1: 'Assumptions'!$C$99
Name BAU_DEMAND_Y1: 'Assumptions'!$C$100
Name OPT_DEMAND_Y1: 'Assumptions'!$C$101
Name BASE_DEMAND_SAVINGS: 'Assumptions'!$C$102
Name BASE_SERVED_RETAIL: 'Assumptions'!$C$103
Name BESS_ENERGY_REV: 'Assumptions'!$C$104
Name BESS_SERVED_RETAIL: 'Assumptions'!$C$105
Name BESS_UNSERVED_VALUE: 'Assumptions'!$C$106
Name BESS_DEMAND_SAVINGS: 'Assumptions'!$C$107
Name BESS_MATCHED_SHARE: 'Assumptions'!$C$108
Name DPPA_C_DN_Y1: 'Assumptions'!$C$109
Name DPPA_C_DPPA_Y1: 'Assumptions'!$C$110
Name DPPA_C_CL_Y1: 'Assumptions'!$C$111
Name DPPA_C_BL_Y1: 'Assumptions'!$C$112
Name DPPA_CFD_STRIKE_Y1: 'Assumptions'!$C$113
Name DPPA_CFD_OFFSET_Y1: 'Assumptions'!$C$114
Name DPPA_FMP_REV_Y1: 'Assumptions'!$C$115
Name DPPA_MATCHED_RETAIL_Y1: 'Assumptions'!$C$116

Sheet Cover
B2: Investment Case Workbook - Factory A Vietnam DPPA Grid CfD E2E
B3: Grid-connected DPPA with CfD (ND57/2025) · prepared 2026-09-12 · REopt dispatch + proforma_vietnam financial engine
B4: REopt run UUID: 3c7f58d2-b360-4045-9af4-bd57507e9fb3
B6: Model validation status | C6: =IF(COUNTIF('Pro Forma (Audit)'!F98:F106,"REVIEW")+COUNTIF('FX Sensitivity'!F5:F8,"REVIEW")=0,"ALL CHECKS PASS","REVIEW REQUIRED") | D6: Live tie-out of every Excel-derived metric against the engine
B8: Colour legend
B9: Hardcoded input / engine output | C9: Case file terms, REopt dispatch results, 8760-h settlement totals, tie-out references
B10: Live Excel formula (white) | C10: Everything derivable is a formula - trace with Excel's formula auditing tools
B11: PASS / REVIEW check cell | C11: Excel-vs-engine tie-out at stated tolerances
B13: Contents
B14: Executive Summary | C14: Headline KPIs for both counterparties
B15: Assumptions | C15: Every case input & contract term with unit, source and named cell
B16: Model Basis | C16: Methodology, settlement math, simplifications register
B17: Pro Forma (Audit) | C17: Full cash flow rebuilt with live formulas + engine tie-out
B18: FX Sensitivity | C18: USD returns under VND depreciation (editable)
B19: Buyer Analysis | C19: Offtaker savings vs business-as-usual
B20: Developer Returns | C20: Sources & uses, coverage, equity cash flow
B21: Technical Results | C21: System sizing, year-1 energy balance, bill comparison
B22: Battery SOH | C22: State of health replayed from the solved dispatch; drives the battery derate
B23: Dispatch Profile | C23: 8760-h dispatch incl. original PV generation; chart shows the peak-load week
B24: Load Duration | C24: Load and net-load duration curves
B25: Year 1 BAU vs DPPA | C25: Side-by-side year-1 buyer/seller position
B26: Monthly / Hourly Settlement | C26: ND57 fee chain, VND-native (full configuration on Assumptions)
B28: Prepared for investment and lending review. Figures are model outputs, not offers; REopt sizing is optimizer output and may shift with solver versions.
B29: Regenerate offline anytime: python -m proforma_vietnam.rebuild_report --case-dir <case>.

Sheet Executive Summary
B1: Investment & PPA Negotiation Summary - Factory A Vietnam DPPA Grid CfD E2E
B2: Grid-connected DPPA with CfD (ND57/2025) · prepared 2026-09-12 · REopt dispatch + proforma_vietnam financial model
B4: Project & System
B5: PV Size (kW) | C5: 5996.297
B6: Battery Power (kW) | C6: 2011.12
B7: Battery Energy (kWh) | C7: 12330.71
B8: Total Investment (USD) | C8: 4518797.4
B10: Contract Terms
B11: CfD Strike Price (VND/kWh) | C11: 2000
B12: CfD Strike Escalation (per year) | C12: 0.04
B13: Annual Contract Volume (kWh) | C13: 7664883.2
B14: Transmission Loss Factor k | C14: 1.026
B15: Distribution Loss Factor K_pp | C15: 1.027263
B16: DPPA Service Fee (VND/kWh) | C16: 360
B17: Settlement Adder C_CL (VND/kWh) | C17: 163.3
B18: Analysis Period (Years) | C18: 20
B20: Developer (Seller) Returns
B21: Equity IRR | C21: 0.15063243
B22: Project IRR | C22: 0.12242528
B23: NPV (USD) | C23: 986352.68 | D23: At owner discount rate
B24: Minimum DSCR (debt years) | C24: 1.0664623 | D24: Lender covenant view
B25: Average DSCR | C25: 1.2417576
B26: Simple Payback (Years) | C26: 10.458617
B27: Equity Investment (USD) | C27: 1355639.2
B28: Debt Principal (USD) | C28: 3163158.2
B30: Buyer (Offtaker) Outcome
B31: Year 1 BAU Cost (USD) | C31: 731030.93
B32: Year 1 Cost With Project (USD) | C32: 796739.54
B33: Year 1 Buyer Savings (USD) | C33: -65708.612
B34: Year 1 Savings (% of BAU) | C34: -0.089884859
B35: First 10 Years Buyer Savings (USD) | C35: -812136.26 | D35: Cumulative, years 1-10
B36: First 10 Years Savings (% of BAU) | C36: -0.092531784
B37: Lifetime Buyer Savings (USD) | C37: -2078855.7 | D37: Sum over analysis period
B38: Lifetime Savings (% of BAU) | C38: -0.09549748
B40: Model Basis & Conventions
B41: • Buyer settlement quantity Q_Khc = min(hourly load, loss-adjusted generation Q_adj); excess generation is sold by the generator at FMP and never billed to the buyer.
B42: • PV degradation, O&M escalation and battery replacement (REopt schedule) are applied across the analysis period.
B43: • PV straight-line depreciation over 20 years (Circular 45/2013/TT-BTC permits 7-20 years for generating equipment).
B44: • Vietnam CIT: 4-year exemption + 9-year 50% reduction from first profitable year; 5-year tax-loss carryforward.
B45: • All USD figures at the fixed contract exchange rate (see Assumptions); FX drift between VND revenue and USD reporting is quantified on the FX Sensitivity sheet.

Sheet Assumptions
B1: Assumptions & Model Inputs
B2: Shaded cells are hardcoded inputs (case file or engine output); named cells drive every formula on the Pro Forma (Audit) sheet.
B4: Project & Run
B5: Case name | C5: Factory A Vietnam DPPA Grid CfD E2E | E5: case.json
B6: Financing structure | C6: Grid DPPA with CfD (ND57/2025) | E6: proforma_vietnam.structures
B7: REopt run UUID | C7: 3c7f58d2-b360-4045-9af4-bd57507e9fb3 | E7: REopt API
B8: Report prepared | C8: 2026-09-12
B9: Analysis period | C9: 20 | D9: years | E9: proforma_vietnam.defaults replacement policy (PROJECT_YEARS) unless case.json financial.analysis_years overrides
B10: Tariff year | C10: 2025 | E10: case.json tariff.year
B11: Voltage level | C11: 22-110kV | E11: case.json tariff.voltage_level
B12: TOU schedule | C12: decision_963 | E12: case.json tariff.tou_schedule
B13: Site & Load Profile (case.json)
B14: Latitude | C14: 10.8231 | D14: deg | E14: case.json site.latitude
B15: Longitude | C15: 106.6297 | D15: deg | E15: case.json site.longitude
B16: Load profile file | C16: Sample Load Profile/Emivest_clean.csv | E16: case.json load_profile.path (8760 hourly kW)
B17: Load year | C17: 2025 | E17: case.json load_profile.year
B18: PV Technology (case.json)
B19: PV minimum size | C19: 0 | D19: kW | E19: case.json technologies.pv.min_kw
B20: PV maximum size | C20: 10000 | D20: kW | E20: case.json technologies.pv.max_kw
B21: PV installed cost | C21: 480 | D21: USD/kW | E21: case.json technologies.pv.installed_cost_per_kw
B22: PV O&M cost | C22: 6 | D22: USD/kW/yr | E22: case.json technologies.pv.om_cost_per_kw
B23: PV degradation (case input) | C23: 0.005 | D23: per year | E23: case.json technologies.pv.degradation_fraction
B24: PVWatts tilt | C24: 10 | E24: case.json technologies.pv.pvwatts (production factor inputs)
B25: PVWatts azimuth | C25: 180 | E25: case.json technologies.pv.pvwatts (production factor inputs)
B26: PVWatts array_type | C26: 1 | E26: case.json technologies.pv.pvwatts (production factor inputs)
B27: PVWatts module_type | C27: 0 | E27: case.json technologies.pv.pvwatts (production factor inputs)
B28: PVWatts losses | C28: 14 | E28: case.json technologies.pv.pvwatts (production factor inputs)
B29: PVWatts dc_ac_ratio | C29: 1.2 | E29: case.json technologies.pv.pvwatts (production factor inputs)
B30: Storage Technology (case.json)
B31: Storage minimum power | C31: 0 | D31: kW | E31: case.json technologies.storage.min_kw
B32: Storage maximum power | C32: 5000 | D32: kW | E32: case.json technologies.storage.max_kw
B33: Storage minimum energy | C33: 0 | D33: kWh | E33: case.json technologies.storage.min_kwh
B34: Storage maximum energy | C34: 20000 | D34: kWh | E34: case.json technologies.storage.max_kwh
B35: Storage cost per kW | C35: 80 | D35: USD/kW | E35: case.json technologies.storage.installed_cost_per_kw
B36: Storage cost per kWh | C36: 120 | D36: USD/kWh | E36: case.json technologies.storage.installed_cost_per_kwh
B37: Storage fixed cost | C37: 0 | D37: USD | E37: case.json technologies.storage.installed_cost_constant
B38: O&M (fraction of installed cost) | C38: 0.01 | D38: per year | E38: case.json technologies.storage.om_cost_fraction_of_installed_cost
B39: Currency & FX
B40: Model currency | C40: USD | E40: EVN tariff converted VND→USD before REopt; see Model Basis
B41: Contract exchange rate | C41: 26300 | D41: VND per USD | E41: case.json tariff.exchange_rate_vnd_per_usd
B42: FX treatment | C42: Held flat over the analysis period | E42: Simplification - see FX Sensitivity sheet
B43: Capital Costs
B44: PV capex | C44: 2878222.6 | D44: USD | E44: REopt PV size_kw × installed_cost_per_kw
B45: BESS capex | C45: 1640574.8 | D45: USD | E45: REopt ElectricStorage initial_capital_cost
B46: Other capex | C46: 0 | D46: USD | E46: case.json (developer overrides)
B47: Total investment | C47: =PV_CAPEX+BESS_CAPEX+OTHER_CAPEX | D47: USD | E47: Formula: PV + BESS + Other
B48: Operating Costs
B49: Year-1 O&M | C49: 52383.521 | D49: USD/yr | E49: REopt Financial.year_one_om_costs_before_tax
B50: O&M escalation | C50: 0.03 | D50: per year | E50: vietnam_defaults.json / case.json financial.om_escalation_rate
B51: Replacement Policy
B52: Battery replacement | C52: Not scheduled inside the 20 year horizon | E52: Client direction 2026-09-12: capacity fade is carried on the Battery SOH sheet and derates the battery's savings; REopt sent replace_cost 0. Opt in per case with technologies.storage.replacement
B53: Battery cycle life (EFC to 80 percent) | C53: 8000 | D53: cycles | E53: proforma_vietnam.defaults BESS_CYCLE_LIFE_EFC unless case.json technologies.storage.cycle_life_efc overrides (sets the SOH cycle fade: (1 - 0.80) / cycle life per kWh discharged)
B54: PV inverter replacement year | C54: 11 | D54: year | E54: proforma_vietnam.defaults replacement policy
B55: PV inverter replacement fraction of PV capex | C55: 0.1 | D55: fraction | E55: proforma_vietnam.defaults replacement policy
B56: PV inverter replacement cost | C56: 287822.26 | D56: USD | E56: Engine: fraction x solved PV capex (none booked when the run has no PV)
B57: Tariff & Escalation
B58: EVN energy escalation | C58: 0.04 | D58: per year | E58: case.json tariff.evn_energy_escalation_rate
B59: EVN capacity (demand) escalation | C59: 0.04 | D59: per year | E59: case.json tariff.evn_capacity_escalation_rate
B60: PV degradation | C60: 0.005 | D60: per year | E60: REopt PV.degradation_fraction
B61: Tariff currency fed to REopt | C61: USD | E61: case.json tariff.currency
B62: Two-component tariff pilot | C62: FALSE | D62: yes/no | E62: case.json tariff.two_component_pilot_enabled
B63: Contract Terms
B64: ESCO energy price (fraction of EVN tariff) | C64: 0.9 | D64: fraction | E64: case.json esco_contract.esco_energy_discount_fraction
B65: Demand savings share to ESCO | C65: 0.8 | D65: fraction | E65: case.json esco_contract.demand_savings_esco_share
B66: Grid charging enabled | C66: FALSE | D66: yes/no | E66: case.json esco_contract.grid_charging_enabled
B67: CfD strike price | C67: 2000 | D67: VND/kWh | E67: case.json dppa.cfd_strike_per_kwh_vnd
B68: CfD strike escalation | C68: 0.04 | D68: per year | E68: case.json dppa.cfd_strike_escalation_rate
B69: DPPA fee / FMP escalation | C69: 0.04 | D69: per year | E69: case.json dppa.fee_escalation_rate
B70: Annual CfD contract volume | C70: 7664883.2 | D70: kWh/yr | E70: case.json dppa.cfd_contract_volume_kwh_per_hour
B71: Transmission loss factor k (price-only) | C71: 1.026 | D71: ratio | E71: ND57; CFMP = FMP × k
B72: Distribution loss factor K_pp | C72: 1.027263 | D72: ratio | E72: ND57 by voltage; Q_adj = Q_meter / K_pp
B73: DPPA system service fee | C73: 360 | D73: VND/kWh | E73: 2025 EVN published fee
B74: Settlement adder C_CL | C74: 163.3 | D74: VND/kWh | E74: 2025 EVN published adder
B75: Allocation fraction δ | C75: 1 | D75: fraction | E75: case.json dppa.allocation_fraction_delta
B76: FMP / CFMP price series | C76: DPPA DOC/fmp_cfmp_vn.json | E76: case.json dppa.fmp_series_path (8760-hour VND/kWh)
B77: Financing
B78: Debt fraction | C78: 0.7 | D78: of total capex | E78: vietnam_defaults.json / case.json financial.debt_fraction
B79: Debt interest rate | C79: 0.085 | D79: per year | E79: vietnam_defaults.json / case.json financial.debt_interest_rate_fraction
B80: Debt term | C80: 10 | D80: years | E80: vietnam_defaults.json / case.json financial.debt_term_years
B81: Debt principal | C81: =TOTAL_CAPEX*DEBT_FRACTION | D81: USD | E81: Formula: total investment × debt fraction
B82: Equity investment | C82: =TOTAL_CAPEX-DEBT_PRINCIPAL | D82: USD | E82: Formula: total investment − debt
B83: Annual debt payment (level) | C83: =IF(OR(DEBT_PRINCIPAL<=0,DEBT_TERM_YEARS<=0),0,IF(DEBT_RATE=0,DEBT_PRINCIPAL/DEBT_TERM_YEARS,DEBT_PRINCIPAL*(DEBT_RATE*(1+DEBT_RATE)^DEBT_TERM_YEARS)/((1+DEBT_RATE)^DEBT_TERM_YEARS-1))) | D83: USD/yr | E83: Standard annuity over the debt term
B84: Owner discount rate | C84: 0.1 | D84: per year | E84: case.json financial.owner_discount_rate_fraction
B85: Tax & Depreciation (Vietnam)
B86: CIT regime | C86: RE producer - Law 67/2025 preferential (10% / 15y) | E86: proforma_vietnam.cash_flow (structure-dependent; explicit override wins)
B87: CIT standard rate | C87: 0.2 | D87: of taxable income | E87: Law 67/2025/QH15; vietnam_defaults.json
B88: CIT preferential rate (RE producer) | C88: 0.1 | D88: of taxable income | E88: Law 67/2025/QH15 + Decree 320/2025/NĐ-CP (first-15-year window)
B89: CIT preferential-rate period | C89: 15 | D89: years (from year 1) | E89: Law 67/2025/QH15
B90: CIT holiday | C90: 4 | D90: years | E90: Law 67/2025 (from first profitable year); Circular 78/2014 Art. 18 shape
B91: CIT reduced-rate period | C91: 9 | D91: years | E91: Law 67/2025; Circular 78/2014 Art. 18 shape
B92: CIT reduction during period | C92: 0.5 | D92: of applicable base rate | E92: Law 67/2025 (50% of base rate)
B93: Tax-loss carryforward limit | C93: 5 | D93: years | E93: Law 67/2025; Circular 78/2014 Art. 9 shape
B94: Incentive clock cap | C94: 4 | D94: year (latest start) | E94: Law 67/2025; Circular 78/2014 Art. 18 shape
B95: PV depreciation (straight-line) | C95: 20 | D95: years | E95: Circular 45/2013/TT-BTC (7–20 yr band)
B96: BESS depreciation (straight-line) | C96: 8 | D96: years | E96: Circular 45/2013/TT-BTC
B97: Year-1 Engine Outputs (hardcoded - dispatch × tariff, not derivable in-sheet)
B98: Year-1 BAU EVN bill | C98: 731030.93 | D98: USD | E98: REopt ElectricTariff.year_one_bill_before_tax_bau
B99: Year-1 optimized EVN bill | C99: 148205.46 | D99: USD | E99: REopt ElectricTariff.year_one_bill_before_tax
B100: Year-1 BAU demand charge | C100: 0 | D100: USD | E100: REopt year_one_demand_cost_before_tax_bau
B101: Year-1 optimized demand charge | C101: 0 | D101: USD | E101: REopt year_one_demand_cost_before_tax
...

Sheet Model Basis
B1: Model Basis, Conventions & Simplifications
B3: 1. Model architecture
B4: • REopt (NLR optimization engine) selects PV/BESS sizing and hourly dispatch against the EVN time-of-use tariff over an 8760-hour year.
B5: • proforma_vietnam post-processes the REopt run: an hourly ND57/2025 DPPA settlement layer (when applicable) and a 20-year developer cash flow with Vietnam tax and debt.
B6: • This workbook is generated from that engine. The Pro Forma (Audit) sheet re-derives the full cash flow with live Excel formulas from the named inputs on the Assumptions sheet; the Checks block ties every metric back to the engine (PASS/REVIEW).
B8: 2. Currency & FX
B9: • All money flows are computed in USD at the fixed contract rate (26,300 VND/USD).
B10: • Underlying revenue is VND-denominated (EVN tariff, FMP market, DPPA fees). Holding FX flat for the analysis period is a simplification: the FX Sensitivity sheet quantifies USD-reported returns under 0-3%/yr VND depreciation.
B11: • Sheets that show VND amounts (Hourly/Monthly Settlement, DPPA fee inputs) are VND-native regulatory quantities, not conversions.
B12: • Debt is assumed VND-denominated (local bank), so DSCR is FX-neutral.
B14: 3. Settlement math - ND57/2025 grid DPPA with CfD
B15: • Q_adj[h] = Q_re_meter[h] / K_pp × delta - quantity conversion generator→customer uses K_pp only (CD7 Ví dụ 1); k is price-only.
... B51: • EVN retail tariff (current & QĐ963 TOU structures) as configured in the case file.

Sheet Pro Forma (Audit)
A1: Pro Forma (Audit) - every white cell is a live Excel formula
A2: Shaded cells are hardcoded engine outputs (REopt dispatch / 8760-h settlement / tie-out reference). All other cells derive from the named cells on the Assumptions sheet. Currency: USD at the fixed contract FX rate.
A4: TIMELINE & INDEXATION
A5: Year | B5: index | C5: 0 | D5: 1 | E5: 2 | F5: 3 | G5: 4 | H5: 5 | I5: 6 | J5: 7 | K5: 8 | L5: 9 | M5: 10 | N5: 11 | O5: 12 | P5: 13 | Q5: 14 | R5: 15 | S5: 16 | T5: 17 | U5: 18 | V5: 19 | W5: 20
A6: EVN energy escalation factor | B6: index | D6: =(1+ESC_ENERGY)^(D$5-1) | E6: =(1+ESC_ENERGY)^(E$5-1) | F6: =(1+ESC_ENERGY)^(F$5-1) | G6: =(1+ESC_ENERGY)^(G$5-1) | H6: =(1+ESC_ENERGY)^(H$5-1) | I6: =(1+ESC_ENERGY)^(I$5-1) | J6: =(1+ESC_ENERGY)^(J$5-1) | K6: =(1+ESC_ENERGY)^(K$5-1) | ... W6: =(1+ESC_ENERGY)^(W$5-1)
A7: EVN capacity escalation factor | B7: index | D7: =(1+ESC_CAPACITY)^(D$5-1) | E7: =(1+ESC_CAPACITY)^(E$5-1) | F7: =(1+ESC_CAPACITY)^(F$5-1) | G7: =(1+ESC_CAPACITY)^(G$5-1) | H7: =(1+ESC_CAPACITY)^(H$5-1) | I7: =(1+ESC_CAPACITY)^(I$5-1) | J7: =(1+ESC_CAPACITY)^(J$5-1) | K7: =(1+ESC_CAPACITY)^(K$5-1) | ... W7: =(1+ESC_CAPACITY)^(W$5-1)
A8: O&M escalation factor | B8: index | D8: =(1+ESC_OM)^(D$5-1) | E8: =(1+ESC_OM)^(E$5-1) | F8: =(1+ESC_OM)^(F$5-1) | G8: =(1+ESC_OM)^(G$5-1) | H8: =(1+ESC_OM)^(H$5-1) | I8: =(1+ESC_OM)^(I$5-1) | J8: =(1+ESC_OM)^(J$5-1) | K8: =(1+ESC_OM)^(K$5-1) | ... W8: =(1+ESC_OM)^(W$5-1)
A9: PV degradation factor | B9: index | D9: =(1-PV_DEGRADATION)^(D$5-1) | E9: =(1-PV_DEGRADATION)^(E$5-1) | F9: =(1-PV_DEGRADATION)^(F$5-1) | G9: =(1-PV_DEGRADATION)^(G$5-1) | H9: =(1-PV_DEGRADATION)^(H$5-1) | I9: =(1-PV_DEGRADATION)^(I$5-1) | J9: =(1-PV_DEGRADATION)^(J$5-1) | K9: =(1-PV_DEGRADATION)^(K$5-1) | ... W9: =(1-PV_DEGRADATION)^(W$5-1)
A10: Battery SOH factor (year average) | B10: index | C10: 1 | D10: 0.99162852 | E10: 0.98171758 | F10: 0.97352153 | G10: 0.96590164 | H10: 0.95860584 | I10: 0.95152458 | J10: 0.94459849 | K10: 0.93779116 | L10: 0.93107839 | M10: 0.92444313 | N10: 0.91787287 | O10: 0.91135808 | P10: 0.90489134 | Q10: 0.89846673 | R10: 0.89207942 | S10: 0.88572545 | T10: 0.87940148 | U10: 0.8731047 | V10: 0.8668327 | W10: 0.86058341
A11: Generation factor (PV degradation, battery SOH) | B11: index | D11: =(1-BESS_MATCHED_SHARE)*D9+BESS_MATCHED_SHARE*D10 | E11: =(1-BESS_MATCHED_SHARE)*E9+BESS_MATCHED_SHARE*E10 | F11: =(1-BESS_MATCHED_SHARE)*F9+BESS_MATCHED_SHARE*F10 | G11: =(1-BESS_MATCHED_SHARE)*G9+BESS_MATCHED_SHARE*G10 | H11: =(1-BESS_MATCHED_SHARE)*H9+BESS_MATCHED_SHARE*H10 | I11: =(1-BESS_MATCHED_SHARE)*I9+BESS_MATCHED_SHARE*I10 | J11: =(1-BESS_MATCHED_SHARE)*J9+BESS_MATCHED_SHARE*J10 | K11: =(1-BESS_MATCHED_SHARE)*K9+BESS_MATCHED_SHARE*K10 | ... W11: =(1-BESS_MATCHED_SHARE)*W9+BESS_MATCHED_SHARE*W10
A12: DPPA fee / FMP escalation factor | B12: index | D12: =(1+ESC_FEE)^(D$5-1) | E12: =(1+ESC_FEE)^(E$5-1) | F12: =(1+ESC_FEE)^(F$5-1) | G12: =(1+ESC_FEE)^(G$5-1) | H12: =(1+ESC_FEE)^(H$5-1) | I12: =(1+ESC_FEE)^(I$5-1) | J12: =(1+ESC_FEE)^(J$5-1) | K12: =(1+ESC_FEE)^(K$5-1) | ... W12: =(1+ESC_FEE)^(W$5-1)
A13: CfD strike escalation factor | B13: index | D13: =(1+ESC_STRIKE)^(D$5-1) | E13: =(1+ESC_STRIKE)^(E$5-1) | F13: =(1+ESC_STRIKE)^(F$5-1) | G13: =(1+ESC_STRIKE)^(G$5-1) | H13: =(1+ESC_STRIKE)^(H$5-1) | I13: =(1+ESC_STRIKE)^(I$5-1) | J13: =(1+ESC_STRIKE)^(J$5-1) | K13: =(1+ESC_STRIKE)^(K$5-1) | ... W13: =(1+ESC_STRIKE)^(W$5-1)
A15: REVENUE (USD)
A16: Generator FMP market revenue | B16: USD | D16: =DPPA_FMP_REV_Y1*D12*D11 | E16: =DPPA_FMP_REV_Y1*E12*E11 | F16: =DPPA_FMP_REV_Y1*F12*F11 | G16: =DPPA_FMP_REV_Y1*G12*G11 | H16: =DPPA_FMP_REV_Y1*H12*H11 | I16: =DPPA_FMP_REV_Y1*I12*I11 | J16: =DPPA_FMP_REV_Y1*J12*J11 | K16: =DPPA_FMP_REV_Y1*K12*K11 | ... W16: =DPPA_FMP_REV_Y1*W12*W11
A17: CfD strike leg (P_c × Q_cfd) | B17: USD | D17: =DPPA_CFD_STRIKE_Y1*D13 | E17: =DPPA_CFD_STRIKE_Y1*E13 | F17: =DPPA_CFD_STRIKE_Y1*F13 | G17: =DPPA_CFD_STRIKE_Y1*G13 | H17: =DPPA_CFD_STRIKE_Y1*H13 | I17: =DPPA_CFD_STRIKE_Y1*I13 | J17: =DPPA_CFD_STRIKE_Y1*J13 | K17: =DPPA_CFD_STRIKE_Y1*K13 | ... W17: =DPPA_CFD_STRIKE_Y1*W13
A18: CfD market offset (FMP × Q_cfd) | B18: USD | D18: =DPPA_CFD_OFFSET_Y1*D12 | E18: =DPPA_CFD_OFFSET_Y1*E12 | F18: =DPPA_CFD_OFFSET_Y1*F12 | G18: =DPPA_CFD_OFFSET_Y1*G12 | H18: =DPPA_CFD_OFFSET_Y1*H12 | I18: =DPPA_CFD_OFFSET_Y1*I12 | J18: =DPPA_CFD_OFFSET_Y1*J12 | K18: =DPPA_CFD_OFFSET_Y1*K12 | ... W18: =DPPA_CFD_OFFSET_Y1*W12
A19: CfD net settlement (to generator) | B19: USD | D19: =D17-D18 | E19: =E17-E18 | F19: =F17-F18 | G19: =G17-G18 | H19: =H17-H18 | I19: =I17-I18 | J19: =J17-J18 | K19: =K17-K18 | ... W19: =W17-W18
A20: Generator revenue (FMP + CfD net) | B20: USD | D20: =D16+D19 | E20: =E16+E19 | F20: =F16+F19 | G20: =G16+G19 | H20: =H16+H19 | I20: =I16+I19 | J20: =J16+J19 | K20: =K16+K19 | ... W20: =W16+W19
A21: Demand charge savings (total) | B21: USD | D21: =((BASE_DEMAND_SAVINGS-BESS_DEMAND_SAVINGS)+BESS_DEMAND_SAVINGS*D10)*D7 | E21: =((BASE_DEMAND_SAVINGS-BESS_DEMAND_SAVINGS)+BESS_DEMAND_SAVINGS*E10)*E7 | F21: =((BASE_DEMAND_SAVINGS-BESS_DEMAND_SAVINGS)+BESS_DEMAND_SAVINGS*F10)*F7 | G21: =((BASE_DEMAND_SAVINGS-BESS_DEMAND_SAVINGS)+BESS_DEMAND_SAVINGS*G10)*G7 | H21: =((BASE_DEMAND_SAVINGS-BESS_DEMAND_SAVINGS)+BESS_DEMAND_SAVINGS*H10)*H7 | I21: =((BASE_DEMAND_SAVINGS-BESS_DEMAND_SAVINGS)+BESS_DEMAND_SAVINGS*I10)*I7 | J21: =((BASE_DEMAND_SAVINGS-BESS_DEMAND_SAVINGS)+BESS_DEMAND_SAVINGS*J10)*J7 | K21: =((BASE_DEMAND_SAVINGS-BESS_DEMAND_SAVINGS)+BESS_DEMAND_SAVINGS*K10)*K7 | ... W21: =((BASE_DEMAND_SAVINGS-BESS_DEMAND_SAVINGS)+BESS_DEMAND_SAVINGS*W10)*W7
A22: ESCO share of demand savings | B22: USD | D22: =D21*DEMAND_SHARE | E22: =E21*DEMAND_SHARE | F22: =F21*DEMAND_SHARE | G22: =G21*DEMAND_SHARE | H22: =H21*DEMAND_SHARE | I22: =I21*DEMAND_SHARE | J22: =J21*DEMAND_SHARE | K22: =K21*DEMAND_SHARE | ... W22: =W21*DEMAND_SHARE
A23: Total developer revenue | B23: USD | D23: =D20+D22 | E23: =E20+E22 | F23: =F20+F22 | G23: =G20+G22 | H23: =H20+H22 | I23: =I20+I22 | J23: =J20+J22 | K23: =K20+K22 | ... W23: =W20+W22
A25: OPERATING COSTS (USD)
A26: O&M | B26: USD | D26: =OM_YEAR1*D8 | E26: =OM_YEAR1*E8 | F26: =OM_YEAR1*F8 | G26: =OM_YEAR1*G8 | H26: =OM_YEAR1*H8 | I26: =OM_YEAR1*I8 | J26: =OM_YEAR1*J8 | K26: =OM_YEAR1*K8 | ... W26: =OM_YEAR1*W8
A27: Equipment replacement (engine schedule) | B27: USD | D27: 0 | E27: 0 | F27: 0 | G27: 0 | H27: 0 | I27: 0 | J27: 0 | K27: 0 | L27: 0 | M27: 0 | N27: 287822.26 | O27: 0 | P27: 0 | Q27: 0 | R27: 0 | S27: 0 | T27: 0 | U27: 0 | V27: 0 | W27: 0
A28: EBITDA | B28: USD | D28: =D23-D26-D27 | E28: =E23-E26-E27 | F28: =F23-F26-F27 | G28: =G23-G26-G27 | H28: =H23-H26-H27 | I28: =I23-I26-I27 | J28: =J23-J26-J27 | K28: =K23-K26-K27 | ... W28: =W23-W26-W27
A30: DEBT SCHEDULE (USD)
A31: Opening debt balance | B31: USD | D31: =DEBT_PRINCIPAL | E31: =D35 | F31: =E35 | G31: =F35 | H31: =G35 | I31: =H35 | J31: =I35 | K31: =J35 | L31: =K35 | ... W31: =V35
A32: Interest | B32: USD | D32: =IF(D$5<=DEBT_TERM_YEARS,D31*DEBT_RATE,0) | E32: =IF(E$5<=DEBT_TERM_YEARS,E31*DEBT_RATE,0) | F32: =IF(F$5<=DEBT_TERM_YEARS,F31*DEBT_RATE,0) | G32: =IF(G$5<=DEBT_TERM_YEARS,G31*DEBT_RATE,0) | H32: =IF(H$5<=DEBT_TERM_YEARS,H31*DEBT_RATE,0) | I32: =IF(I$5<=DEBT_TERM_YEARS,I31*DEBT_RATE,0) | J32: =IF(J$5<=DEBT_TERM_YEARS,J31*DEBT_RATE,0) | K32: =IF(K$5<=DEBT_TERM_YEARS,K31*DEBT_RATE,0) | ... W32: =IF(W$5<=DEBT_TERM_YEARS,W31*DEBT_RATE,0)
A33: Principal repayment | B33: USD | D33: =IF(D$5<=DEBT_TERM_YEARS,MIN(MAX(DEBT_PAYMENT-D32,0),D31),0) | E33: =IF(E$5<=DEBT_TERM_YEARS,MIN(MAX(DEBT_PAYMENT-E32,0),E31),0) | F33: =IF(F$5<=DEBT_TERM_YEARS,MIN(MAX(DEBT_PAYMENT-F32,0),F31),0) | G33: =IF(G$5<=DEBT_TERM_YEARS,MIN(MAX(DEBT_PAYMENT-G32,0),G31),0) | H33: =IF(H$5<=DEBT_TERM_YEARS,MIN(MAX(DEBT_PAYMENT-H32,0),H31),0) | I33: =IF(I$5<=DEBT_TERM_YEARS,MIN(MAX(DEBT_PAYMENT-I32,0),I31),0) | J33: =IF(J$5<=DEBT_TERM_YEARS,MIN(MAX(DEBT_PAYMENT-J32,0),J31),0) | K33: =IF(K$5<=DEBT_TERM_YEARS,MIN(MAX(DEBT_PAYMENT-K32,0),K31),0) | ... W33: =IF(W$5<=DEBT_TERM_YEARS,MIN(MAX(DEBT_PAYMENT-W32,0),W31),0)
A34: Debt service | B34: USD | D34: =D32+D33 | E34: =E32+E33 | F34: =F32+F33 | G34: =G32+G33 | H34: =H32+H33 | I34: =I32+I33 | J34: =J32+J33 | K34: =K32+K33 | ... W34: =W32+W33
A35: Closing debt balance | B35: USD | D35: =D31-D33 | E35: =E31-E33 | F35: =F31-F33 | G35: =G31-G33 | H35: =H31-H33 | I35: =I31-I33 | J35: =J31-J33 | K35: =K31-K33 | ... W35: =W31-W33
A37: DEPRECIATION & VIETNAM CIT (USD)
A38: PV depreciation (straight-line) | B38: USD | D38: =IF(D$5<=PV_DEP_YEARS,PV_CAPEX/PV_DEP_YEARS,0) | E38: =IF(E$5<=PV_DEP_YEARS,PV_CAPEX/PV_DEP_YEARS,0) | F38: =IF(F$5<=PV_DEP_YEARS,PV_CAPEX/PV_DEP_YEARS,0) | G38: =IF(G$5<=PV_DEP_YEARS,PV_CAPEX/PV_DEP_YEARS,0) | H38: =IF(H$5<=PV_DEP_YEARS,PV_CAPEX/PV_DEP_YEARS,0) | I38: =IF(I$5<=PV_DEP_YEARS,PV_CAPEX/PV_DEP_YEARS,0) | J38: =IF(J$5<=PV_DEP_YEARS,PV_CAPEX/PV_DEP_YEARS,0) | K38: =IF(K$5<=PV_DEP_YEARS,PV_CAPEX/PV_DEP_YEARS,0) | ... W38: =IF(W$5<=PV_DEP_YEARS,PV_CAPEX/PV_DEP_YEARS,0)
A39: BESS depreciation (straight-line) | B39: USD | D39: =IF(D$5<=BESS_DEP_YEARS,BESS_CAPEX/BESS_DEP_YEARS,0) | E39: =IF(E$5<=BESS_DEP_YEARS,BESS_CAPEX/BESS_DEP_YEARS,0) | F39: =IF(F$5<=BESS_DEP_YEARS,BESS_CAPEX/BESS_DEP_YEARS,0) | G39: =IF(G$5<=BESS_DEP_YEARS,BESS_CAPEX/BESS_DEP_YEARS,0) | H39: =IF(H$5<=BESS_DEP_YEARS,BESS_CAPEX/BESS_DEP_YEARS,0) | I39: =IF(I$5<=BESS_DEP_YEARS,BESS_CAPEX/BESS_DEP_YEARS,0) | J39: =IF(J$5<=BESS_DEP_YEARS,BESS_CAPEX/BESS_DEP_YEARS,0) | K39: =IF(K$5<=BESS_DEP_YEARS,BESS_CAPEX/BESS_DEP_YEARS,0) | ... W39: =IF(W$5<=BESS_DEP_YEARS,BESS_CAPEX/BESS_DEP_YEARS,0)
A40: Replacement depreciation (in-service yr 11) | B40: USD | D40: =IF(AND(D$5>=11,D$5<=11+BESS_DEP_YEARS-1),$N$27/BESS_DEP_YEARS,0) | E40: =IF(AND(E$5>=11,E$5<=11+BESS_DEP_YEARS-1),$N$27/BESS_DEP_YEARS,0) | F40: =IF(AND(F$5>=11,F$5<=11+BESS_DEP_YEARS-1),$N$27/BESS_DEP_YEARS,0) | G40: =IF(AND(G$5>=11,G$5<=11+BESS_DEP_YEARS-1),$N$27/BESS_DEP_YEARS,0) | H40: =IF(AND(H$5>=11,H$5<=11+BESS_DEP_YEARS-1),$N$27/BESS_DEP_YEARS,0) | I40: =IF(AND(I$5>=11,I$5<=11+BESS_DEP_YEARS-1),$N$27/BESS_DEP_YEARS,0) | J40: =IF(AND(J$5>=11,J$5<=11+BESS_DEP_YEARS-1),$N$27/BESS_DEP_YEARS,0) | K40: =IF(AND(K$5>=11,K$5<=11+BESS_DEP_YEARS-1),$N$27/BESS_DEP_YEARS,0) | ... W40: =IF(AND(W$5>=11,W$5<=11+BESS_DEP_YEARS-1),$N$27/BESS_DEP_YEARS,0)
A41: Total depreciation | B41: USD | D41: =D38+D39+D40 | E41: =E38+E39+E40 | F41: =F38+F39+F40 | G41: =G38+G39+G40 | H41: =H38+H39+H40 | I41: =I38+I39+I40 | J41: =J38+J39+J40 | K41: =K38+K39+K40 | ... W41: =W38+W39+W40
A42: Taxable income before loss relief (EBT) | B42: USD | D42: =D28+D27-D41-D32 | E42: =E28+E27-E41-E32 | F42: =F28+F27-F41-F32 | G42: =G28+G27-G41-G32 | H42: =H28+H27-H41-H32 | I42: =I28+I27-I41-I32 | J42: =J28+J27-J41-J32 | K42: =K28+K27-K41-K32 | ... W42: =W28+W27-W41-W32
A43: New tax loss arising | B43: USD | D43: =MAX(-D42,0) | E43: =MAX(-E42,0) | F43: =MAX(-F42,0) | G43: =MAX(-G42,0) | H43: =MAX(-H42,0) | I43: =MAX(-I42,0) | J43: =MAX(-J42,0) | K43: =MAX(-K42,0) | ... W43: =MAX(-W42,0)
A44: Assessable income (pre-relief) | B44: USD | D44: =MAX(D42,0) | E44: =MAX(E42,0) | F44: =MAX(F42,0) | G44: =MAX(G42,0) | H44: =MAX(H42,0) | I44: =MAX(I42,0) | J44: =MAX(J42,0) | K44: =MAX(K42,0) | ... W44: =MAX(W42,0)
A45: Loss vintage aged 1y - available | B45: USD | D45: 0 | E45: =D43 | F45: =E43 | G45: =F43 | H45: =G43 | I45: =H43 | J45: =I43 | K45: =J43 | L45: =K43 | ... W45: =V43
A46: Loss vintage aged 2y - available | B46: USD | D46: 0 | E46: =MAX(D45-D54,0) | F46: =MAX(E45-E54,0) | G46: =MAX(F45-F54,0) | H46: =MAX(G45-G54,0) | I46: =MAX(H45-H54,0) | J46: =MAX(I45-I54,0) | K46: =MAX(J45-J54,0) | L46: =MAX(K45-K54,0) | ... W46: =MAX(V45-V54,0)
A47: Loss vintage aged 3y - available | B47: USD | D47: 0 | E47: =MAX(D46-D53,0) | F47: =MAX(E46-E53,0) | G47: =MAX(F46-F53,0) | H47: =MAX(G46-G53,0) | I47: =MAX(H46-H53,0) | J47: =MAX(I46-I53,0) | K47: =MAX(J46-J53,0) | L47: =MAX(K46-K53,0) | ... W47: =MAX(V46-V53,0)
A48: Loss vintage aged 4y - available | B48: USD | D48: 0 | E48: =MAX(D47-D52,0) | F48: =MAX(E47-E52,0) | G48: =MAX(F47-F52,0) | H48: =MAX(G47-G52,0) | I48: =MAX(H47-H52,0) | J48: =MAX(I47-I52,0) | K48: =MAX(J47-J52,0) | L48: =MAX(K47-K52,0) | ... W48: =MAX(V47-V52,0)
A49: Loss vintage aged 5y - available | B49: USD | D49: 0 | E49: =MAX(D48-D51,0) | F49: =MAX(E48-E51,0) | G49: =MAX(F48-F51,0) | H49: =MAX(G48-G51,0) | I49: =MAX(H48-H51,0) | J49: =MAX(I48-I51,0) | K49: =MAX(J48-J51,0) | L49: =MAX(K48-K51,0) | ... W49: =MAX(V48-V51,0)
A50: Loss vintage aged 5y - utilised | B50: USD | D50: =MIN(D49,MAX(D44,0)) | E50: =MIN(E49,MAX(E44,0)) | F50: =MIN(F49,MAX(F44,0)) | G50: =MIN(G49,MAX(G44,0)) | H50: =MIN(H49,MAX(H44,0)) | I50: =MIN(I49,MAX(I44,0)) | J50: =MIN(J49,MAX(J44,0)) | K50: =MIN(K49,MAX(K44,0)) | ... W50: =MIN(W49,MAX(W44,0))
A51: Loss vintage aged 4y - utilised | B51: USD | D51: =MIN(D48,MAX(D44-D50,0)) | E51: =MIN(E48,MAX(E44-E50,0)) | F51: =MIN(F48,MAX(F44-F50,0)) | G51: =MIN(G48,MAX(G44-G50,0)) | H51: =MIN(H48,MAX(H44-H50,0)) | I51: =MIN(I48,MAX(I44-I50,0)) | J51: =MIN(J48,MAX(J44-J50,0)) | K51: =MIN(K48,MAX(K44-K50,0)) | ... W51: =MIN(W48,MAX(W44-W50,0))
A52: Loss vintage aged 3y - utilised | B52: USD | D52: =MIN(D47,MAX(D44-D50-D51,0)) | E52: =MIN(E47,MAX(E44-E50-E51,0)) | F52: =MIN(F47,MAX(F44-F50-F51,0)) | G52: =MIN(G47,MAX(G44-G50-G51,0)) | H52: =MIN(H47,MAX(H44-H50-H51,0)) | I52: =MIN(I47,MAX(I44-I50-I51,0)) | J52: =MIN(J47,MAX(J44-J50-J51,0)) | K52: =MIN(K47,MAX(K44-K50-K51,0)) | ... W52: =MIN(W47,MAX(W44-W50-W51,0))
A53: Loss vintage aged 2y - utilised | B53: USD | D53: =MIN(D46,MAX(D44-D50-D51-D52,0)) | E53: =MIN(E46,MAX(E44-E50-E51-E52,0)) | F53: =MIN(F46,MAX(F44-F50-F51-F52,0)) | G53: =MIN(G46,MAX(G44-G50-G51-G52,0)) | H53: =MIN(H46,MAX(H44-H50-H51-H52,0)) | I53: =MIN(I46,MAX(I44-I50-I51-I52,0)) | J53: =MIN(J46,MAX(J44-J50-J51-J52,0)) | K53: =MIN(K46,MAX(K44-K50-K51-K52,0)) | ... W53: =MIN(W46,MAX(W44-W50-W51-W52,0))
A54: Loss vintage aged 1y - utilised | B54: USD | D54: =MIN(D45,MAX(D44-D50-D51-D52-D53,0)) | E54: =MIN(E45,MAX(E44-E50-E51-E52-E53,0)) | F54: =MIN(F45,MAX(F44-F50-F51-F52-F53,0)) | G54: =MIN(G45,MAX(G44-G50-G51-G52-G53,0)) | H54: =MIN(H45,MAX(H44-H50-H51-H52-H53,0)) | I54: =MIN(I45,MAX(I44-I50-I51-I52-I53,0)) | J54: =MIN(J45,MAX(J44-J50-J51-J52-J53,0)) | K54: =MIN(K45,MAX(K44-K50-K51-K52-K53,0)) | ... W54: =MIN(W45,MAX(W44-W50-W51-W52-W53,0))
A55: Loss relief utilised (FIFO, ≤5y old) | B55: USD | D55: =D50+D51+D52+D53+D54 | E55: =E50+E51+E52+E53+E54 | F55: =F50+F51+F52+F53+F54 | G55: =G50+G51+G52+G53+G54 | H55: =H50+H51+H52+H53+H54 | I55: =I50+I51+I52+I53+I54 | J55: =J50+J51+J52+J53+J54 | K55: =K50+K51+K52+K53+K54 | ... W55: =W50+W51+W52+W53+W54
A56: Taxable income after loss relief | B56: USD | D56: =D44-D55 | E56: =E44-E55 | F56: =F44-F55 | G56: =G44-G55 | H56: =H44-H55 | I56: =I44-I55 | J56: =J44-J55 | K56: =K44-K55 | ... W56: =W44-W55
A57: Profitable-to-date flag (starts CIT clock) | B57: 0/1 | D57: =IF(D42>0,1,0) | E57: =IF(OR(D57=1,E42>0),1,0) | F57: =IF(OR(E57=1,F42>0),1,0) | G57: =IF(OR(F57=1,G42>0),1,0) | H57: =IF(OR(G57=1,H42>0),1,0) | I57: =IF(OR(H57=1,I42>0),1,0) | J57: =IF(OR(I57=1,J42>0),1,0) | K57: =IF(OR(J57=1,K42>0),1,0) | L57: =IF(OR(K57=1,L42>0),1,0) | ... W57: =IF(OR(V57=1,W42>0),1,0)
A58: CIT clock start year (first profit, capped) | C58: =MIN(IFERROR(MATCH(1,D57:W57,0),CIT_CLOCK_CAP_YEAR),CIT_CLOCK_CAP_YEAR) | D58: Circular 78/2014 Art. 18
A59: Applicable base CIT rate (preferential window) | B59: % | D59: =IF(D$5<=CIT_PREF_YEARS,CIT_PREF_RATE,CIT_RATE) | E59: =IF(E$5<=CIT_PREF_YEARS,CIT_PREF_RATE,CIT_RATE) | F59: =IF(F$5<=CIT_PREF_YEARS,CIT_PREF_RATE,CIT_RATE) | G59: =IF(G$5<=CIT_PREF_YEARS,CIT_PREF_RATE,CIT_RATE) | H59: =IF(H$5<=CIT_PREF_YEARS,CIT_PREF_RATE,CIT_RATE) | I59: =IF(I$5<=CIT_PREF_YEARS,CIT_PREF_RATE,CIT_RATE) | J59: =IF(J$5<=CIT_PREF_YEARS,CIT_PREF_RATE,CIT_RATE) | K59: =IF(K$5<=CIT_PREF_YEARS,CIT_PREF_RATE,CIT_RATE) | ... W59: =IF(W$5<=CIT_PREF_YEARS,CIT_PREF_RATE,CIT_RATE)
A60: Applicable CIT rate | B60: % | D60: =IF(D$5<$C$58+CIT_HOLIDAY_YEARS,0,IF(D$5<$C$58+CIT_HOLIDAY_YEARS+CIT_REDUCED_YEARS,D59*CIT_REDUCED_FRACTION,D59)) | E60: =IF(E$5<$C$58+CIT_HOLIDAY_YEARS,0,IF(E$5<$C$58+CIT_HOLIDAY_YEARS+CIT_REDUCED_YEARS,E59*CIT_REDUCED_FRACTION,E59)) | F60: =IF(F$5<$C$58+CIT_HOLIDAY_YEARS,0,IF(F$5<$C$58+CIT_HOLIDAY_YEARS+CIT_REDUCED_YEARS,F59*CIT_REDUCED_FRACTION,F59)) | G60: =IF(G$5<$C$58+CIT_HOLIDAY_YEARS,0,IF(G$5<$C$58+CIT_HOLIDAY_YEARS+CIT_REDUCED_YEARS,G59*CIT_REDUCED_FRACTION,G59)) | H60: =IF(H$5<$C$58+CIT_HOLIDAY_YEARS,0,IF(H$5<$C$58+CIT_HOLIDAY_YEARS+CIT_REDUCED_YEARS,H59*CIT_REDUCED_FRACTION,H59)) | I60: =IF(I$5<$C$58+CIT_HOLIDAY_YEARS,0,IF(I$5<$C$58+CIT_HOLIDAY_YEARS+CIT_REDUCED_YEARS,I59*CIT_REDUCED_FRACTION,I59)) | J60: =IF(J$5<$C$58+CIT_HOLIDAY_YEARS,0,IF(J$5<$C$58+CIT_HOLIDAY_YEARS+CIT_REDUCED_YEARS,J59*CIT_REDUCED_FRACTION,J59)) | K60: =IF(K$5<$C$58+CIT_HOLIDAY_YEARS,0,IF(K$5<$C$58+CIT_HOLIDAY_YEARS+CIT_REDUCED_YEARS,K59*CIT_REDUCED_FRACTION,K59)) | ... W60: =IF(W$5<$C$58+CIT_HOLIDAY_YEARS,0,IF(W$5<$C$58+CIT_HOLIDAY_YEARS+CIT_REDUCED_YEARS,W59*CIT_REDUCED_FRACTION,W59))
A61: CIT payable | B61: USD | D61: =D56*D60 | E61: =E56*E60 | F61: =F56*F60 | G61: =G56*G60 | H61: =H56*H60 | I61: =I56*I60 | J61: =J56*J60 | K61: =K56*K60 | ... W61: =W56*W60
A63: CASH FLOW & COVERAGE (USD)
A64: Cash available for debt service (CFADS) | B64: USD | D64: =D28-D61 | E64: =E28-E61 | F64: =F28-F61 | G64: =G28-G61 | H64: =H28-H61 | I64: =I28-I61 | J64: =J28-J61 | K64: =K28-K61 | ... W64: =W28-W61
A65: Project cash flow (unlevered, post-tax) | B65: USD | C65: =-TOTAL_CAPEX | D65: =D64 | E65: =E64 | F65: =F64 | G65: =G64 | H65: =H64 | I65: =I64 | J65: =J64 | K65: =K64 | ... W65: =W64
A66: Equity cash flow | B66: USD | C66: =-EQUITY_INVESTMENT | D66: =D64-D34 | E66: =E64-E34 | F66: =F64-F34 | G66: =G64-G34 | H66: =H64-H34 | I66: =I64-I34 | J66: =J64-J34 | K66: =K64-K34 | ... W66: =W64-W34
A67: Cumulative equity cash flow | B67: USD | C67: =C66 | D67: =C67+D66 | E67: =D67+E66 | F67: =E67+F66 | G67: =F67+G66 | H67: =G67+H66 | I67: =H67+I66 | J67: =I67+J66 | K67: =J67+K66 | ... W67: =V67+W66
A68: DSCR (debt years) | B68: x | D68: =IF(D34>0,D64/D34,"") | E68: =IF(E34>0,E64/E34,"") | F68: =IF(F34>0,F64/F34,"") | G68: =IF(G34>0,G64/G34,"") | H68: =IF(H34>0,H64/H34,"") | I68: =IF(I34>0,I64/I34,"") | J68: =IF(J34>0,J64/J34,"") | K68: =IF(K34>0,K64/K34,"") | ... W68: =IF(W34>0,W64/W34,"")
A70: OFFTAKER (BUYER) POSITION (USD)
A71: BAU EVN bill (energy + demand) | B71: USD | D71: =BAU_BILL_Y1*D6 | E71: =BAU_BILL_Y1*E6 | F71: =BAU_BILL_Y1*F6 | G71: =BAU_BILL_Y1*G6 | H71: =BAU_BILL_Y1*H6 | I71: =BAU_BILL_Y1*I6 | J71: =BAU_BILL_Y1*J6 | K71: =BAU_BILL_Y1*K6 | ... W71: =BAU_BILL_Y1*W6
A72: C_DN spot energy (Q_Khc × CFMP × K_pp) | B72: USD | D72: =DPPA_C_DN_Y1*D12*D11 | E72: =DPPA_C_DN_Y1*E12*E11 | F72: =DPPA_C_DN_Y1*F12*F11 | G72: =DPPA_C_DN_Y1*G12*G11 | H72: =DPPA_C_DN_Y1*H12*H11 | I72: =DPPA_C_DN_Y1*I12*I11 | J72: =DPPA_C_DN_Y1*J12*J11 | K72: =DPPA_C_DN_Y1*K12*K11 | ... W72: =DPPA_C_DN_Y1*W12*W11
A73: C_DPPA system service fee | B73: USD | D73: =DPPA_C_DPPA_Y1*D12*D11 | E73: =DPPA_C_DPPA_Y1*E12*E11 | F73: =DPPA_C_DPPA_Y1*F12*F11 | G73: =DPPA_C_DPPA_Y1*G12*G11 | H73: =DPPA_C_DPPA_Y1*H12*H11 | I73: =DPPA_C_DPPA_Y1*I12*I11 | J73: =DPPA_C_DPPA_Y1*J12*J11 | K73: =DPPA_C_DPPA_Y1*K12*K11 | ... W73: =DPPA_C_DPPA_Y1*W12*W11
A74: C_CL settlement adder | B74: USD | D74: =DPPA_C_CL_Y1*D12*D11 | E74: =DPPA_C_CL_Y1*E12*E11 | F74: =DPPA_C_CL_Y1*F12*F11 | G74: =DPPA_C_CL_Y1*G12*G11 | H74: =DPPA_C_CL_Y1*H12*H11 | I74: =DPPA_C_CL_Y1*I12*I11 | J74: =DPPA_C_CL_Y1*J12*J11 | K74: =DPPA_C_CL_Y1*K12*K11 | ... W74: =DPPA_C_CL_Y1*W12*W11
A75: C_BL retail shortfall (incl. degradation repurchase) | B75: USD | D75: =(DPPA_C_BL_Y1+DPPA_MATCHED_RETAIL_Y1*(1-D11))*D6 | E75: =(DPPA_C_BL_Y1+DPPA_MATCHED_RETAIL_Y1*(1-E11))*E6 | F75: =(DPPA_C_BL_Y1+DPPA_MATCHED_RETAIL_Y1*(1-F11))*F6 | G75: =(DPPA_C_BL_Y1+DPPA_MATCHED_RETAIL_Y1*(1-G11))*G6 | H75: =(DPPA_C_BL_Y1+DPPA_MATCHED_RETAIL_Y1*(1-H11))*H6 | I75: =(DPPA_C_BL_Y1+DPPA_MATCHED_RETAIL_Y1*(1-I11))*I6 | J75: =(DPPA_C_BL_Y1+DPPA_MATCHED_RETAIL_Y1*(1-J11))*J6 | K75: =(DPPA_C_BL_Y1+DPPA_MATCHED_RETAIL_Y1*(1-K11))*K6 | ... W75: =(DPPA_C_BL_Y1+DPPA_MATCHED_RETAIL_Y1*(1-W11))*W6
A76: Buyer cost with project | B76: USD | D76: =D72+D73+D74+D75+D19+OPT_DEMAND_Y1*D7+D22+BESS_DEMAND_SAVINGS*(1-D10)*D7 | E76: =E72+E73+E74+E75+E19+OPT_DEMAND_Y1*E7+E22+BESS_DEMAND_SAVINGS*(1-E10)*E7 | F76: =F72+F73+F74+F75+F19+OPT_DEMAND_Y1*F7+F22+BESS_DEMAND_SAVINGS*(1-F10)*F7 | G76: =G72+G73+G74+G75+G19+OPT_DEMAND_Y1*G7+G22+BESS_DEMAND_SAVINGS*(1-G10)*G7 | H76: =H72+H73+H74+H75+H19+OPT_DEMAND_Y1*H7+H22+BESS_DEMAND_SAVINGS*(1-H10)*H7 | I76: =I72+I73+I74+I75+I19+OPT_DEMAND_Y1*I7+I22+BESS_DEMAND_SAVINGS*(1-I10)*I7 | J76: =J72+J73+J74+J75+J19+OPT_DEMAND_Y1*J7+J22+BESS_DEMAND_SAVINGS*(1-J10)*J7 | K76: =K72+K73+K74+K75+K19+OPT_DEMAND_Y1*K7+K22+BESS_DEMAND_SAVINGS*(1-K10)*K7 | ... W76: =W72+W73+W74+W75+W19+OPT_DEMAND_Y1*W7+W22+BESS_DEMAND_SAVINGS*(1-W10)*W7
A77: Buyer savings vs BAU | B77: USD | D77: =D71-D76 | E77: =E71-E76 | F77: =F71-F76 | G77: =G71-G76 | H77: =H71-H76 | I77: =I71-I76 | J77: =J71-J76 | K77: =K71-K76 | ... W77: =W71-W76
A78: Buyer savings (% of BAU) | B78: % | D78: =IF(D71=0,"",D77/D71) | E78: =IF(E71=0,"",E77/E71) | F78: =IF(F71=0,"",F77/F71) | G78: =IF(G71=0,"",G77/G71) | H78: =IF(H71=0,"",H77/H71) | I78: =IF(I71=0,"",I77/I71) | J78: =IF(J71=0,"",J77/J71) | K78: =IF(K71=0,"",K77/K71) | ... W78: =IF(W71=0,"",W77/W71)
A80: RETURN METRICS (Excel formulas)
A81: Equity IRR | C81: =IRR(C66:W66)
A82: Project IRR (unlevered) | C82: =IRR(C65:W65)
A83: Equity NPV @ owner discount rate | C83: =NPV(DISC_RATE,D66:W66)+C66
A84: Minimum DSCR (debt years) | C84: =MIN(D68:W68) | D84: MIN ignores the blank non-debt years
A85: Average DSCR (debt years) | C85: =AVERAGE(D68:W68)
A86: First year cumulative equity CF ≥ 0 | C86: =MATCH(TRUE,INDEX(D67:W67>=0,0),0)
A87: Simple equity payback | C87: =IF(ISNA($C$86),"n/a",$C$86-1+IFERROR(-INDEX(C67:W67,$C$86)/INDEX(D66:W66,$C$86),0)) | D87: years
A88: ROI (cumulative equity CF / equity) | C88: =SUM(D66:W66)/EQUITY_INVESTMENT
A89: Buyer savings, years 1-10 (% of BAU) | C89: =SUM(D77:M77)/SUM(D71:M71)
A91: CHECKS - EXCEL vs ENGINE (per-year tie-out)
A92: Equity cash flow (engine) | B92: USD | C92: -1355639.2 | D92: 32040.77 | E92: 49940.528 | F92: 68784.152 | G92: 88402.107 | H92: 108778.02 | I92: 129920.05 | J92: 151845.38 | K92: 164424.51 | L92: 174948.85 | M92: 196403.95 | N92: 414617.93 | O92: 727345.12 | P92: 753148.68 | Q92: 779881.87 | R92: 807576.97 | S92: 801721.27 | T92: 757656.81 | U92: 783582.83 | V92: 803242.8 | W92: 831060.52
A93: CFADS (engine) | B93: USD | D93: 514130.44 | E93: 532030.2 | F93: 550873.83 | G93: 570491.78 | H93: 590867.7 | I93: 612009.73 | J93: 633935.05 | K93: 646514.18 | L93: 657038.52 | M93: 678493.63 | N93: 414617.93 | O93: 727345.12 | P93: 753148.68 | Q93: 779881.87 | R93: 807576.97 | S93: 801721.27 | T93: 757656.81 | U93: 783582.83 | V93: 803242.8 | W93: 831060.52
A94: CIT (engine) | B94: USD | D94: 0 | E94: 0 | F94: 0 | G94: 0 | H94: 0 | I94: 0 | J94: 0 | K94: 10151.234 | L94: 23186.913 | M94: 26148.163 | N94: 27502.699 | O94: 28813.485 | P94: 30171.567 | Q94: 31578.577 | R94: 33036.214 | S94: 69092.484 | T94: 144441.98 | U94: 150923.48 | V94: 164832.92 | W94: 171787.35
A95: Max |Excel − engine| this year | B95: USD | C95: =ABS(C66-C92) | D95: =MAX(ABS(D66-D92),ABS(D64-D93),ABS(D61-D94)) | E95: =MAX(ABS(E66-E92),ABS(E64-E93),ABS(E61-E94)) | F95: =MAX(ABS(F66-F92),ABS(F64-F93),ABS(F61-F94)) | G95: =MAX(ABS(G66-G92),ABS(G64-G93),ABS(G61-G94)) | H95: =MAX(ABS(H66-H92),ABS(H64-H93),ABS(H61-H94)) | I95: =MAX(ABS(I66-I92),ABS(I64-I93),ABS(I61-I94)) | J95: =MAX(ABS(J66-J92),ABS(J64-J93),ABS(J61-J94)) | K95: =MAX(ABS(K66-K92),ABS(K64-K93),ABS(K61-K94)) | ... W95: =MAX(ABS(W66-W92),ABS(W64-W93),ABS(W61-W94))
A97: Check | C97: Excel | D97: Engine | E97: Delta | F97: Status
A98: Per-year cash flow tie-out (max delta, all years) | C98: =MAX(C95:W95) | D98: 0 | E98: =ABS(C98-D98) | F98: =IF(ABS(C98-D98)<=1.0,"PASS","REVIEW")
A99: Equity IRR | C99: =$C$81 | D99: 0.15063243 | E99: =ABS(C99-D99) | F99: =IF(ABS(C99-D99)<=0.0005,"PASS","REVIEW")
A100: Project IRR | C100: =$C$82 | D100: 0.12242528 | E100: =ABS(C100-D100) | F100: =IF(ABS(C100-D100)<=0.0005,"PASS","REVIEW")
A101: Equity NPV | C101: =$C$83 | D101: 986352.68 | E101: =ABS(C101-D101) | F101: =IF(ABS(C101-D101)<=1.0,"PASS","REVIEW")
A102: Minimum DSCR | C102: =$C$84 | D102: 1.0664623 | E102: =ABS(C102-D102) | F102: =IF(ABS(C102-D102)<=0.005,"PASS","REVIEW")
A103: Average DSCR | C103: =$C$85 | D103: 1.2417576 | E103: =ABS(C103-D103) | F103: =IF(ABS(C103-D103)<=0.005,"PASS","REVIEW")
A104: Simple equity payback | C104: =$C$87 | D104: 10.458617 | E104: =ABS(C104-D104) | F104: =IF(ABS(C104-D104)<=0.05,"PASS","REVIEW")
A105: ROI | C105: =$C$88 | D105: 6.3625506 | E105: =ABS(C105-D105) | F105: =IF(ABS(C105-D105)<=0.0005,"PASS","REVIEW")
A106: Buyer savings, years 1-10 (% of BAU) | C106: =$C$89 | D106: -0.092531784 | E106: =ABS(C106-D106) | F106: =IF(ABS(C106-D106)<=0.0005,"PASS","REVIEW")

Sheet FX Sensitivity
A1: FX Sensitivity - VND depreciation vs USD returns
A2: Cash flows are VND-denominated (EVN tariff / DPPA settlement) but reported in USD at the fixed contract rate. Each scenario deflates the year-t USD equity cash flow by (1+d)^t. Debt is assumed VND-denominated, so DSCR is unchanged. The rate cells are editable; engine columns validate the default scenarios.
A4: VND depreciation (per year) | B4: Equity IRR (USD) | C4: Equity NPV (USD) | D4: Equity IRR (engine) | E4: Equity NPV (engine) | F4: Status
A5: 0 | B5: =IRR(B12:V12) | C5: =NPV(DISC_RATE,C12:V12)+B12 | D5: 0.15063243 | E5: 986352.68 | F5: =IF(AND(ABS(B5-D5)<=0.0005,ABS(C5-E5)<=1.0),"PASS","REVIEW")
A6: 0.01 | B6: =IRR(B13:V13) | C6: =NPV(DISC_RATE,C13:V13)+B13 | D6: 0.13924003 | E6: 711041.82 | F6: =IF(AND(ABS(B6-D6)<=0.0005,ABS(C6-E6)<=1.0),"PASS","REVIEW")
A7: 0.02 | B7: =IRR(B14:V14) | C7: =NPV(DISC_RATE,C14:V14)+B14 | D7: 0.12807101 | E7: 474526.54 | F7: =IF(AND(ABS(B7-D7)<=0.0005,ABS(C7-E7)<=1.0),"PASS","REVIEW")
A8: 0.03 | B8: =IRR(B15:V15) | C8: =NPV(DISC_RATE,C15:V15)+B15 | D8: 0.11711887 | E8: 270731.7 | F8: =IF(AND(ABS(B8-D8)<=0.0005,ABS(C8-E8)<=1.0),"PASS","REVIEW")
A10: Helper - FX-adjusted equity cash flow per scenario (USD): CF_t / (1 + d)^t
B11: 0 | C11: 1 | D11: 2 | E11: 3 | F11: 4 | G11: 5 | H11: 6 | I11: 7 | J11: 8 | K11: 9 | L11: 10 | M11: 11 | N11: 12 | O11: 13 | P11: 14 | Q11: 15 | R11: 16 | S11: 17 | T11: 18 | U11: 19 | V11: 20
A12: =A5 | B12: ='Pro Forma (Audit)'!C66/(1+$A5)^B$11 | C12: ='Pro Forma (Audit)'!D66/(1+$A5)^C$11 | D12: ='Pro Forma (Audit)'!E66/(1+$A5)^D$11 | E12: ='Pro Forma (Audit)'!F66/(1+$A5)^E$11 | F12: ='Pro Forma (Audit)'!G66/(1+$A5)^F$11 | G12: ='Pro Forma (Audit)'!H66/(1+$A5)^G$11 | H12: ='Pro Forma (Audit)'!I66/(1+$A5)^H$11 | I12: ='Pro Forma (Audit)'!J66/(1+$A5)^I$11 | ... V12: ='Pro Forma (Audit)'!W66/(1+$A5)^V$11
A13: =A6 | B13: ='Pro Forma (Audit)'!C66/(1+$A6)^B$11 | C13: ='Pro Forma (Audit)'!D66/(1+$A6)^C$11 | D13: ='Pro Forma (Audit)'!E66/(1+$A6)^D$11 | E13: ='Pro Forma (Audit)'!F66/(1+$A6)^E$11 | F13: ='Pro Forma (Audit)'!G66/(1+$A6)^F$11 | G13: ='Pro Forma (Audit)'!H66/(1+$A6)^G$11 | H13: ='Pro Forma (Audit)'!I66/(1+$A6)^H$11 | I13: ='Pro Forma (Audit)'!J66/(1+$A6)^I$11 | ... V13: ='Pro Forma (Audit)'!W66/(1+$A6)^V$11
A14: =A7 | B14: ='Pro Forma (Audit)'!C66/(1+$A7)^B$11 | C14: ='Pro Forma (Audit)'!D66/(1+$A7)^C$11 | D14: ='Pro Forma (Audit)'!E66/(1+$A7)^D$11 | E14: ='Pro Forma (Audit)'!F66/(1+$A7)^E$11 | F14: ='Pro Forma (Audit)'!G66/(1+$A7)^F$11 | G14: ='Pro Forma (Audit)'!H66/(1+$A7)^G$11 | H14: ='Pro Forma (Audit)'!I66/(1+$A7)^H$11 | I14: ='Pro Forma (Audit)'!J66/(1+$A7)^I$11 | ... V14: ='Pro Forma (Audit)'!W66/(1+$A7)^V$11
A15: =A8 | B15: ='Pro Forma (Audit)'!C66/(1+$A8)^B$11 | C15: ='Pro Forma (Audit)'!D66/(1+$A8)^C$11 | D15: ='Pro Forma (Audit)'!E66/(1+$A8)^D$11 | E15: ='Pro Forma (Audit)'!F66/(1+$A8)^E$11 | F15: ='Pro Forma (Audit)'!G66/(1+$A8)^F$11 | G15: ='Pro Forma (Audit)'!H66/(1+$A8)^G$11 | H15: ='Pro Forma (Audit)'!I66/(1+$A8)^H$11 | I15: ='Pro Forma (Audit)'!J66/(1+$A8)^I$11 | ... V15: ='Pro Forma (Audit)'!W66/(1+$A8)^V$11

Sheet Buyer Analysis
B1: Buyer Analysis - Cost vs Business-As-Usual
B2: Annual electricity cost with the project compared against the EVN-only baseline (USD)
B4: Year 1 Snapshot
B5: Year 1 BAU Cost (USD) | C5: 731030.93
B6: Year 1 Cost With Project (USD) | C6: 796739.54
B7: Year 1 Savings (USD) | C7: -65708.612
B8: Year 1 Savings (% of BAU) | C8: -0.089884859
B9: of which C_DN spot energy (USD) | C9: 366771.55
B10: of which C_DPPA + C_CL fees (USD) | C10: 126704.56
B11: of which C_BL retail shortfall (USD) | C11: 172364.17
B12: of which CfD payment, net (USD) | C12: 130899.25 | D12: Positive = buyer pays generator
B13: First 10 Years Savings (USD) | C13: -812136.26 | D13: Cumulative, years 1-10
B14: First 10 Years Savings (% of BAU) | C14: -0.092531784
B15: Lifetime Savings (USD) | C15: -2078855.7 | D15: Cumulative over analysis period
B16: Lifetime Savings (% of BAU) | C16: -0.09549748
A18: Year | B18: BAU Cost (USD) | C18: Cost With Project (USD) | D18: Savings (USD) | E18: Savings (% of BAU) | F18: Cumulative Savings (USD)
A19: 1 | B19: 731030.93 | C19: 796739.54 | D19: -65708.612 | E19: -0.089884859 | F19: -65708.612
A20: 2 | B20: 760272.17 | C20: 829086.41 | D20: -68814.241 | E20: -0.09051264 | F20: -134522.85
A21: 3 | B21: 790683.05 | C21: 862695.4 | D21: -72012.345 | E21: -0.09107612 | F21: -206535.2
A22: 4 | B22: 822310.38 | C22: 897648.09 | D22: -75337.715 | E22: -0.091617127 | F22: -281872.91
A23: 5 | B23: 855202.79 | C23: 934005.39 | D23: -78802.598 | E23: -0.092144926 | F23: -360675.51
A24: 6 | B24: 889410.9 | C24: 971826.87 | D24: -82415.969 | E24: -0.092663547 | F24: -443091.48
A25: 7 | B25: 924987.34 | C25: 1011173.2 | D25: -86185.857 | E25: -0.093175175 | F25: -529277.34
A26: 8 | B26: 961986.83 | C26: 1052106.9 | D26: -90120.038 | E26: -0.093681156 | F26: -619397.38
A27: 9 | B27: 1000466.3 | C27: 1094692.6 | D27: -94226.302 | E27: -0.094182384 | F27: -713623.68
A28: 10 | B28: 1040485 | C28: 1138997.5 | D28: -98512.587 | E28: -0.094679492 | F28: -812136.26
A29: 11 | B29: 1082104.4 | C29: 1185091.4 | D29: -102987.06 | E29: -0.095172945 | F29: -915123.32
A30: 12 | B30: 1125388.5 | C30: 1233046.7 | D30: -107658.16 | E30: -0.095663101 | F30: -1022781.5
... A38: 20 | B38: 1540171.9 | C38: 1693404.2 | D38: -153232.26 | E38: -0.09949036 | F38: -2078855.7

Sheet Developer Returns
B1: Developer Returns - Financing & Cash Flow
B2: Seller/ESCO investment case: sources & uses, return metrics and annual equity cash flow (USD)
B4: Sources & Uses
B5: Total Investment (USD) | C5: 4518797.4
B6: Debt Principal (USD) | C6: 3163158.2
B7: Equity Investment (USD) | C7: 1355639.2
B9: Return Metrics
B10: Equity IRR | C10: 0.15063243
B11: Project IRR | C11: 0.12242528
B12: NPV (USD) | C12: 986352.68 | D12: At owner discount rate
B13: Minimum DSCR (debt years) | C13: 1.0664623
B14: Average DSCR | C14: 1.2417576
B15: Simple Payback (Years) | C15: 10.458617
B16: ROI (cumulative equity CF / equity) | C16: 6.3625506
A18: Year | B18: Revenue (USD) | C18: O&M + Replacement (USD) | D18: CIT (USD) | E18: CFADS (USD) | F18: Debt Service (USD) | G18: DSCR | H18: Equity Cash Flow (USD) | I18: Cumulative Equity CF (USD)
A19: 1 | B19: 566513.97 | C19: 52383.521 | D19: 0 | E19: 514130.44 | F19: 482089.67 | G19: 1.0664623 | H19: 32040.77 | I19: -1323598.4
A20: 2 | B20: 585985.23 | C20: 53955.027 | D20: 0 | E20: 532030.2 | F20: 482089.67 | G20: 1.1035918 | H20: 49940.528 | I20: -1273657.9
A21: 3 | B21: 606447.5 | C21: 55573.678 | D21: 0 | E21: 550873.83 | F21: 482089.67 | G21: 1.1426792 | H21: 68784.152 | I21: -1204873.8
A22: 4 | B22: 627732.67 | C22: 57240.888 | D22: 0 | E22: 570491.78 | F22: 482089.67 | G22: 1.1833727 | H22: 88402.107 | I22: -1116471.7
A23: 5 | B23: 649825.81 | C23: 58958.115 | D23: 0 | E23: 590867.7 | F23: 482089.67 | G23: 1.2256386 | H23: 108778.02 | I23: -1007693.6
A24: 6 | B24: 672736.59 | C24: 60726.858 | D24: 0 | E24: 612009.73 | F24: 482089.67 | G24: 1.2694935 | H24: 129920.05 | I24: -877773.57
A25: 7 | B25: 696483.71 | C25: 62548.664 | D25: 0 | E25: 633935.05 | F25: 482089.67 | G25: 1.3149733 | H25: 151845.38 | I25: -725928.2
A26: 8 | B26: 721090.54 | C26: 64425.124 | D26: 10151.234 | E26: 646514.18 | F26: 482089.67 | G26: 1.3410662 | H26: 164424.51 | I26: -561503.69
A27: 9 | B27: 746583.31 | C27: 66357.878 | D27: 23186.913 | E27: 657038.52 | F27: 482089.67 | G27: 1.3628969 | H27: 174948.85 | I27: -386554.84
A28: 10 | B28: 772990.41 | C28: 68348.614 | D28: 26148.163 | E28: 678493.63 | F28: 482089.67 | G28: 1.4074013 | H28: 196403.95 | I28: -190150.89
A29: 11 | B29: 800341.96 | C29: 358221.33 | D29: 27502.699 | E29: 414617.93 | F29: 0 | H29: 414617.93 | I29: 224467.04
A30: 12 | B30: 828669.65 | C30: 72511.044 | D30: 28813.485 | E30: 727345.12 | F30: 0 | H30: 727345.12 | I30: 951812.16
A31: 13 | B31: 858006.62 | C31: 74686.376 | D31: 30171.567 | E31: 753148.68 | F31: 0 | H31: 753148.68 | I31: 1704960.8
A32: 14 | B32: 888387.42 | C32: 76926.967 | D32: 31578.577 | E32: 779881.87 | F32: 0 | H32: 779881.87 | I32: 2484842.7
A33: 15 | B33: 919847.96 | C33: 79234.776 | D33: 33036.214 | E33: 807576.97 | F33: 0 | H33: 807576.97 | I33: 3292419.7
A34: 16 | B34: 952425.57 | C34: 81611.819 | D34: 69092.484 | E34: 801721.27 | F34: 0 | H34: 801721.27 | I34: 4094141
A35: 17 | B35: 986158.96 | C35: 84060.174 | D35: 144441.98 | E35: 757656.81 | F35: 0 | H35: 757656.81 | I35: 4851797.8
A36: 18 | B36: 1021088.3 | C36: 86581.979 | D36: 150923.48 | E36: 783582.83 | F36: 0 | H36: 783582.83 | I36: 5635380.6
A37: 19 | B37: 1057255.2 | C37: 89179.439 | D37: 164832.92 | E37: 803242.8 | F37: 0 | H37: 803242.8 | I37: 6438623.4
A38: 20 | B38: 1094702.7 | C38: 91854.822 | D38: 171787.35 | E38: 831060.52 | F38: 0 | H38: 831060.52 | I38: 7269683.9

Sheet Technical Results
A1: Metric | B1: Value
A2: System Sizing
A3: PV Size (kW) | B3: 5996.297
A4: Battery Power (kW) | B4: 2011.12
A5: Battery Energy (kWh) | B5: 12330.71
A7: Annual Energy Balance (Year 1)
A8: PV to Load (kWh) | B8: 3915831.5
A9: PV to Storage (kWh) | B9: 3029670.4
A10: PV to Grid (kWh) | B10: 0
A11: Storage to Load (kWh) | B11: 2725990
A12: Grid to Load (kWh) | B12: 2958491.1
A13: PV Curtailed (kWh) | B13: 1497539.6
A14: Grid to Storage (kWh) | B14: 0
A16: Year-1 Utility Bill Comparison
A17: BAU Utility Bill (USD) | B17: 731030.93
A18: Optimized Utility Bill (USD) | B18: 148205.46
A19: Utility Bill Savings (USD) | B19: 582825.47
A20: BAU Demand Charge (USD) | B20: 0
A21: Optimized Demand Charge (USD) | B21: 0
A22: Demand Charge Savings (USD) | B22: 0
A24: Solar Resource (Year 1)
A25: Annual POA Irradiation (kWh/m²) | B25: 1929.6822
A26: Performance Ratio (Year 1) | B26: 0.72967589

Sheet Battery SOH
A1: Battery state of health
A3: Method: REopt.jl v0.57.0 daily fade recurrence replayed over the horizon on the solved year-1 dispatch. SOH[d] = SOH[d-1] - (k_cal x a x Eavg[d-1] x d^(a-1) + k_cyc x E_discharged[d-1]), SOH in kWh, with the hours-per-time-step factor removed (h = 1) so 15 minute and hourly solves age alike.
A4: Cycle fade: k_cyc = (1 - 0.80) / cycle life = 2.500e-05 kWh lost per kWh discharged (cycle life 8,000 EFC to 80 percent).
A5: Calendar fade: k_cal = 1.16e-03, exponent a = 0.428 (NREL laboratory defaults, no chemistry or temperature calibration).
A6: Use: the year-average SOH multiplies the battery's share of the savings on the Pro Forma (Audit) sheet (row 'Battery SOH factor'). Energy delivered is assumed to scale with capacity, the battery treated as capacity-bound every day: an upper bound on the loss. The optimiser does not see this curve; no battery replacement is scheduled unless the case opts in.
A7: Energy attribution: inside the served series (PV-charged storage). Demand attribution: counterfactual.
A9: Nominal capacity (kWh) | B9: 12330.71
A10: SOH end of year 10 | B10: 0.92119669
A11: SOH end of year 20 | B11: 0.85751376
A12: First year below 80 percent | B12: Not within the 20 year horizon
A13: Equivalent full cycles, year 1 | B13: 221.07324
A14: Equivalent full cycles, cumulative | B14: 4421.4648
A15: Average daily discharge, year 1 (kWh) | B15: 7468.4658
A16: Value lost to fade over the horizon (USD) | B16: 589983.2
A18: Year | B18: SOH end of year | C18: SOH year average (derate factor) | D18: Usable capacity (kWh) | E18: EFC in year | F18: Cumulative EFC | G18: Calendar fade (kWh) | H18: Cycle fade (kWh) | I18: Value lost to fade (USD) | J18: End of life (80 percent)
A19: 0 | B19: 1 | C19: 1 | D19: 12330.71 | E19: 0 | F19: 0 | G19: 0 | H19: 0 | I19: 0 | J19: 0.8
A20: 1 | B20: 0.98620752 | C20: 0.99162852 | D20: 12160.639 | E20: 221.07324 | F20: 221.07324 | G20: 102.16346 | H20: 67.907669 | I20: 1926.1351 | J20: 0.8
A21: 2 | B21: 0.97754035 | C21: 0.98171758 | D21: 12053.767 | E21: 221.07324 | F21: 442.14648 | G21: 38.72253 | H21: 68.149751 | I21: 4374.7338 | J21: 0.8
A22: 3 | B22: 0.96969515 | C22: 0.97352153 | D22: 11957.03 | E22: 221.07324 | F22: 663.21972 | G22: 28.587098 | H22: 68.149751 | I22: 6589.3757 | J22: 0.8
A23: 4 | B23: 0.96226153 | C23: 0.96590164 | D23: 11865.368 | E23: 221.07324 | F23: 884.29297 | G23: 23.512063 | H23: 68.149751 | I23: 8825.0698 | J23: 0.8
A24: 5 | B24: 0.95508522 | C24: 0.95860584 | D24: 11776.879 | E24: 221.07324 | F24: 1105.3662 | G24: 20.339287 | H24: 68.149751 | I24: 11141.844 | J24: 0.8
A25: 6 | B25: 0.94808867 | C25: 0.95152458 | D25: 11690.606 | E25: 221.07324 | F25: 1326.4394 | G25: 18.122697 | H25: 68.149751 | I25: 13569.783 | J25: 0.8
A26: 7 | B26: 0.94122652 | C26: 0.94459849 | D26: 11605.991 | E26: 221.07324 | F26: 1547.5127 | G26: 16.465452 | H26: 68.149751 | I26: 16128.957 | J26: 0.8
A27: 8 | B27: 0.93446958 | C27: 0.93779116 | D27: 11522.673 | E27: 221.07324 | F27: 1768.5859 | G27: 15.168108 | H27: 68.149751 | I27: 18835.196 | J27: 0.8
A28: 9 | B28: 0.92779779 | C28: 0.93107839 | D28: 11440.406 | E28: 221.07324 | F28: 1989.6592 | G28: 14.118111 | H28: 68.149751 | I28: 21702.352 | J28: 0.8
A29: 10 | B29: 0.92119669 | C29: 0.92444313 | D29: 11359.009 | E29: 221.07324 | F29: 2210.7324 | G29: 13.246553 | H29: 68.149751 | I29: 24743.359 | J29: 0.8
A30: 11 | B30: 0.91465543 | C30: 0.91787287 | D30: 11278.351 | E30: 221.07324 | F30: 2431.8057 | G30: 12.50861 | H30: 68.149751 | I30: 27970.788 | J30: 0.8
... A39: 20 | B39: 0.85751376 | C39: 0.86058341 | D39: 10573.754 | E39: 221.07324 | F39: 4421.4648 | G39: 8.7766864 | H39: 68.149751 | I39: 67582.236 | J39: 0.8

Sheet Dispatch Profile
A1: Hour | B1: Load (kW) | C1: PV Irradiation (W/m²) | D1: PV Generation Total (kW) | E1: PV to Load (kW) | F1: PV to Storage (kW) | G1: PV to Grid (kW) | H1: PV Curtailed (kW) | I1: Grid to Load (kW) | J1: Grid to Storage (kW) | K1: Storage to Load (kW)
A2: 1 | B2: 1020 | C2: 0 | D2: 0 | E2: 0 | F2: 0 | G2: 0 | H2: 0 | I2: 1020 | J2: 0 | K2: 0
A3: 2 | B3: 1078.4 | C3: 0 | D3: 0 | E3: 0 | F3: 0 | G3: 0 | H3: 0 | I3: 1078.4 | J3: 0 | K3: 0
A4: 3 | B4: 906.4 | C4: 0 | D4: 0 | E4: 0 | F4: 0 | G4: 0 | H4: 0 | I4: 810.13 | J4: 0 | K4: 100.19558
A5: 4 | B5: 860.8 | C5: 0 | D5: 0 | E5: 0 | F5: 0 | G5: 0 | H5: 0 | I5: 0 | J5: 0 | K5: 895.90066
A6: 5 | B6: 996.8 | C6: 0 | D6: 0 | E6: 0 | F6: 0 | G6: 0 | H6: 0 | I6: 0 | J6: 0 | K6: 1037.4463
A7: 6 | B7: 983.2 | C7: 0 | D7: 0 | E7: 0 | F7: 0 | G7: 0 | H7: 0 | I7: 0 | J7: 0 | K7: 1023.2917
A8: 7 | B8: 586.4 | C8: 11.75 | D8: 17.587046 | E8: 17.587046 | F8: 0 | G8: 0 | H8: 0 | I8: 0 | J8: 0 | K8: 592.72447
A9: 8 | B9: 104.269 | C9: 120.27 | D9: 544.18784 | E9: 108.52076 | F9: -435.66708 | G9: 0 | H9: 0 | I9: 0 | J9: 0 | K9: 0
A10: 9 | B10: 89.172 | C10: 270.88 | D10: 1273.4518 | E10: 92.808148 | F10: -1180.6437 | G10: 0 | H10: 0 | I10: 0 | J10: 0 | K10: 0
A11: 10 | B11: 105.232 | C11: 505.48 | D11: 2362.5893 | E11: 109.52302 | F11: -2093.1229 | G11: 0 | H11: 159.94346 | I11: 0 | J11: 0 | K11: 0
A12: 11 | B12: 89.626 | C12: 573.07 | D12: 2636.3855 | E12: 93.27962 | F12: -2093.1229 | G12: 0 | H12: 449.98297 | I12: 0 | J12: 0 | K12: 0
A13: 12 | B13: 119.641 | C13: 477.66 | D13: 2176.8482 | E13: 124.51958 | F13: -2052.3286 | G13: 0 | H13: 0 | I13: 0 | J13: 0 | K13: 0
... A8761: 8760 | B8761: 1216 | C8761: 0 | D8761: 0 | E8761: 0 | F8761: 0 | G8761: 0 | H8761: 0 | I8761: 0 | J8761: 0 | K8761: 1265.5846

Sheet Load Duration
A1: Rank | B1: Load (kW) | C1: Net Load (kW)
A2: 1 | B2: 2428 | C2: 2428
A3: 2 | B3: 2418.5558 | C3: 2418.556
A4: 3 | B4: 2414.4 | C4: 2379.2
A5: 4 | B5: 2405.0087 | C5: 2369.946
A6: 5 | B6: 2390.381 | C6: 2341.493
A7: 6 | B7: 2389.6 | C7: 2330.4
A8: 7 | B8: 2387.844 | C8: 2321.335
A9: 8 | B9: 2381.0831 | C9: 2227.735
A10: 9 | B10: 2380.3051 | C10: 2208.8
A11: 10 | B11: 2379.2 | C11: 2200.208
A12: 11 | B12: 2378.556 | C12: 2156.8
A13: 12 | B13: 2369.9456 | C13: 2148.411
... A8761: 8760 | B8761: 0 | C8761: 0

Sheet Year 1 BAU vs DPPA
A1: Line Item | B1: Year 1 (USD) | C1: Side
A2: Buyer (Factory) - Year 1 Outflow (USD)
A3: BAU EVN energy + demand bill | B3: 731030.93 | C3: bau
A4: C_DN spot energy (Q_Khc × CFMP × K_pp) | B4: 366771.55 | C4: dppa
A5: C_DPPA system service fee | B5: 87165.377 | C5: dppa
A6: C_CL settlement adder | B6: 39539.184 | C6: dppa
A7: C_BL retail shortfall (P_evn × shortfall) | B7: 172364.17 | C7: dppa
A8: CfD payment to ESCO (positive = pay) | B8: 130899.25 | C8: dppa
A9: Optimized demand charge (kept by EVN) | B9: 0 | C9: dppa
A10: ESCO demand savings share charged back | B10: 0 | C10: dppa
A11: Total buyer outflow | B11: 796739.54 | C11: both
A12: Buyer savings vs BAU | B12: -65708.612 | C12: delta
A13: Buyer savings as % of BAU | B13: -0.089884859 | C13: delta_fraction
A14: Seller (ESCO / Generator) - Year 1 Revenue (USD)
A15: Discount-to-EVN energy revenue (Phase 2) | B15: 0 | C15: bau_esco
A16: FMP market revenue (Q_re_meter × FMP) | B16: 435614.71 | C16: dppa
A17: CfD net (from buyer) | B17: 130899.25 | C17: dppa
A18: Demand savings share (80%) | B18: 0 | C18: both_esco
A19: ESCO grid arbitrage revenue | B19: 0 | C19: both_esco
A20: Total ESCO / generator revenue | B20: 566513.97 | C20: both_esco
A21: System Energy Flows (kWh / yr)
A22: PV → load | B22: 3915831.5 | C22: flow
A23: PV → storage | B23: 3029670.4 | C23: flow
A24: PV → grid (export at FMP) | B24: 1497539.6 | C24: flow
A25: Storage → load | B25: 2725990 | C25: flow
A26: Q_re_meter (total generator injection) | B26: 8139361.1 | C26: flow
A27: Q_adj (loss-adjusted customer-side) | B27: 7923346.9 | C27: flow
A28: Q_Khc (matched consumption, settled) | B28: 6389869.9 | C28: flow
A29: EVN retail shortfall | B29: 2950221.7 | C29: flow

Sheet Monthly Settlement
A1: Month | B1: C_DN (VND) | C1: C_DPPA (VND) | D1: C_CL (VND) | E1: C_BL (VND) | F1: CfD Net (VND) | G1: Generator Revenue (VND) | H1: Customer Total (VND)
A2: 1 | B2: 8.0935144e+08 | C2: 1.9085944e+08 | D2: 86575964 | E2: 4.5636306e+08 | F2: 2.7960321e+08 | G2: 1.3146922e+09 | H2: 1.8227531e+09
A3: 2 | B3: 7.7480174e+08 | C3: 1.8644146e+08 | D3: 84571916 | E3: 2.4324678e+08 | F3: 2.9094036e+08 | G3: 1.3253992e+09 | H3: 1.5800022e+09
A4: 3 | B4: 1.0732897e+09 | C4: 2.212879e+08 | D4: 1.0037865e+08 | E4: 3.068432e+08 | F4: 2.0212093e+08 | G4: 1.5849026e+09 | H4: 1.9039204e+09
A5: 4 | B5: 1.0180566e+09 | C5: 2.0029315e+08 | D5: 90855197 | E5: 2.5709087e+08 | F5: 1.4121731e+08 | G5: 1.4172996e+09 | H5: 1.7075131e+09
A6: 5 | B6: 9.535904e+08 | C6: 2.0995973e+08 | D6: 95240067 | E6: 1.8824624e+08 | F6: 2.534042e+08 | G6: 1.3138659e+09 | H6: 1.7004406e+09
A7: 6 | B7: 5.5676903e+08 | C7: 1.848953e+08 | D7: 83870561 | E7: 3.4442419e+08 | F7: 4.7514826e+08 | G7: 1.0732449e+09 | H7: 1.6451073e+09
A8: 7 | B8: 6.1377388e+08 | C8: 1.8457309e+08 | D8: 83724402 | E8: 2.9796721e+08 | F8: 4.2390822e+08 | G8: 1.1249403e+09 | H8: 1.6039468e+09
A9: 8 | B9: 7.6409384e+08 | C9: 1.7886158e+08 | D9: 81133598 | E9: 4.7264738e+08 | F9: 2.6233222e+08 | G9: 1.253896e+09 | H9: 1.7590686e+09
A10: 9 | B10: 5.7099189e+08 | C10: 1.8379911e+08 | D10: 83373320 | E10: 4.2724312e+08 | F10: 4.5330683e+08 | G10: 1.0823364e+09 | H10: 1.7187143e+09
A11: 10 | B11: 7.4908022e+08 | C11: 1.7078138e+08 | D11: 77468333 | E11: 5.6998029e+08 | F11: 2.2849346e+08 | G11: 1.0572264e+09 | H11: 1.7958037e+09
A12: 11 | B12: 8.8567331e+08 | C12: 1.9562359e+08 | D12: 88737035 | E12: 4.5869577e+08 | F12: 2.3603337e+08 | G12: 1.1840262e+09 | H12: 1.8647631e+09
A13: 12 | B13: 9.0987698e+08 | C13: 1.9297746e+08 | D13: 87536719 | E13: 4.5977224e+08 | F13: 1.9614204e+08 | G13: 1.2069872e+09 | H13: 1.8463054e+09

Sheet Hourly Settlement
A1: Hour | B1: Load (kW) | C1: Q_re_meter (kW) | D1: Q_re_delivered (kW) | E1: Q_adj (kW) | F1: Q_Khc (kW) | G1: FMP (VND/kWh) | H1: C_DN (VND) | I1: C_DPPA (VND) | J1: C_CL (VND) | K1: C_BL (VND) | L1: CfD Payment (VND)
A2: 1 | B2: 1020 | C2: 0 | D2: 0 | E2: 0 | F2: 0 | G2: 1377.55 | H2: 0 | I2: 0 | J2: 0 | K2: 1213800 | L2: 0
A3: 2 | B3: 1078.4 | C3: 0 | D3: 0 | E3: 0 | F3: 0 | G3: 1316 | H3: 0 | I3: 0 | J3: 0 | K3: 1283296 | L3: 0
A4: 3 | B4: 906.4 | C4: 100.19558 | D4: 100.19558 | E4: 97.536446 | F4: 97.536446 | G4: 1367.3 | H4: 142504.2 | I4: 35113.12 | J4: 15927.702 | K4: 962547.63 | L4: 0
A5: 4 | B5: 860.8 | C5: 895.90066 | D5: 895.90066 | E5: 872.12395 | F5: 860.8 | G5: 1420.5 | H5: 1301886.6 | I5: 309888 | J5: 140568.64 | K5: 0 | L5: 285499.37
A6: 5 | B6: 996.8 | C6: 1037.4463 | D6: 1037.4463 | E6: 1009.913 | F6: 996.8 | G6: 1423.7 | H6: 1511250.9 | I6: 358848 | J6: 162777.44 | K6: 0 | L6: 574455.84
A7: 6 | B7: 983.2 | C7: 1023.2917 | D7: 1023.2917 | E7: 996.13414 | F7: 983.2 | G7: 1433.15 | H7: 1498854 | I7: 353952 | J7: 160556.56 | K7: 0 | L7: 557326.92
A8: 7 | B8: 586.4 | C8: 610.31151 | D8: 610.31151 | E8: 594.11418 | F8: 586.4 | G8: 1460.05 | H8: 908093.43 | I8: 211104 | J8: 95759.12 | K8: 0 | L8: 316626.68
A9: 8 | B9: 104.269 | C9: 108.52076 | D9: 108.52076 | E9: 105.64067 | F9: 104.269 | G9: 1481.35 | H9: 163091.23 | I9: 37536.84 | J9: 17027.128 | K9: 0 | L9: 54079.117
A10: 9 | B10: 89.172 | C10: 92.808148 | D10: 92.808148 | E10: 90.345071 | F10: 89.172 | G10: 1273.8 | H10: 119873.54 | I10: 32101.92 | J10: 14561.788 | K10: 0 | L10: 64756.706
A11: 10 | B11: 105.232 | C11: 269.46648 | D11: 109.52302 | E11: 262.31499 | F11: 105.232 | G11: 1251.7 | H11: 139185.26 | I11: 37883.52 | J11: 17184.386 | K11: 0 | L11: 78745.106
A12: 11 | B12: 89.626 | C12: 543.26259 | D12: 93.27962 | E12: 528.8447 | F12: 89.626 | G12: 1237.2 | H12: 117193.73 | I12: 32265.36 | J12: 14635.926 | K12: 0 | L12: 68366.713
A13: 12 | B13: 119.641 | C13: 124.51958 | D13: 124.51958 | E13: 121.21489 | F13: 119.641 | G13: 1241.95 | H13: 156736.63 | I13: 43070.76 | J13: 19537.375 | K13: 0 | L13: 90693.86
... A8761: 8760 | B8761: 1216 | C8761: 1265.5846 | D8761: 1265.5846 | E8761: 1231.9967 | F8761: 1216 | G8761: 1658.6 | H8761: 2122538.8 | I8761: 437760 | J8761: 198572.8 | K8761: 0 | L8761: 394753.31
