Workbook
Name PROJECT_YEARS: 'Assumptions'!$C$9
Name FX_VND_PER_USD: 'Assumptions'!$C$12
Name PV_CAPEX: 'Assumptions'!$C$15
Name BESS_CAPEX: 'Assumptions'!$C$16
Name OTHER_CAPEX: 'Assumptions'!$C$17
Name TOTAL_CAPEX: 'Assumptions'!$C$18
Name OM_YEAR1: 'Assumptions'!$C$20
Name ESC_OM: 'Assumptions'!$C$21
Name ESC_ENERGY: 'Assumptions'!$C$30
Name ESC_CAPACITY: 'Assumptions'!$C$31
Name PV_DEGRADATION: 'Assumptions'!$C$32
Name ESCO_DISCOUNT: 'Assumptions'!$C$34
Name DEMAND_SHARE: 'Assumptions'!$C$35
Name ESC_STRIKE: 'Assumptions'!$C$38
Name ESC_FEE: 'Assumptions'!$C$39
Name DEBT_FRACTION: 'Assumptions'!$C$48
Name DEBT_RATE: 'Assumptions'!$C$49
Name DEBT_TERM_YEARS: 'Assumptions'!$C$50
Name DEBT_PRINCIPAL: 'Assumptions'!$C$51
Name EQUITY_INVESTMENT: 'Assumptions'!$C$52
Name DEBT_PAYMENT: 'Assumptions'!$C$53
Name DISC_RATE: 'Assumptions'!$C$54
Name CIT_RATE: 'Assumptions'!$C$57
Name CIT_PREF_RATE: 'Assumptions'!$C$58
Name CIT_PREF_YEARS: 'Assumptions'!$C$59
Name CIT_HOLIDAY_YEARS: 'Assumptions'!$C$60
Name CIT_REDUCED_YEARS: 'Assumptions'!$C$61
Name CIT_REDUCED_FRACTION: 'Assumptions'!$C$62
Name CIT_LOSS_CF_YEARS: 'Assumptions'!$C$63
Name CIT_CLOCK_CAP_YEAR: 'Assumptions'!$C$64
Name PV_DEP_YEARS: 'Assumptions'!$C$65
Name BESS_DEP_YEARS: 'Assumptions'!$C$66
Name BAU_BILL_Y1: 'Assumptions'!$C$68
Name OPT_BILL_Y1: 'Assumptions'!$C$69
Name BAU_DEMAND_Y1: 'Assumptions'!$C$70
Name OPT_DEMAND_Y1: 'Assumptions'!$C$71
Name BASE_DEMAND_SAVINGS: 'Assumptions'!$C$72
Name BASE_SERVED_RETAIL: 'Assumptions'!$C$73
Name DPPA_C_DN_Y1: 'Assumptions'!$C$74
Name DPPA_C_DPPA_Y1: 'Assumptions'!$C$75
Name DPPA_C_CL_Y1: 'Assumptions'!$C$76
Name DPPA_C_BL_Y1: 'Assumptions'!$C$77
Name DPPA_CFD_STRIKE_Y1: 'Assumptions'!$C$78
Name DPPA_CFD_OFFSET_Y1: 'Assumptions'!$C$79
Name DPPA_FMP_REV_Y1: 'Assumptions'!$C$80
Name DPPA_MATCHED_RETAIL_Y1: 'Assumptions'!$C$81

Sheet Cover
B2: Investment Case Workbook - Vietnam ESCO / DPPA Case
B3: Grid-connected DPPA with CfD (ND57/2025) · prepared 2026-09-13 · REopt dispatch + proforma_vietnam financial engine
B4: REopt run UUID: 51114e02-ba05-4c15-a826-c4078ec7034a
B6: Model validation status | C6: =IF(COUNTIF('Pro Forma (Audit)'!F97:F105,"REVIEW")+COUNTIF('FX Sensitivity'!F5:F8,"REVIEW")=0,"ALL CHECKS PASS","REVIEW REQUIRED") | D6: Live tie-out of every Excel-derived metric against the engine
B8: Colour legend
B9: Hardcoded input / engine output | C9: Case file terms, REopt dispatch results, 8760-h settlement totals, tie-out references
B10: Live Excel formula (white) | C10: Everything derivable is a formula - trace with Excel's formula auditing tools
B11: PASS / REVIEW check cell | C11: Excel-vs-engine tie-out at stated tolerances
B13: Contents
B14: Executive Summary | C14: Headline KPIs for both counterparties
B15: Assumptions | C15: Every case input & contract term with unit, source and named cell
B16: Model Basis | C16: Methodology, settlement math, simplifications register
B17: Pro Forma (Audit) | C17: Full cash flow rebuilt with live formulas + engine tie-out
B18: FX Sensitivity | C18: USD returns under VND depreciation (editable)
B19: Buyer Analysis | C19: Offtaker savings vs business-as-usual
B20: Developer Returns | C20: Sources & uses, coverage, equity cash flow
B21: Technical Results | C21: System sizing, year-1 energy balance, bill comparison
B22: Dispatch Profile | C22: 8760-h dispatch incl. original PV generation; chart shows the peak-load week
B23: Load Duration | C23: Load and net-load duration curves
B24: Year 1 BAU vs DPPA | C24: Side-by-side year-1 buyer/seller position
B25: Monthly / Hourly Settlement | C25: ND57 fee chain, VND-native (full configuration on Assumptions)
B27: Prepared for investment and lending review. Figures are model outputs, not offers; REopt sizing is optimizer output and may shift with solver versions.
B28: Regenerate offline anytime: python -m proforma_vietnam.rebuild_report --case-dir <case>.

Sheet Executive Summary
B1: Investment & PPA Negotiation Summary - Vietnam ESCO / DPPA Case
B2: Grid-connected DPPA with CfD (ND57/2025) · prepared 2026-09-13 · REopt dispatch + proforma_vietnam financial model
B4: Project & System
B5: PV Size (kW) | C5: 2829.159
B6: Battery Power (kW) | C6: 306.08
B7: Battery Energy (kWh) | C7: 1450.72
B8: Total Investment (USD) | C8: 1556569.1
B10: Contract Terms
B11: CfD Strike Price (VND/kWh) | C11: 2000
B12: CfD Strike Escalation (per year) | C12: 0.04
B13: Annual Contract Volume (kWh) | C13: 7664883.2
B14: Transmission Loss Factor k | C14: 1.026
B15: Distribution Loss Factor K_pp | C15: 1.027263
B16: DPPA Service Fee (VND/kWh) | C16: 360
B17: Settlement Adder C_CL (VND/kWh) | C17: 163.3
B18: Analysis Period (Years) | C18: 20
B20: Developer (Seller) Returns
B21: Equity IRR | C21: 0.28385393
B22: Project IRR | C22: 0.18337348
B23: NPV (USD) | C23: 1137682.3 | D23: At owner discount rate
B24: Minimum DSCR (debt years) | C24: 0.91308881 | D24: Lender covenant view
B25: Average DSCR | C25: 1.7116866
B26: Simple Payback (Years) | C26: 4.1772135
B27: Equity Investment (USD) | C27: 466970.74
B28: Debt Principal (USD) | C28: 1089598.4
B30: Buyer (Offtaker) Outcome
B31: Year 1 BAU Cost (USD) | C31: 731030.93
B32: Year 1 Cost With Project (USD) | C32: 805683.4
B33: Year 1 Buyer Savings (USD) | C33: -74652.466
B34: Year 1 Savings (% of BAU) | C34: -0.10211944
B35: First 10 Years Buyer Savings (USD) | C35: -898833.73 | D35: Cumulative, years 1-10
B36: First 10 Years Savings (% of BAU) | C36: -0.10240977
B37: Lifetime Buyer Savings (USD) | C37: -2236896.5 | D37: Sum over analysis period
B38: Lifetime Savings (% of BAU) | C38: -0.10275748
B40: Model Basis & Conventions
B41: • Buyer settlement quantity Q_Khc = min(hourly load, loss-adjusted generation Q_adj); excess generation is sold by the generator at FMP and never billed to the buyer.
B42: • PV degradation, O&M escalation and battery replacement (REopt schedule) are applied across the analysis period.
B43: • PV straight-line depreciation over 20 years (Circular 45/2013/TT-BTC permits 7-20 years for generating equipment).
B44: • Vietnam CIT: 4-year exemption + 9-year 50% reduction from first profitable year; 5-year tax-loss carryforward.
B45: • All USD figures at the fixed contract exchange rate (see Assumptions); FX drift between VND revenue and USD reporting is quantified on the FX Sensitivity sheet.

Sheet Assumptions
B1: Assumptions & Model Inputs
B2: Shaded cells are hardcoded inputs (case file or engine output); named cells drive every formula on the Pro Forma (Audit) sheet.
B4: Project & Run
B5: Case name | C5: Vietnam case | E5: case.json
B6: Financing structure | C6: Grid DPPA with CfD (ND57/2025) | E6: proforma_vietnam.structures
B7: REopt run UUID | C7: 51114e02-ba05-4c15-a826-c4078ec7034a | E7: REopt API
B8: Report prepared | C8: 2026-09-13
B9: Analysis period | C9: 20 | D9: years | E9: proforma_vietnam.defaults replacement policy (PROJECT_YEARS) unless case.json financial.analysis_years overrides
B10: Currency & FX
B11: Model currency | C11: USD | E11: EVN tariff converted VND→USD before REopt; see Model Basis
B12: Contract exchange rate | C12: 26300 | D12: VND per USD | E12: case.json tariff.exchange_rate_vnd_per_usd
B13: FX treatment | C13: Held flat over the analysis period | E13: Simplification - see FX Sensitivity sheet
B14: Capital Costs
B15: PV capex | C15: 1357996.3 | D15: USD | E15: REopt PV size_kw × installed_cost_per_kw
B16: BESS capex | C16: 198572.8 | D16: USD | E16: REopt ElectricStorage initial_capital_cost
B17: Other capex | C17: 0 | D17: USD | E17: case.json (developer overrides)
B18: Total investment | C18: =PV_CAPEX+BESS_CAPEX+OTHER_CAPEX | D18: USD | E18: Formula: PV + BESS + Other
B19: Operating Costs
B20: Year-1 O&M | C20: 18960.679 | D20: USD/yr | E20: REopt Financial.year_one_om_costs_before_tax
B21: O&M escalation | C21: 0.03 | D21: per year | E21: vietnam_defaults.json / case.json financial.om_escalation_rate
B22: Replacement Policy
B23: BESS replacement year (storage inverter and pack together) | C23: 10 | D23: year | E23: proforma_vietnam.defaults replacement policy unless case.json technologies.storage overrides
B24: BESS replacement cost per kW | D24: USD/kW | E24: proforma_vietnam.defaults replacement policy unless case.json technologies.storage overrides (sent to REopt)
B25: BESS replacement cost per kWh | D25: USD/kWh | E25: proforma_vietnam.defaults replacement policy unless case.json technologies.storage overrides (sent to REopt)
B26: PV inverter replacement year | C26: 11 | D26: year | E26: proforma_vietnam.defaults replacement policy
B27: PV inverter replacement fraction of PV capex | C27: 0.1 | D27: fraction | E27: proforma_vietnam.defaults replacement policy
B28: PV inverter replacement cost | C28: 135799.63 | D28: USD | E28: Engine: fraction x solved PV capex (none booked when the run has no PV)
B29: Tariff & Escalation
B30: EVN energy escalation | C30: 0.04 | D30: per year | E30: case.json tariff.evn_energy_escalation_rate
B31: EVN capacity (demand) escalation | C31: 0.04 | D31: per year | E31: case.json tariff.evn_capacity_escalation_rate
B32: PV degradation | C32: 0.005 | D32: per year | E32: REopt PV.degradation_fraction
B33: Contract Terms
B34: ESCO energy price (fraction of EVN tariff) | C34: 0.9 | D34: fraction | E34: case.json esco_contract.esco_energy_discount_fraction
B35: Demand savings share to ESCO | C35: 0.8 | D35: fraction | E35: case.json esco_contract.demand_savings_esco_share
B36: Grid charging enabled | C36: FALSE | D36: yes/no | E36: case.json esco_contract.grid_charging_enabled
B37: CfD strike price | C37: 2000 | D37: VND/kWh | E37: case.json dppa.cfd_strike_per_kwh_vnd
B38: CfD strike escalation | C38: 0.04 | D38: per year | E38: case.json dppa.cfd_strike_escalation_rate
B39: DPPA fee / FMP escalation | C39: 0.04 | D39: per year | E39: case.json dppa.fee_escalation_rate
B40: Annual CfD contract volume | C40: 7664883.2 | D40: kWh/yr | E40: case.json dppa.cfd_contract_volume_kwh_per_hour
B41: Transmission loss factor k (price-only) | C41: 1.026 | D41: ratio | E41: ND57; CFMP = FMP × k
B42: Distribution loss factor K_pp | C42: 1.027263 | D42: ratio | E42: ND57 by voltage; Q_adj = Q_meter / K_pp
B43: DPPA system service fee | C43: 360 | D43: VND/kWh | E43: 2025 EVN published fee
B44: Settlement adder C_CL | C44: 163.3 | D44: VND/kWh | E44: 2025 EVN published adder
B45: Allocation fraction δ | C45: 1 | D45: fraction | E45: case.json dppa.allocation_fraction_delta
B46: FMP / CFMP price series | C46: DPPA DOC/fmp_cfmp_vn.json | E46: case.json dppa.fmp_series_path (8760-hour VND/kWh)
B47: Financing
B48: Debt fraction | C48: 0.7 | D48: of total capex | E48: vietnam_defaults.json / case.json financial.debt_fraction
B49: Debt interest rate | C49: 0.085 | D49: per year | E49: vietnam_defaults.json / case.json financial.debt_interest_rate_fraction
B50: Debt term | C50: 10 | D50: years | E50: vietnam_defaults.json / case.json financial.debt_term_years
B51: Debt principal | C51: =TOTAL_CAPEX*DEBT_FRACTION | D51: USD | E51: Formula: total investment × debt fraction
B52: Equity investment | C52: =TOTAL_CAPEX-DEBT_PRINCIPAL | D52: USD | E52: Formula: total investment − debt
B53: Annual debt payment (level) | C53: =IF(OR(DEBT_PRINCIPAL<=0,DEBT_TERM_YEARS<=0),0,IF(DEBT_RATE=0,DEBT_PRINCIPAL/DEBT_TERM_YEARS,DEBT_PRINCIPAL*(DEBT_RATE*(1+DEBT_RATE)^DEBT_TERM_YEARS)/((1+DEBT_RATE)^DEBT_TERM_YEARS-1))) | D53: USD/yr | E53: Standard annuity over the debt term
B54: Owner discount rate | C54: 0.1 | D54: per year | E54: case.json financial.owner_discount_rate_fraction
B55: Tax & Depreciation (Vietnam)
B56: CIT regime | C56: RE producer - Law 67/2025 preferential (10% / 15y) | E56: proforma_vietnam.cash_flow (structure-dependent; explicit override wins)
B57: CIT standard rate | C57: 0.2 | D57: of taxable income | E57: Law 67/2025/QH15; vietnam_defaults.json
B58: CIT preferential rate (RE producer) | C58: 0.1 | D58: of taxable income | E58: Law 67/2025/QH15 + Decree 320/2025/NĐ-CP (first-15-year window)
B59: CIT preferential-rate period | C59: 15 | D59: years (from year 1) | E59: Law 67/2025/QH15
B60: CIT holiday | C60: 4 | D60: years | E60: Law 67/2025 (from first profitable year); Circular 78/2014 Art. 18 shape
B61: CIT reduced-rate period | C61: 9 | D61: years | E61: Law 67/2025; Circular 78/2014 Art. 18 shape
B62: CIT reduction during period | C62: 0.5 | D62: of applicable base rate | E62: Law 67/2025 (50% of base rate)
B63: Tax-loss carryforward limit | C63: 5 | D63: years | E63: Law 67/2025; Circular 78/2014 Art. 9 shape
B64: Incentive clock cap | C64: 4 | D64: year (latest start) | E64: Law 67/2025; Circular 78/2014 Art. 18 shape
B65: PV depreciation (straight-line) | C65: 20 | D65: years | E65: Circular 45/2013/TT-BTC (7–20 yr band)
B66: BESS depreciation (straight-line) | C66: 8 | D66: years | E66: Circular 45/2013/TT-BTC
B67: Year-1 Engine Outputs (hardcoded - dispatch × tariff, not derivable in-sheet)
B68: Year-1 BAU EVN bill | C68: 731030.93 | D68: USD | E68: REopt ElectricTariff.year_one_bill_before_tax_bau
B69: Year-1 optimized EVN bill | C69: 473979.31 | D69: USD | E69: REopt ElectricTariff.year_one_bill_before_tax
B70: Year-1 BAU demand charge | C70: 0 | D70: USD | E70: REopt year_one_demand_cost_before_tax_bau
B71: Year-1 optimized demand charge | C71: 0 | D71: USD | E71: REopt year_one_demand_cost_before_tax
B72: Year-1 demand savings base | C72: 0 | D72: USD | E72: max(BAU − optimized demand charge, 0)
B73: Year-1 served-energy retail value | C73: 257051.65 | D73: USD | E73: Σ project-served kWh × EVN TOU rate (8760 h)
B74: Year-1 C_DN (spot energy) | C74: 174753.55 | D74: USD | E74: settle_dppa_year_one: Σ Q_Khc × CFMP × K_pp
B75: Year-1 C_DPPA (system fee) | C75: 45048.7 | D75: USD | E75: Σ Q_Khc × f_dppa
B76: Year-1 C_CL (settlement adder) | C76: 20434.591 | D76: USD | E76: Σ Q_Khc × f_cl
B77: Year-1 C_BL (retail shortfall) | C77: 481870.22 | D77: USD | E77: Σ shortfall × EVN TOU rate
B78: Year-1 CfD strike leg | C78: 247489.13 | D78: USD | E78: Σ P_c × min(Q_c, Q_Khc)
B79: Year-1 CfD market offset | C79: 163912.79 | D79: USD | E79: Σ FMP × min(Q_c, Q_Khc)
... B81: Year-1 matched-energy retail value | C81: 249160.7 | D81: USD | E81: Σ Q_Khc × EVN TOU rate (degradation repurchase)

Sheet Model Basis
B1: Model Basis, Conventions & Simplifications
B3: 1. Model architecture
B4: • REopt (NLR optimization engine) selects PV/BESS sizing and hourly dispatch against the EVN time-of-use tariff over an 8760-hour year.
B5: • proforma_vietnam post-processes the REopt run: an hourly ND57/2025 DPPA settlement layer (when applicable) and a 20-year developer cash flow with Vietnam tax and debt.
B6: • This workbook is generated from that engine. The Pro Forma (Audit) sheet re-derives the full cash flow with live Excel formulas from the named inputs on the Assumptions sheet; the Checks block ties every metric back to the engine (PASS/REVIEW).
B8: 2. Currency & FX
B9: • All money flows are computed in USD at the fixed contract rate (26,300 VND/USD).
B10: • Underlying revenue is VND-denominated (EVN tariff, FMP market, DPPA fees). Holding FX flat for the analysis period is a simplification: the FX Sensitivity sheet quantifies USD-reported returns under 0-3%/yr VND depreciation.
B11: • Sheets that show VND amounts (Hourly/Monthly Settlement, DPPA fee inputs) are VND-native regulatory quantities, not conversions.
B12: • Debt is assumed VND-denominated (local bank), so DSCR is FX-neutral.
B14: 3. Settlement math - ND57/2025 grid DPPA with CfD
B15: • Q_adj[h] = Q_re_meter[h] / K_pp × delta - quantity conversion generator→customer uses K_pp only (CD7 Ví dụ 1); k is price-only.
... B50: • EVN retail tariff (current & QĐ963 TOU structures) as configured in the case file.

Sheet Pro Forma (Audit)
A1: Pro Forma (Audit) - every white cell is a live Excel formula
A2: Shaded cells are hardcoded engine outputs (REopt dispatch / 8760-h settlement / tie-out reference). All other cells derive from the named cells on the Assumptions sheet. Currency: USD at the fixed contract FX rate.
A4: TIMELINE & INDEXATION
A5: Year | B5: index | C5: 0 | D5: 1 | E5: 2 | F5: 3 | G5: 4 | H5: 5 | I5: 6 | J5: 7 | K5: 8 | L5: 9 | M5: 10 | N5: 11 | O5: 12 | P5: 13 | Q5: 14 | R5: 15 | S5: 16 | T5: 17 | U5: 18 | V5: 19 | W5: 20
A6: EVN energy escalation factor | B6: index | D6: =(1+ESC_ENERGY)^(D$5-1) | E6: =(1+ESC_ENERGY)^(E$5-1) | F6: =(1+ESC_ENERGY)^(F$5-1) | G6: =(1+ESC_ENERGY)^(G$5-1) | H6: =(1+ESC_ENERGY)^(H$5-1) | I6: =(1+ESC_ENERGY)^(I$5-1) | J6: =(1+ESC_ENERGY)^(J$5-1) | K6: =(1+ESC_ENERGY)^(K$5-1) | ... W6: =(1+ESC_ENERGY)^(W$5-1)
A7: EVN capacity escalation factor | B7: index | D7: =(1+ESC_CAPACITY)^(D$5-1) | E7: =(1+ESC_CAPACITY)^(E$5-1) | F7: =(1+ESC_CAPACITY)^(F$5-1) | G7: =(1+ESC_CAPACITY)^(G$5-1) | H7: =(1+ESC_CAPACITY)^(H$5-1) | I7: =(1+ESC_CAPACITY)^(I$5-1) | J7: =(1+ESC_CAPACITY)^(J$5-1) | K7: =(1+ESC_CAPACITY)^(K$5-1) | ... W7: =(1+ESC_CAPACITY)^(W$5-1)
A8: O&M escalation factor | B8: index | D8: =(1+ESC_OM)^(D$5-1) | E8: =(1+ESC_OM)^(E$5-1) | F8: =(1+ESC_OM)^(F$5-1) | G8: =(1+ESC_OM)^(G$5-1) | H8: =(1+ESC_OM)^(H$5-1) | I8: =(1+ESC_OM)^(I$5-1) | J8: =(1+ESC_OM)^(J$5-1) | K8: =(1+ESC_OM)^(K$5-1) | ... W8: =(1+ESC_OM)^(W$5-1)
A9: PV degradation factor | B9: index | D9: =(1-PV_DEGRADATION)^(D$5-1) | E9: =(1-PV_DEGRADATION)^(E$5-1) | F9: =(1-PV_DEGRADATION)^(F$5-1) | G9: =(1-PV_DEGRADATION)^(G$5-1) | H9: =(1-PV_DEGRADATION)^(H$5-1) | I9: =(1-PV_DEGRADATION)^(I$5-1) | J9: =(1-PV_DEGRADATION)^(J$5-1) | K9: =(1-PV_DEGRADATION)^(K$5-1) | ... W9: =(1-PV_DEGRADATION)^(W$5-1)
A10: DPPA fee / FMP escalation factor | B10: index | D10: =(1+ESC_FEE)^(D$5-1) | E10: =(1+ESC_FEE)^(E$5-1) | F10: =(1+ESC_FEE)^(F$5-1) | G10: =(1+ESC_FEE)^(G$5-1) | H10: =(1+ESC_FEE)^(H$5-1) | I10: =(1+ESC_FEE)^(I$5-1) | J10: =(1+ESC_FEE)^(J$5-1) | K10: =(1+ESC_FEE)^(K$5-1) | ... W10: =(1+ESC_FEE)^(W$5-1)
A11: CfD strike escalation factor | B11: index | D11: =(1+ESC_STRIKE)^(D$5-1) | E11: =(1+ESC_STRIKE)^(E$5-1) | F11: =(1+ESC_STRIKE)^(F$5-1) | G11: =(1+ESC_STRIKE)^(G$5-1) | H11: =(1+ESC_STRIKE)^(H$5-1) | I11: =(1+ESC_STRIKE)^(I$5-1) | J11: =(1+ESC_STRIKE)^(J$5-1) | K11: =(1+ESC_STRIKE)^(K$5-1) | ... W11: =(1+ESC_STRIKE)^(W$5-1)
A13: REVENUE (USD)
A14: Generator FMP market revenue | B14: USD | D14: =DPPA_FMP_REV_Y1*D10*D9 | E14: =DPPA_FMP_REV_Y1*E10*E9 | F14: =DPPA_FMP_REV_Y1*F10*F9 | G14: =DPPA_FMP_REV_Y1*G10*G9 | H14: =DPPA_FMP_REV_Y1*H10*H9 | I14: =DPPA_FMP_REV_Y1*I10*I9 | J14: =DPPA_FMP_REV_Y1*J10*J9 | K14: =DPPA_FMP_REV_Y1*K10*K9 | ... W14: =DPPA_FMP_REV_Y1*W10*W9
A15: CfD strike leg (P_c × Q_cfd) | B15: USD | D15: =DPPA_CFD_STRIKE_Y1*D11 | E15: =DPPA_CFD_STRIKE_Y1*E11 | F15: =DPPA_CFD_STRIKE_Y1*F11 | G15: =DPPA_CFD_STRIKE_Y1*G11 | H15: =DPPA_CFD_STRIKE_Y1*H11 | I15: =DPPA_CFD_STRIKE_Y1*I11 | J15: =DPPA_CFD_STRIKE_Y1*J11 | K15: =DPPA_CFD_STRIKE_Y1*K11 | ... W15: =DPPA_CFD_STRIKE_Y1*W11
A16: CfD market offset (FMP × Q_cfd) | B16: USD | D16: =DPPA_CFD_OFFSET_Y1*D10 | E16: =DPPA_CFD_OFFSET_Y1*E10 | F16: =DPPA_CFD_OFFSET_Y1*F10 | G16: =DPPA_CFD_OFFSET_Y1*G10 | H16: =DPPA_CFD_OFFSET_Y1*H10 | I16: =DPPA_CFD_OFFSET_Y1*I10 | J16: =DPPA_CFD_OFFSET_Y1*J10 | K16: =DPPA_CFD_OFFSET_Y1*K10 | ... W16: =DPPA_CFD_OFFSET_Y1*W10
A17: CfD net settlement (to generator) | B17: USD | D17: =D15-D16 | E17: =E15-E16 | F17: =F15-F16 | G17: =G15-G16 | H17: =H15-H16 | I17: =I15-I16 | J17: =J15-J16 | K17: =K15-K16 | ... W17: =W15-W16
A18: Generator revenue (FMP + CfD net) | B18: USD | D18: =D14+D17 | E18: =E14+E17 | F18: =F14+F17 | G18: =G14+G17 | H18: =H14+H17 | I18: =I14+I17 | J18: =J14+J17 | K18: =K14+K17 | ... W18: =W14+W17
A19: Demand charge savings (total) | B19: USD | D19: =BASE_DEMAND_SAVINGS*D7 | E19: =BASE_DEMAND_SAVINGS*E7 | F19: =BASE_DEMAND_SAVINGS*F7 | G19: =BASE_DEMAND_SAVINGS*G7 | H19: =BASE_DEMAND_SAVINGS*H7 | I19: =BASE_DEMAND_SAVINGS*I7 | J19: =BASE_DEMAND_SAVINGS*J7 | K19: =BASE_DEMAND_SAVINGS*K7 | ... W19: =BASE_DEMAND_SAVINGS*W7
A20: ESCO share of demand savings | B20: USD | D20: =D19*DEMAND_SHARE | E20: =E19*DEMAND_SHARE | F20: =F19*DEMAND_SHARE | G20: =G19*DEMAND_SHARE | H20: =H19*DEMAND_SHARE | I20: =I19*DEMAND_SHARE | J20: =J19*DEMAND_SHARE | K20: =K19*DEMAND_SHARE | ... W20: =W19*DEMAND_SHARE
A21: Total developer revenue | B21: USD | D21: =D18+D20 | E21: =E18+E20 | F21: =F18+F20 | G21: =G18+G20 | H21: =H18+H20 | I21: =I18+I20 | J21: =J18+J20 | K21: =K18+K20 | ... W21: =W18+W20
A23: OPERATING COSTS (USD)
A24: O&M | B24: USD | D24: =OM_YEAR1*D8 | E24: =OM_YEAR1*E8 | F24: =OM_YEAR1*F8 | G24: =OM_YEAR1*G8 | H24: =OM_YEAR1*H8 | I24: =OM_YEAR1*I8 | J24: =OM_YEAR1*J8 | K24: =OM_YEAR1*K8 | ... W24: =OM_YEAR1*W8
A25: Equipment replacement (engine schedule) | B25: USD | D25: 0 | E25: 0 | F25: 0 | G25: 0 | H25: 0 | I25: 0 | J25: 0 | K25: 0 | L25: 0 | M25: 198572.8 | N25: 135799.63 | O25: 0 | P25: 0 | Q25: 0 | R25: 0 | S25: 0 | T25: 0 | U25: 0 | V25: 0 | W25: 0
A26: EBITDA | B26: USD | D26: =D21-D24-D25 | E26: =E21-E24-E25 | F26: =F21-F24-F25 | G26: =G21-G24-G25 | H26: =H21-H24-H25 | I26: =I21-I24-I25 | J26: =J21-J24-J25 | K26: =K21-K24-K25 | ... W26: =W21-W24-W25
A28: DEBT SCHEDULE (USD)
A29: Opening debt balance | B29: USD | D29: =DEBT_PRINCIPAL | E29: =D33 | F29: =E33 | G29: =F33 | H29: =G33 | I29: =H33 | J29: =I33 | K29: =J33 | L29: =K33 | ... W29: =V33
A30: Interest | B30: USD | D30: =IF(D$5<=DEBT_TERM_YEARS,D29*DEBT_RATE,0) | E30: =IF(E$5<=DEBT_TERM_YEARS,E29*DEBT_RATE,0) | F30: =IF(F$5<=DEBT_TERM_YEARS,F29*DEBT_RATE,0) | G30: =IF(G$5<=DEBT_TERM_YEARS,G29*DEBT_RATE,0) | H30: =IF(H$5<=DEBT_TERM_YEARS,H29*DEBT_RATE,0) | I30: =IF(I$5<=DEBT_TERM_YEARS,I29*DEBT_RATE,0) | J30: =IF(J$5<=DEBT_TERM_YEARS,J29*DEBT_RATE,0) | K30: =IF(K$5<=DEBT_TERM_YEARS,K29*DEBT_RATE,0) | ... W30: =IF(W$5<=DEBT_TERM_YEARS,W29*DEBT_RATE,0)
A31: Principal repayment | B31: USD | D31: =IF(D$5<=DEBT_TERM_YEARS,MIN(MAX(DEBT_PAYMENT-D30,0),D29),0) | E31: =IF(E$5<=DEBT_TERM_YEARS,MIN(MAX(DEBT_PAYMENT-E30,0),E29),0) | F31: =IF(F$5<=DEBT_TERM_YEARS,MIN(MAX(DEBT_PAYMENT-F30,0),F29),0) | G31: =IF(G$5<=DEBT_TERM_YEARS,MIN(MAX(DEBT_PAYMENT-G30,0),G29),0) | H31: =IF(H$5<=DEBT_TERM_YEARS,MIN(MAX(DEBT_PAYMENT-H30,0),H29),0) | I31: =IF(I$5<=DEBT_TERM_YEARS,MIN(MAX(DEBT_PAYMENT-I30,0),I29),0) | J31: =IF(J$5<=DEBT_TERM_YEARS,MIN(MAX(DEBT_PAYMENT-J30,0),J29),0) | K31: =IF(K$5<=DEBT_TERM_YEARS,MIN(MAX(DEBT_PAYMENT-K30,0),K29),0) | ... W31: =IF(W$5<=DEBT_TERM_YEARS,MIN(MAX(DEBT_PAYMENT-W30,0),W29),0)
A32: Debt service | B32: USD | D32: =D30+D31 | E32: =E30+E31 | F32: =F30+F31 | G32: =G30+G31 | H32: =H30+H31 | I32: =I30+I31 | J32: =J30+J31 | K32: =K30+K31 | ... W32: =W30+W31
A33: Closing debt balance | B33: USD | D33: =D29-D31 | E33: =E29-E31 | F33: =F29-F31 | G33: =G29-G31 | H33: =H29-H31 | I33: =I29-I31 | J33: =J29-J31 | K33: =K29-K31 | ... W33: =W29-W31
A35: DEPRECIATION & VIETNAM CIT (USD)
A36: PV depreciation (straight-line) | B36: USD | D36: =IF(D$5<=PV_DEP_YEARS,PV_CAPEX/PV_DEP_YEARS,0) | E36: =IF(E$5<=PV_DEP_YEARS,PV_CAPEX/PV_DEP_YEARS,0) | F36: =IF(F$5<=PV_DEP_YEARS,PV_CAPEX/PV_DEP_YEARS,0) | G36: =IF(G$5<=PV_DEP_YEARS,PV_CAPEX/PV_DEP_YEARS,0) | H36: =IF(H$5<=PV_DEP_YEARS,PV_CAPEX/PV_DEP_YEARS,0) | I36: =IF(I$5<=PV_DEP_YEARS,PV_CAPEX/PV_DEP_YEARS,0) | J36: =IF(J$5<=PV_DEP_YEARS,PV_CAPEX/PV_DEP_YEARS,0) | K36: =IF(K$5<=PV_DEP_YEARS,PV_CAPEX/PV_DEP_YEARS,0) | ... W36: =IF(W$5<=PV_DEP_YEARS,PV_CAPEX/PV_DEP_YEARS,0)
A37: BESS depreciation (straight-line) | B37: USD | D37: =IF(D$5<=BESS_DEP_YEARS,BESS_CAPEX/BESS_DEP_YEARS,0) | E37: =IF(E$5<=BESS_DEP_YEARS,BESS_CAPEX/BESS_DEP_YEARS,0) | F37: =IF(F$5<=BESS_DEP_YEARS,BESS_CAPEX/BESS_DEP_YEARS,0) | G37: =IF(G$5<=BESS_DEP_YEARS,BESS_CAPEX/BESS_DEP_YEARS,0) | H37: =IF(H$5<=BESS_DEP_YEARS,BESS_CAPEX/BESS_DEP_YEARS,0) | I37: =IF(I$5<=BESS_DEP_YEARS,BESS_CAPEX/BESS_DEP_YEARS,0) | J37: =IF(J$5<=BESS_DEP_YEARS,BESS_CAPEX/BESS_DEP_YEARS,0) | K37: =IF(K$5<=BESS_DEP_YEARS,BESS_CAPEX/BESS_DEP_YEARS,0) | ... W37: =IF(W$5<=BESS_DEP_YEARS,BESS_CAPEX/BESS_DEP_YEARS,0)
A38: Replacement depreciation (in-service yr 10) | B38: USD | D38: =IF(AND(D$5>=10,D$5<=10+BESS_DEP_YEARS-1),$M$25/BESS_DEP_YEARS,0) | E38: =IF(AND(E$5>=10,E$5<=10+BESS_DEP_YEARS-1),$M$25/BESS_DEP_YEARS,0) | F38: =IF(AND(F$5>=10,F$5<=10+BESS_DEP_YEARS-1),$M$25/BESS_DEP_YEARS,0) | G38: =IF(AND(G$5>=10,G$5<=10+BESS_DEP_YEARS-1),$M$25/BESS_DEP_YEARS,0) | H38: =IF(AND(H$5>=10,H$5<=10+BESS_DEP_YEARS-1),$M$25/BESS_DEP_YEARS,0) | I38: =IF(AND(I$5>=10,I$5<=10+BESS_DEP_YEARS-1),$M$25/BESS_DEP_YEARS,0) | J38: =IF(AND(J$5>=10,J$5<=10+BESS_DEP_YEARS-1),$M$25/BESS_DEP_YEARS,0) | K38: =IF(AND(K$5>=10,K$5<=10+BESS_DEP_YEARS-1),$M$25/BESS_DEP_YEARS,0) | ... W38: =IF(AND(W$5>=10,W$5<=10+BESS_DEP_YEARS-1),$M$25/BESS_DEP_YEARS,0)
A39: Replacement depreciation (in-service yr 11) | B39: USD | D39: =IF(AND(D$5>=11,D$5<=11+BESS_DEP_YEARS-1),$N$25/BESS_DEP_YEARS,0) | E39: =IF(AND(E$5>=11,E$5<=11+BESS_DEP_YEARS-1),$N$25/BESS_DEP_YEARS,0) | F39: =IF(AND(F$5>=11,F$5<=11+BESS_DEP_YEARS-1),$N$25/BESS_DEP_YEARS,0) | G39: =IF(AND(G$5>=11,G$5<=11+BESS_DEP_YEARS-1),$N$25/BESS_DEP_YEARS,0) | H39: =IF(AND(H$5>=11,H$5<=11+BESS_DEP_YEARS-1),$N$25/BESS_DEP_YEARS,0) | I39: =IF(AND(I$5>=11,I$5<=11+BESS_DEP_YEARS-1),$N$25/BESS_DEP_YEARS,0) | J39: =IF(AND(J$5>=11,J$5<=11+BESS_DEP_YEARS-1),$N$25/BESS_DEP_YEARS,0) | K39: =IF(AND(K$5>=11,K$5<=11+BESS_DEP_YEARS-1),$N$25/BESS_DEP_YEARS,0) | ... W39: =IF(AND(W$5>=11,W$5<=11+BESS_DEP_YEARS-1),$N$25/BESS_DEP_YEARS,0)
A40: Total depreciation | B40: USD | D40: =D36+D37+D38+D39 | E40: =E36+E37+E38+E39 | F40: =F36+F37+F38+F39 | G40: =G36+G37+G38+G39 | H40: =H36+H37+H38+H39 | I40: =I36+I37+I38+I39 | J40: =J36+J37+J38+J39 | K40: =K36+K37+K38+K39 | ... W40: =W36+W37+W38+W39
A41: Taxable income before loss relief (EBT) | B41: USD | D41: =D26+D25-D40-D30 | E41: =E26+E25-E40-E30 | F41: =F26+F25-F40-F30 | G41: =G26+G25-G40-G30 | H41: =H26+H25-H40-H30 | I41: =I26+I25-I40-I30 | J41: =J26+J25-J40-J30 | K41: =K26+K25-K40-K30 | ... W41: =W26+W25-W40-W30
A42: New tax loss arising | B42: USD | D42: =MAX(-D41,0) | E42: =MAX(-E41,0) | F42: =MAX(-F41,0) | G42: =MAX(-G41,0) | H42: =MAX(-H41,0) | I42: =MAX(-I41,0) | J42: =MAX(-J41,0) | K42: =MAX(-K41,0) | ... W42: =MAX(-W41,0)
A43: Assessable income (pre-relief) | B43: USD | D43: =MAX(D41,0) | E43: =MAX(E41,0) | F43: =MAX(F41,0) | G43: =MAX(G41,0) | H43: =MAX(H41,0) | I43: =MAX(I41,0) | J43: =MAX(J41,0) | K43: =MAX(K41,0) | ... W43: =MAX(W41,0)
A44: Loss vintage aged 1y - available | B44: USD | D44: 0 | E44: =D42 | F44: =E42 | G44: =F42 | H44: =G42 | I44: =H42 | J44: =I42 | K44: =J42 | L44: =K42 | ... W44: =V42
A45: Loss vintage aged 2y - available | B45: USD | D45: 0 | E45: =MAX(D44-D53,0) | F45: =MAX(E44-E53,0) | G45: =MAX(F44-F53,0) | H45: =MAX(G44-G53,0) | I45: =MAX(H44-H53,0) | J45: =MAX(I44-I53,0) | K45: =MAX(J44-J53,0) | L45: =MAX(K44-K53,0) | ... W45: =MAX(V44-V53,0)
A46: Loss vintage aged 3y - available | B46: USD | D46: 0 | E46: =MAX(D45-D52,0) | F46: =MAX(E45-E52,0) | G46: =MAX(F45-F52,0) | H46: =MAX(G45-G52,0) | I46: =MAX(H45-H52,0) | J46: =MAX(I45-I52,0) | K46: =MAX(J45-J52,0) | L46: =MAX(K45-K52,0) | ... W46: =MAX(V45-V52,0)
A47: Loss vintage aged 4y - available | B47: USD | D47: 0 | E47: =MAX(D46-D51,0) | F47: =MAX(E46-E51,0) | G47: =MAX(F46-F51,0) | H47: =MAX(G46-G51,0) | I47: =MAX(H46-H51,0) | J47: =MAX(I46-I51,0) | K47: =MAX(J46-J51,0) | L47: =MAX(K46-K51,0) | ... W47: =MAX(V46-V51,0)
A48: Loss vintage aged 5y - available | B48: USD | D48: 0 | E48: =MAX(D47-D50,0) | F48: =MAX(E47-E50,0) | G48: =MAX(F47-F50,0) | H48: =MAX(G47-G50,0) | I48: =MAX(H47-H50,0) | J48: =MAX(I47-I50,0) | K48: =MAX(J47-J50,0) | L48: =MAX(K47-K50,0) | ... W48: =MAX(V47-V50,0)
A49: Loss vintage aged 5y - utilised | B49: USD | D49: =MIN(D48,MAX(D43,0)) | E49: =MIN(E48,MAX(E43,0)) | F49: =MIN(F48,MAX(F43,0)) | G49: =MIN(G48,MAX(G43,0)) | H49: =MIN(H48,MAX(H43,0)) | I49: =MIN(I48,MAX(I43,0)) | J49: =MIN(J48,MAX(J43,0)) | K49: =MIN(K48,MAX(K43,0)) | ... W49: =MIN(W48,MAX(W43,0))
A50: Loss vintage aged 4y - utilised | B50: USD | D50: =MIN(D47,MAX(D43-D49,0)) | E50: =MIN(E47,MAX(E43-E49,0)) | F50: =MIN(F47,MAX(F43-F49,0)) | G50: =MIN(G47,MAX(G43-G49,0)) | H50: =MIN(H47,MAX(H43-H49,0)) | I50: =MIN(I47,MAX(I43-I49,0)) | J50: =MIN(J47,MAX(J43-J49,0)) | K50: =MIN(K47,MAX(K43-K49,0)) | ... W50: =MIN(W47,MAX(W43-W49,0))
A51: Loss vintage aged 3y - utilised | B51: USD | D51: =MIN(D46,MAX(D43-D49-D50,0)) | E51: =MIN(E46,MAX(E43-E49-E50,0)) | F51: =MIN(F46,MAX(F43-F49-F50,0)) | G51: =MIN(G46,MAX(G43-G49-G50,0)) | H51: =MIN(H46,MAX(H43-H49-H50,0)) | I51: =MIN(I46,MAX(I43-I49-I50,0)) | J51: =MIN(J46,MAX(J43-J49-J50,0)) | K51: =MIN(K46,MAX(K43-K49-K50,0)) | ... W51: =MIN(W46,MAX(W43-W49-W50,0))
A52: Loss vintage aged 2y - utilised | B52: USD | D52: =MIN(D45,MAX(D43-D49-D50-D51,0)) | E52: =MIN(E45,MAX(E43-E49-E50-E51,0)) | F52: =MIN(F45,MAX(F43-F49-F50-F51,0)) | G52: =MIN(G45,MAX(G43-G49-G50-G51,0)) | H52: =MIN(H45,MAX(H43-H49-H50-H51,0)) | I52: =MIN(I45,MAX(I43-I49-I50-I51,0)) | J52: =MIN(J45,MAX(J43-J49-J50-J51,0)) | K52: =MIN(K45,MAX(K43-K49-K50-K51,0)) | ... W52: =MIN(W45,MAX(W43-W49-W50-W51,0))
A53: Loss vintage aged 1y - utilised | B53: USD | D53: =MIN(D44,MAX(D43-D49-D50-D51-D52,0)) | E53: =MIN(E44,MAX(E43-E49-E50-E51-E52,0)) | F53: =MIN(F44,MAX(F43-F49-F50-F51-F52,0)) | G53: =MIN(G44,MAX(G43-G49-G50-G51-G52,0)) | H53: =MIN(H44,MAX(H43-H49-H50-H51-H52,0)) | I53: =MIN(I44,MAX(I43-I49-I50-I51-I52,0)) | J53: =MIN(J44,MAX(J43-J49-J50-J51-J52,0)) | K53: =MIN(K44,MAX(K43-K49-K50-K51-K52,0)) | ... W53: =MIN(W44,MAX(W43-W49-W50-W51-W52,0))
A54: Loss relief utilised (FIFO, ≤5y old) | B54: USD | D54: =D49+D50+D51+D52+D53 | E54: =E49+E50+E51+E52+E53 | F54: =F49+F50+F51+F52+F53 | G54: =G49+G50+G51+G52+G53 | H54: =H49+H50+H51+H52+H53 | I54: =I49+I50+I51+I52+I53 | J54: =J49+J50+J51+J52+J53 | K54: =K49+K50+K51+K52+K53 | ... W54: =W49+W50+W51+W52+W53
A55: Taxable income after loss relief | B55: USD | D55: =D43-D54 | E55: =E43-E54 | F55: =F43-F54 | G55: =G43-G54 | H55: =H43-H54 | I55: =I43-I54 | J55: =J43-J54 | K55: =K43-K54 | ... W55: =W43-W54
A56: Profitable-to-date flag (starts CIT clock) | B56: 0/1 | D56: =IF(D41>0,1,0) | E56: =IF(OR(D56=1,E41>0),1,0) | F56: =IF(OR(E56=1,F41>0),1,0) | G56: =IF(OR(F56=1,G41>0),1,0) | H56: =IF(OR(G56=1,H41>0),1,0) | I56: =IF(OR(H56=1,I41>0),1,0) | J56: =IF(OR(I56=1,J41>0),1,0) | K56: =IF(OR(J56=1,K41>0),1,0) | L56: =IF(OR(K56=1,L41>0),1,0) | ... W56: =IF(OR(V56=1,W41>0),1,0)
A57: CIT clock start year (first profit, capped) | C57: =MIN(IFERROR(MATCH(1,D56:W56,0),CIT_CLOCK_CAP_YEAR),CIT_CLOCK_CAP_YEAR) | D57: Circular 78/2014 Art. 18
A58: Applicable base CIT rate (preferential window) | B58: % | D58: =IF(D$5<=CIT_PREF_YEARS,CIT_PREF_RATE,CIT_RATE) | E58: =IF(E$5<=CIT_PREF_YEARS,CIT_PREF_RATE,CIT_RATE) | F58: =IF(F$5<=CIT_PREF_YEARS,CIT_PREF_RATE,CIT_RATE) | G58: =IF(G$5<=CIT_PREF_YEARS,CIT_PREF_RATE,CIT_RATE) | H58: =IF(H$5<=CIT_PREF_YEARS,CIT_PREF_RATE,CIT_RATE) | I58: =IF(I$5<=CIT_PREF_YEARS,CIT_PREF_RATE,CIT_RATE) | J58: =IF(J$5<=CIT_PREF_YEARS,CIT_PREF_RATE,CIT_RATE) | K58: =IF(K$5<=CIT_PREF_YEARS,CIT_PREF_RATE,CIT_RATE) | ... W58: =IF(W$5<=CIT_PREF_YEARS,CIT_PREF_RATE,CIT_RATE)
A59: Applicable CIT rate | B59: % | D59: =IF(D$5<$C$57+CIT_HOLIDAY_YEARS,0,IF(D$5<$C$57+CIT_HOLIDAY_YEARS+CIT_REDUCED_YEARS,D58*CIT_REDUCED_FRACTION,D58)) | E59: =IF(E$5<$C$57+CIT_HOLIDAY_YEARS,0,IF(E$5<$C$57+CIT_HOLIDAY_YEARS+CIT_REDUCED_YEARS,E58*CIT_REDUCED_FRACTION,E58)) | F59: =IF(F$5<$C$57+CIT_HOLIDAY_YEARS,0,IF(F$5<$C$57+CIT_HOLIDAY_YEARS+CIT_REDUCED_YEARS,F58*CIT_REDUCED_FRACTION,F58)) | G59: =IF(G$5<$C$57+CIT_HOLIDAY_YEARS,0,IF(G$5<$C$57+CIT_HOLIDAY_YEARS+CIT_REDUCED_YEARS,G58*CIT_REDUCED_FRACTION,G58)) | H59: =IF(H$5<$C$57+CIT_HOLIDAY_YEARS,0,IF(H$5<$C$57+CIT_HOLIDAY_YEARS+CIT_REDUCED_YEARS,H58*CIT_REDUCED_FRACTION,H58)) | I59: =IF(I$5<$C$57+CIT_HOLIDAY_YEARS,0,IF(I$5<$C$57+CIT_HOLIDAY_YEARS+CIT_REDUCED_YEARS,I58*CIT_REDUCED_FRACTION,I58)) | J59: =IF(J$5<$C$57+CIT_HOLIDAY_YEARS,0,IF(J$5<$C$57+CIT_HOLIDAY_YEARS+CIT_REDUCED_YEARS,J58*CIT_REDUCED_FRACTION,J58)) | K59: =IF(K$5<$C$57+CIT_HOLIDAY_YEARS,0,IF(K$5<$C$57+CIT_HOLIDAY_YEARS+CIT_REDUCED_YEARS,K58*CIT_REDUCED_FRACTION,K58)) | ... W59: =IF(W$5<$C$57+CIT_HOLIDAY_YEARS,0,IF(W$5<$C$57+CIT_HOLIDAY_YEARS+CIT_REDUCED_YEARS,W58*CIT_REDUCED_FRACTION,W58))
A60: CIT payable | B60: USD | D60: =D55*D59 | E60: =E55*E59 | F60: =F55*F59 | G60: =G55*G59 | H60: =H55*H59 | I60: =I55*I59 | J60: =J55*J59 | K60: =K55*K59 | ... W60: =W55*W59
A62: CASH FLOW & COVERAGE (USD)
A63: Cash available for debt service (CFADS) | B63: USD | D63: =D26-D60 | E63: =E26-E60 | F63: =F26-F60 | G63: =G26-G60 | H63: =H26-H60 | I63: =I26-I60 | J63: =J26-J60 | K63: =K26-K60 | ... W63: =W26-W60
A64: Project cash flow (unlevered, post-tax) | B64: USD | C64: =-TOTAL_CAPEX | D64: =D63 | E64: =E63 | F64: =F63 | G64: =G63 | H64: =H63 | I64: =I63 | J64: =J63 | K64: =K63 | ... W64: =W63
A65: Equity cash flow | B65: USD | C65: =-EQUITY_INVESTMENT | D65: =D63-D32 | E65: =E63-E32 | F65: =F63-F32 | G65: =G63-G32 | H65: =H63-H32 | I65: =I63-I32 | J65: =J63-J32 | K65: =K63-K32 | ... W65: =W63-W32
A66: Cumulative equity cash flow | B66: USD | C66: =C65 | D66: =C66+D65 | E66: =D66+E65 | F66: =E66+F65 | G66: =F66+G65 | H66: =G66+H65 | I66: =H66+I65 | J66: =I66+J65 | K66: =J66+K65 | ... W66: =V66+W65
A67: DSCR (debt years) | B67: x | D67: =IF(D32>0,D63/D32,"") | E67: =IF(E32>0,E63/E32,"") | F67: =IF(F32>0,F63/F32,"") | G67: =IF(G32>0,G63/G32,"") | H67: =IF(H32>0,H63/H32,"") | I67: =IF(I32>0,I63/I32,"") | J67: =IF(J32>0,J63/J32,"") | K67: =IF(K32>0,K63/K32,"") | ... W67: =IF(W32>0,W63/W32,"")
A69: OFFTAKER (BUYER) POSITION (USD)
A70: BAU EVN bill (energy + demand) | B70: USD | D70: =BAU_BILL_Y1*D6 | E70: =BAU_BILL_Y1*E6 | F70: =BAU_BILL_Y1*F6 | G70: =BAU_BILL_Y1*G6 | H70: =BAU_BILL_Y1*H6 | I70: =BAU_BILL_Y1*I6 | J70: =BAU_BILL_Y1*J6 | K70: =BAU_BILL_Y1*K6 | ... W70: =BAU_BILL_Y1*W6
A71: C_DN spot energy (Q_Khc × CFMP × K_pp) | B71: USD | D71: =DPPA_C_DN_Y1*D10*D9 | E71: =DPPA_C_DN_Y1*E10*E9 | F71: =DPPA_C_DN_Y1*F10*F9 | G71: =DPPA_C_DN_Y1*G10*G9 | H71: =DPPA_C_DN_Y1*H10*H9 | I71: =DPPA_C_DN_Y1*I10*I9 | J71: =DPPA_C_DN_Y1*J10*J9 | K71: =DPPA_C_DN_Y1*K10*K9 | ... W71: =DPPA_C_DN_Y1*W10*W9
A72: C_DPPA system service fee | B72: USD | D72: =DPPA_C_DPPA_Y1*D10*D9 | E72: =DPPA_C_DPPA_Y1*E10*E9 | F72: =DPPA_C_DPPA_Y1*F10*F9 | G72: =DPPA_C_DPPA_Y1*G10*G9 | H72: =DPPA_C_DPPA_Y1*H10*H9 | I72: =DPPA_C_DPPA_Y1*I10*I9 | J72: =DPPA_C_DPPA_Y1*J10*J9 | K72: =DPPA_C_DPPA_Y1*K10*K9 | ... W72: =DPPA_C_DPPA_Y1*W10*W9
A73: C_CL settlement adder | B73: USD | D73: =DPPA_C_CL_Y1*D10*D9 | E73: =DPPA_C_CL_Y1*E10*E9 | F73: =DPPA_C_CL_Y1*F10*F9 | G73: =DPPA_C_CL_Y1*G10*G9 | H73: =DPPA_C_CL_Y1*H10*H9 | I73: =DPPA_C_CL_Y1*I10*I9 | J73: =DPPA_C_CL_Y1*J10*J9 | K73: =DPPA_C_CL_Y1*K10*K9 | ... W73: =DPPA_C_CL_Y1*W10*W9
A74: C_BL retail shortfall (incl. degradation repurchase) | B74: USD | D74: =(DPPA_C_BL_Y1+DPPA_MATCHED_RETAIL_Y1*(1-D9))*D6 | E74: =(DPPA_C_BL_Y1+DPPA_MATCHED_RETAIL_Y1*(1-E9))*E6 | F74: =(DPPA_C_BL_Y1+DPPA_MATCHED_RETAIL_Y1*(1-F9))*F6 | G74: =(DPPA_C_BL_Y1+DPPA_MATCHED_RETAIL_Y1*(1-G9))*G6 | H74: =(DPPA_C_BL_Y1+DPPA_MATCHED_RETAIL_Y1*(1-H9))*H6 | I74: =(DPPA_C_BL_Y1+DPPA_MATCHED_RETAIL_Y1*(1-I9))*I6 | J74: =(DPPA_C_BL_Y1+DPPA_MATCHED_RETAIL_Y1*(1-J9))*J6 | K74: =(DPPA_C_BL_Y1+DPPA_MATCHED_RETAIL_Y1*(1-K9))*K6 | ... W74: =(DPPA_C_BL_Y1+DPPA_MATCHED_RETAIL_Y1*(1-W9))*W6
A75: Buyer cost with project | B75: USD | D75: =D71+D72+D73+D74+D17+OPT_DEMAND_Y1*D7+D20 | E75: =E71+E72+E73+E74+E17+OPT_DEMAND_Y1*E7+E20 | F75: =F71+F72+F73+F74+F17+OPT_DEMAND_Y1*F7+F20 | G75: =G71+G72+G73+G74+G17+OPT_DEMAND_Y1*G7+G20 | H75: =H71+H72+H73+H74+H17+OPT_DEMAND_Y1*H7+H20 | I75: =I71+I72+I73+I74+I17+OPT_DEMAND_Y1*I7+I20 | J75: =J71+J72+J73+J74+J17+OPT_DEMAND_Y1*J7+J20 | K75: =K71+K72+K73+K74+K17+OPT_DEMAND_Y1*K7+K20 | ... W75: =W71+W72+W73+W74+W17+OPT_DEMAND_Y1*W7+W20
A76: Buyer savings vs BAU | B76: USD | D76: =D70-D75 | E76: =E70-E75 | F76: =F70-F75 | G76: =G70-G75 | H76: =H70-H75 | I76: =I70-I75 | J76: =J70-J75 | K76: =K70-K75 | ... W76: =W70-W75
A77: Buyer savings (% of BAU) | B77: % | D77: =IF(D70=0,"",D76/D70) | E77: =IF(E70=0,"",E76/E70) | F77: =IF(F70=0,"",F76/F70) | G77: =IF(G70=0,"",G76/G70) | H77: =IF(H70=0,"",H76/H70) | I77: =IF(I70=0,"",I76/I70) | J77: =IF(J70=0,"",J76/J70) | K77: =IF(K70=0,"",K76/K70) | ... W77: =IF(W70=0,"",W76/W70)
A79: RETURN METRICS (Excel formulas)
A80: Equity IRR | C80: =IRR(C65:W65)
A81: Project IRR (unlevered) | C81: =IRR(C64:W64)
A82: Equity NPV @ owner discount rate | C82: =NPV(DISC_RATE,D65:W65)+C65
A83: Minimum DSCR (debt years) | C83: =MIN(D67:W67) | D83: MIN ignores the blank non-debt years
A84: Average DSCR (debt years) | C84: =AVERAGE(D67:W67)
A85: First year cumulative equity CF ≥ 0 | C85: =MATCH(TRUE,INDEX(D66:W66>=0,0),0)
A86: Simple equity payback | C86: =IF(ISNA($C$85),"n/a",$C$85-1+IFERROR(-INDEX(C66:W66,$C$85)/INDEX(D65:W65,$C$85),0)) | D86: years
A87: ROI (cumulative equity CF / equity) | C87: =SUM(D65:W65)/EQUITY_INVESTMENT
A88: Buyer savings, years 1-10 (% of BAU) | C88: =SUM(D76:M76)/SUM(D70:M70)
A90: CHECKS - EXCEL vs ENGINE (per-year tie-out)
A91: Equity cash flow (engine) | B91: USD | C91: -466970.74 | D91: 96162.673 | E91: 105813.74 | F91: 115820.78 | G91: 126196.96 | H91: 129654.82 | I91: 139820.34 | J91: 150340.15 | K91: 161225.58 | L91: 171247.17 | M91: -14432.749 | N91: 227305.43 | O91: 376277.59 | P91: 389936.45 | Q91: 388604.74 | R91: 402518 | S91: 382806.35 | T91: 396104.11 | U91: 404928.76 | V91: 415832.14 | W91: 430658.8
A92: CFADS (engine) | B92: USD | D92: 262225.86 | E92: 271876.93 | F92: 281883.97 | G92: 292260.15 | H92: 295718.01 | I92: 305883.53 | J92: 316403.33 | K92: 327288.77 | L92: 337310.36 | M92: 151630.44 | N92: 227305.43 | O92: 376277.59 | P92: 389936.45 | Q92: 388604.74 | R92: 402518 | S92: 382806.35 | T92: 396104.11 | U92: 404928.76 | V92: 415832.14 | W92: 430658.8
A93: CIT (engine) | B93: USD | D93: 0 | E93: 0 | F93: 0 | G93: 0 | H93: 7301.1062 | I93: 8291.4993 | J93: 9339.2451 | K93: 10448.23 | L93: 12863.716 | M93: 12866.961 | N93: 13337.3 | O93: 14030.59 | P93: 14749.478 | Q93: 30989.819 | R93: 32535.737 | S93: 68277.496 | T93: 71601.935 | U93: 80013.497 | V93: 86983.082 | W93: 90689.747
A94: Max |Excel − engine| this year | B94: USD | C94: =ABS(C65-C91) | D94: =MAX(ABS(D65-D91),ABS(D63-D92),ABS(D60-D93)) | E94: =MAX(ABS(E65-E91),ABS(E63-E92),ABS(E60-E93)) | F94: =MAX(ABS(F65-F91),ABS(F63-F92),ABS(F60-F93)) | G94: =MAX(ABS(G65-G91),ABS(G63-G92),ABS(G60-G93)) | H94: =MAX(ABS(H65-H91),ABS(H63-H92),ABS(H60-H93)) | I94: =MAX(ABS(I65-I91),ABS(I63-I92),ABS(I60-I93)) | J94: =MAX(ABS(J65-J91),ABS(J63-J92),ABS(J60-J93)) | K94: =MAX(ABS(K65-K91),ABS(K63-K92),ABS(K60-K93)) | ... W94: =MAX(ABS(W65-W91),ABS(W63-W92),ABS(W60-W93))
A96: Check | C96: Excel | D96: Engine | E96: Delta | F96: Status
A97: Per-year cash flow tie-out (max delta, all years) | C97: =MAX(C94:W94) | D97: 0 | E97: =ABS(C97-D97) | F97: =IF(ABS(C97-D97)<=1.0,"PASS","REVIEW")
A98: Equity IRR | C98: =$C$80 | D98: 0.28385393 | E98: =ABS(C98-D98) | F98: =IF(ABS(C98-D98)<=0.0005,"PASS","REVIEW")
A99: Project IRR | C99: =$C$81 | D99: 0.18337348 | E99: =ABS(C99-D99) | F99: =IF(ABS(C99-D99)<=0.0005,"PASS","REVIEW")
A100: Equity NPV | C100: =$C$82 | D100: 1137682.3 | E100: =ABS(C100-D100) | F100: =IF(ABS(C100-D100)<=1.0,"PASS","REVIEW")
A101: Minimum DSCR | C101: =$C$83 | D101: 0.91308881 | E101: =ABS(C101-D101) | F101: =IF(ABS(C101-D101)<=0.005,"PASS","REVIEW")
A102: Average DSCR | C102: =$C$84 | D102: 1.7116866 | E102: =ABS(C102-D102) | F102: =IF(ABS(C102-D102)<=0.005,"PASS","REVIEW")
A103: Simple equity payback | C103: =$C$86 | D103: 4.1772135 | E103: =ABS(C103-D103) | F103: =IF(ABS(C103-D103)<=0.05,"PASS","REVIEW")
A104: ROI | C104: =$C$87 | D104: 10.700503 | E104: =ABS(C104-D104) | F104: =IF(ABS(C104-D104)<=0.0005,"PASS","REVIEW")
A105: Buyer savings, years 1-10 (% of BAU) | C105: =$C$88 | D105: -0.10240977 | E105: =ABS(C105-D105) | F105: =IF(ABS(C105-D105)<=0.0005,"PASS","REVIEW")

Sheet FX Sensitivity
A1: FX Sensitivity - VND depreciation vs USD returns
A2: Cash flows are VND-denominated (EVN tariff / DPPA settlement) but reported in USD at the fixed contract rate. Each scenario deflates the year-t USD equity cash flow by (1+d)^t. Debt is assumed VND-denominated, so DSCR is unchanged. The rate cells are editable; engine columns validate the default scenarios.
A4: VND depreciation (per year) | B4: Equity IRR (USD) | C4: Equity NPV (USD) | D4: Equity IRR (engine) | E4: Equity NPV (engine) | F4: Status
A5: 0 | B5: =IRR(B12:V12) | C5: =NPV(DISC_RATE,C12:V12)+B12 | D5: 0.28385393 | E5: 1137682.3 | F5: =IF(AND(ABS(B5-D5)<=0.0005,ABS(C5-E5)<=1.0),"PASS","REVIEW")
A6: 0.01 | B6: =IRR(B13:V13) | C6: =NPV(DISC_RATE,C13:V13)+B13 | D6: 0.2711425 | E6: 982259.67 | F6: =IF(AND(ABS(B6-D6)<=0.0005,ABS(C6-E6)<=1.0),"PASS","REVIEW")
A7: 0.02 | B7: =IRR(B14:V14) | C7: =NPV(DISC_RATE,C14:V14)+B14 | D7: 0.25868032 | E7: 847452.46 | F7: =IF(AND(ABS(B7-D7)<=0.0005,ABS(C7-E7)<=1.0),"PASS","REVIEW")
A8: 0.03 | B8: =IRR(B15:V15) | C8: =NPV(DISC_RATE,C15:V15)+B15 | D8: 0.24646013 | E8: 730105.58 | F8: =IF(AND(ABS(B8-D8)<=0.0005,ABS(C8-E8)<=1.0),"PASS","REVIEW")
A10: Helper - FX-adjusted equity cash flow per scenario (USD): CF_t / (1 + d)^t
B11: 0 | C11: 1 | D11: 2 | E11: 3 | F11: 4 | G11: 5 | H11: 6 | I11: 7 | J11: 8 | K11: 9 | L11: 10 | M11: 11 | N11: 12 | O11: 13 | P11: 14 | Q11: 15 | R11: 16 | S11: 17 | T11: 18 | U11: 19 | V11: 20
A12: =A5 | B12: ='Pro Forma (Audit)'!C65/(1+$A5)^B$11 | C12: ='Pro Forma (Audit)'!D65/(1+$A5)^C$11 | D12: ='Pro Forma (Audit)'!E65/(1+$A5)^D$11 | E12: ='Pro Forma (Audit)'!F65/(1+$A5)^E$11 | F12: ='Pro Forma (Audit)'!G65/(1+$A5)^F$11 | G12: ='Pro Forma (Audit)'!H65/(1+$A5)^G$11 | H12: ='Pro Forma (Audit)'!I65/(1+$A5)^H$11 | I12: ='Pro Forma (Audit)'!J65/(1+$A5)^I$11 | ... V12: ='Pro Forma (Audit)'!W65/(1+$A5)^V$11
A13: =A6 | B13: ='Pro Forma (Audit)'!C65/(1+$A6)^B$11 | C13: ='Pro Forma (Audit)'!D65/(1+$A6)^C$11 | D13: ='Pro Forma (Audit)'!E65/(1+$A6)^D$11 | E13: ='Pro Forma (Audit)'!F65/(1+$A6)^E$11 | F13: ='Pro Forma (Audit)'!G65/(1+$A6)^F$11 | G13: ='Pro Forma (Audit)'!H65/(1+$A6)^G$11 | H13: ='Pro Forma (Audit)'!I65/(1+$A6)^H$11 | I13: ='Pro Forma (Audit)'!J65/(1+$A6)^I$11 | ... V13: ='Pro Forma (Audit)'!W65/(1+$A6)^V$11
A14: =A7 | B14: ='Pro Forma (Audit)'!C65/(1+$A7)^B$11 | C14: ='Pro Forma (Audit)'!D65/(1+$A7)^C$11 | D14: ='Pro Forma (Audit)'!E65/(1+$A7)^D$11 | E14: ='Pro Forma (Audit)'!F65/(1+$A7)^E$11 | F14: ='Pro Forma (Audit)'!G65/(1+$A7)^F$11 | G14: ='Pro Forma (Audit)'!H65/(1+$A7)^G$11 | H14: ='Pro Forma (Audit)'!I65/(1+$A7)^H$11 | I14: ='Pro Forma (Audit)'!J65/(1+$A7)^I$11 | ... V14: ='Pro Forma (Audit)'!W65/(1+$A7)^V$11
A15: =A8 | B15: ='Pro Forma (Audit)'!C65/(1+$A8)^B$11 | C15: ='Pro Forma (Audit)'!D65/(1+$A8)^C$11 | D15: ='Pro Forma (Audit)'!E65/(1+$A8)^D$11 | E15: ='Pro Forma (Audit)'!F65/(1+$A8)^E$11 | F15: ='Pro Forma (Audit)'!G65/(1+$A8)^F$11 | G15: ='Pro Forma (Audit)'!H65/(1+$A8)^G$11 | H15: ='Pro Forma (Audit)'!I65/(1+$A8)^H$11 | I15: ='Pro Forma (Audit)'!J65/(1+$A8)^I$11 | ... V15: ='Pro Forma (Audit)'!W65/(1+$A8)^V$11

Sheet Buyer Analysis
B1: Buyer Analysis - Cost vs Business-As-Usual
B2: Annual electricity cost with the project compared against the EVN-only baseline (USD)
B4: Year 1 Snapshot
B5: Year 1 BAU Cost (USD) | C5: 731030.93
B6: Year 1 Cost With Project (USD) | C6: 805683.4
B7: Year 1 Savings (USD) | C7: -74652.466
B8: Year 1 Savings (% of BAU) | C8: -0.10211944
B9: of which C_DN spot energy (USD) | C9: 174753.55
B10: of which C_DPPA + C_CL fees (USD) | C10: 65483.291
B11: of which C_BL retail shortfall (USD) | C11: 481870.22
B12: of which CfD payment, net (USD) | C12: 83576.336 | D12: Positive = buyer pays generator
B13: First 10 Years Savings (USD) | C13: -898833.73 | D13: Cumulative, years 1-10
B14: First 10 Years Savings (% of BAU) | C14: -0.10240977
B15: Lifetime Savings (USD) | C15: -2236896.5 | D15: Cumulative over analysis period
B16: Lifetime Savings (% of BAU) | C16: -0.10275748
A18: Year | B18: BAU Cost (USD) | C18: Cost With Project (USD) | D18: Savings (USD) | E18: Savings (% of BAU) | F18: Cumulative Savings (USD)
A19: 1 | B19: 731030.93 | C19: 805683.4 | D19: -74652.466 | E19: -0.10211944 | F19: -74652.466
A20: 2 | B20: 760272.17 | C20: 837957.14 | D20: -77684.969 | E20: -0.10218047 | F20: -152337.44
A21: 3 | B21: 790683.05 | C21: 871523.44 | D21: -80840.387 | E21: -0.1022412 | F21: -233177.82
A22: 4 | B22: 822310.38 | C22: 906434.07 | D22: -84123.692 | E22: -0.10230163 | F22: -317301.51
A23: 5 | B23: 855202.79 | C23: 942742.85 | D23: -87540.059 | E23: -0.10236176 | F23: -404841.57
A24: 6 | B24: 889410.9 | C24: 980505.77 | D24: -91094.87 | E24: -0.10242158 | F24: -495936.44
A25: 7 | B25: 924987.34 | C25: 1019781.1 | D25: -94793.725 | E25: -0.10248111 | F25: -590730.17
A26: 8 | B26: 961986.83 | C26: 1060629.3 | D26: -98642.451 | E26: -0.10254033 | F26: -689372.62
A27: 9 | B27: 1000466.3 | C27: 1103113.4 | D27: -102647.11 | E27: -0.10259927 | F27: -792019.73
A28: 10 | B28: 1040485 | C28: 1147299 | D28: -106814 | E28: -0.1026579 | F28: -898833.73
A29: 11 | B29: 1082104.4 | C29: 1193254.1 | D29: -111149.7 | E29: -0.10271625 | F29: -1009983.4
A30: 12 | B30: 1125388.5 | C30: 1241049.5 | D30: -115661.02 | E30: -0.1027743 | F30: -1125644.4
... A38: 20 | B38: 1540171.9 | C38: 1699161.4 | D38: -158989.46 | E38: -0.10322839 | F38: -2236896.5

Sheet Developer Returns
B1: Developer Returns - Financing & Cash Flow
B2: Seller/ESCO investment case: sources & uses, return metrics and annual equity cash flow (USD)
B4: Sources & Uses
B5: Total Investment (USD) | C5: 1556569.1
B6: Debt Principal (USD) | C6: 1089598.4
B7: Equity Investment (USD) | C7: 466970.74
B9: Return Metrics
B10: Equity IRR | C10: 0.28385393
B11: Project IRR | C11: 0.18337348
B12: NPV (USD) | C12: 1137682.3 | D12: At owner discount rate
B13: Minimum DSCR (debt years) | C13: 0.91308881
B14: Average DSCR | C14: 1.7116866
B15: Simple Payback (Years) | C15: 4.1772135
B16: ROI (cumulative equity CF / equity) | C16: 10.700503
A18: Year | B18: Revenue (USD) | C18: O&M + Replacement (USD) | D18: CIT (USD) | E18: CFADS (USD) | F18: Debt Service (USD) | G18: DSCR | H18: Equity Cash Flow (USD) | I18: Cumulative Equity CF (USD)
A19: 1 | B19: 281186.54 | C19: 18960.679 | D19: 0 | E19: 262225.86 | F19: 166063.19 | G19: 1.5790728 | H19: 96162.673 | I19: -370808.06
A20: 2 | B20: 291406.43 | C20: 19529.499 | D20: 0 | E20: 271876.93 | F20: 166063.19 | G20: 1.6371896 | H20: 105813.74 | I20: -264994.32
A21: 3 | B21: 301999.35 | C21: 20115.384 | D21: 0 | E21: 281883.97 | F21: 166063.19 | G21: 1.6974501 | H21: 115820.78 | I21: -149173.54
A22: 4 | B22: 312978.99 | C22: 20718.846 | D22: 0 | E22: 292260.15 | F22: 166063.19 | G22: 1.7599334 | H22: 126196.96 | I22: -22976.584
A23: 5 | B23: 324359.52 | C23: 21340.411 | D23: 7301.1062 | E23: 295718.01 | F23: 166063.19 | G23: 1.7807559 | H23: 129654.82 | I23: 106678.23
A24: 6 | B24: 336155.65 | C24: 21980.624 | D24: 8291.4993 | E24: 305883.53 | F24: 166063.19 | G24: 1.8419707 | H24: 139820.34 | I24: 246498.57
A25: 7 | B25: 348382.62 | C25: 22640.042 | D25: 9339.2451 | E25: 316403.33 | F25: 166063.19 | G25: 1.9053189 | H25: 150340.15 | I25: 396838.72
A26: 8 | B26: 361056.24 | C26: 23319.244 | D26: 10448.23 | E26: 327288.77 | F26: 166063.19 | G26: 1.9708689 | H26: 161225.58 | I26: 558064.29
A27: 9 | B27: 374192.9 | C27: 24018.821 | D27: 12863.716 | E27: 337310.36 | F27: 166063.19 | G27: 2.0312169 | H27: 171247.17 | I27: 729311.47
A28: 10 | B28: 387809.59 | C28: 223312.19 | D28: 12866.961 | E28: 151630.44 | F28: 166063.19 | G28: 0.91308881 | H28: -14432.749 | I28: 714878.72
A29: 11 | B29: 401923.93 | C29: 161281.2 | D29: 13337.3 | E29: 227305.43 | F29: 0 | H29: 227305.43 | I29: 942184.15
A30: 12 | B30: 416554.19 | C30: 26246.014 | D30: 14030.59 | E30: 376277.59 | F30: 0 | H30: 376277.59 | I30: 1318461.7
A31: 13 | B31: 431719.32 | C31: 27033.395 | D31: 14749.478 | E31: 389936.45 | F31: 0 | H31: 389936.45 | I31: 1708398.2
A32: 14 | B32: 447438.95 | C32: 27844.396 | D32: 30989.819 | E32: 388604.74 | F32: 0 | H32: 388604.74 | I32: 2097002.9
A33: 15 | B33: 463733.47 | C33: 28679.728 | D33: 32535.737 | E33: 402518 | F33: 0 | H33: 402518 | I33: 2499520.9
A34: 16 | B34: 480623.97 | C34: 29540.12 | D34: 68277.496 | E34: 382806.35 | F34: 0 | H34: 382806.35 | I34: 2882327.3
A35: 17 | B35: 498132.37 | C35: 30426.324 | D35: 71601.935 | E35: 396104.11 | F35: 0 | H35: 396104.11 | I35: 3278431.4
A36: 18 | B36: 516281.37 | C36: 31339.114 | D36: 80013.497 | E36: 404928.76 | F36: 0 | H36: 404928.76 | I36: 3683360.1
A37: 19 | B37: 535094.51 | C37: 32279.287 | D37: 86983.082 | E37: 415832.14 | F37: 0 | H37: 415832.14 | I37: 4099192.3
A38: 20 | B38: 554596.21 | C38: 33247.666 | D38: 90689.747 | E38: 430658.8 | F38: 0 | H38: 430658.8 | I38: 4529851.1

Sheet Technical Results
A1: Metric | B1: Value
A2: System Sizing
A3: PV Size (kW) | B3: 2829.159
A4: Battery Power (kW) | B4: 306.08
A5: Battery Energy (kWh) | B5: 1450.72
A7: Annual Energy Balance (Year 1)
A8: PV to Load (kWh) | B8: 3005305.9
A9: PV to Storage (kWh) | B9: 434798.62
A10: PV to Grid (kWh) | B10: 0
A11: Storage to Load (kWh) | B11: 391121.39
A12: Grid to Load (kWh) | B12: 6070538.5
A13: PV Curtailed (kWh) | B13: 543471.89
A14: Grid to Storage (kWh) | B14: 0
A16: Year-1 Utility Bill Comparison
A17: BAU Utility Bill (USD) | B17: 731030.93
A18: Optimized Utility Bill (USD) | B18: 473979.31
A19: Utility Bill Savings (USD) | B19: 257051.62
A20: BAU Demand Charge (USD) | B20: 0
A21: Optimized Demand Charge (USD) | B21: 0
A22: Demand Charge Savings (USD) | B22: 0
A24: Solar Resource (Year 1)
A25: Annual POA Irradiation (kWh/m²) | B25: 1929.6822
A26: Performance Ratio (Year 1) | B26: 0.72967589

Sheet Dispatch Profile
A1: Hour | B1: Load (kW) | C1: PV Irradiation (W/m²) | D1: PV Generation Total (kW) | E1: PV to Load (kW) | F1: PV to Storage (kW) | G1: PV to Grid (kW) | H1: PV Curtailed (kW) | I1: Grid to Load (kW) | J1: Grid to Storage (kW) | K1: Storage to Load (kW)
A2: 1 | B2: 1020 | C2: 0 | D2: 0 | E2: 0 | F2: 0 | G2: 0 | H2: 0 | I2: 1020 | J2: 0 | K2: 0
A3: 2 | B3: 1078.4 | C3: 0 | D3: 0 | E3: 0 | F3: 0 | G3: 0 | H3: 0 | I3: 1078.4 | J3: 0 | K3: 0
A4: 3 | B4: 906.4 | C4: 0 | D4: 0 | E4: 0 | F4: 0 | G4: 0 | H4: 0 | I4: 906.4 | J4: 0 | K4: 0
A5: 4 | B5: 860.8 | C5: 0 | D5: 0 | E5: 0 | F5: 0 | G5: 0 | H5: 0 | I5: 860.8 | J5: 0 | K5: 0
A6: 5 | B6: 996.8 | C6: 0 | D6: 0 | E6: 0 | F6: 0 | G6: 0 | H6: 0 | I6: 996.8 | J6: 0 | K6: 0
A7: 6 | B7: 983.2 | C7: 0 | D7: 0 | E7: 0 | F7: 0 | G7: 0 | H7: 0 | I7: 876.732 | J7: 0 | K7: 110.59946
A8: 7 | B8: 586.4 | C8: 11.75 | D8: 8.2979723 | E8: 8.2979723 | F8: 0 | G8: 0 | H8: 0 | I8: 272.329 | J8: 0 | K8: 317.96047
A9: 8 | B9: 104.269 | C9: 120.27 | D9: 256.75721 | E9: 108.31513 | F9: -148.44208 | G9: 0 | H9: 0 | I9: 0 | J9: 0 | K9: 0
A10: 9 | B10: 89.172 | C10: 270.88 | D10: 600.8374 | E10: 92.632297 | F10: -317.96047 | G10: 0 | H10: 190.24462 | I10: 0 | J10: 0 | K10: 0
A11: 10 | B11: 105.232 | C11: 505.48 | D11: 1114.7113 | E11: 109.3155 | F11: -317.96047 | G11: 0 | H11: 687.43528 | I11: 0 | J11: 0 | K11: 0
A12: 11 | B12: 89.626 | C12: 573.07 | D12: 1243.8939 | E12: 93.103914 | F12: -317.96047 | G12: 0 | H12: 832.8295 | I12: 0 | J12: 0 | K12: 0
A13: 12 | B13: 119.641 | C13: 477.66 | D13: 1027.0756 | E13: 124.28468 | F13: -169.51735 | G13: 0 | H13: 733.27357 | I13: 0 | J13: 0 | K13: 0
... A8761: 8760 | B8761: 1216 | C8761: 0 | D8761: 0 | E8761: 0 | F8761: 0 | G8761: 0 | H8761: 0 | I8761: 1216 | J8761: 0 | K8761: 0

Sheet Load Duration
A1: Rank | B1: Load (kW) | C1: Net Load (kW)
A2: 1 | B2: 2428 | C2: 2428
A3: 2 | B3: 2418.5558 | C3: 2418.556
A4: 3 | B4: 2414.4 | C4: 2414.4
A5: 4 | B5: 2405.0087 | C5: 2405.009
A6: 5 | B6: 2390.381 | C6: 2379.2
A7: 6 | B7: 2389.6 | C7: 2369.946
A8: 7 | B8: 2387.844 | C8: 2361.036
A9: 8 | B9: 2381.0831 | C9: 2330.4
A10: 9 | B10: 2380.3051 | C10: 2321.335
A11: 10 | B11: 2379.2 | C11: 2238.145
A12: 11 | B12: 2378.556 | C12: 2208.8
A13: 12 | B13: 2369.9456 | C13: 2200.208
... A8761: 8760 | B8761: 0 | C8761: 0

Sheet Year 1 BAU vs DPPA
A1: Line Item | B1: Year 1 (USD) | C1: Side
A2: Buyer (Factory) - Year 1 Outflow (USD)
A3: BAU EVN energy + demand bill | B3: 731030.93 | C3: bau
A4: C_DN spot energy (Q_Khc × CFMP × K_pp) | B4: 174753.55 | C4: dppa
A5: C_DPPA system service fee | B5: 45048.7 | C5: dppa
A6: C_CL settlement adder | B6: 20434.591 | C6: dppa
A7: C_BL retail shortfall (P_evn × shortfall) | B7: 481870.22 | C7: dppa
A8: CfD payment to ESCO (positive = pay) | B8: 83576.336 | C8: dppa
A9: Optimized demand charge (kept by EVN) | B9: 0 | C9: dppa
A10: ESCO demand savings share charged back | B10: 0 | C10: dppa
A11: Total buyer outflow | B11: 805683.4 | C11: both
A12: Buyer savings vs BAU | B12: -74652.466 | C12: delta
A13: Buyer savings as % of BAU | B13: -0.10211944 | C13: delta_fraction
A14: Seller (ESCO / Generator) - Year 1 Revenue (USD)
A15: Discount-to-EVN energy revenue (Phase 2) | B15: 0 | C15: bau_esco
A16: FMP market revenue (Q_re_meter × FMP) | B16: 197610.21 | C16: dppa
A17: CfD net (from buyer) | B17: 83576.336 | C17: dppa
A18: Demand savings share (80%) | B18: 0 | C18: both_esco
A19: ESCO grid arbitrage revenue | B19: 0 | C19: both_esco
A20: Total ESCO / generator revenue | B20: 281186.54 | C20: both_esco
A21: System Energy Flows (kWh / yr)
A22: PV → load | B22: 3005305.9 | C22: flow
A23: PV → storage | B23: 434798.62 | C23: flow
A24: PV → grid (export at FMP) | B24: 543471.89 | C24: flow
A25: Storage → load | B25: 391121.39 | C25: flow
A26: Q_re_meter (total generator injection) | B26: 3939899.1 | C26: flow
A27: Q_adj (loss-adjusted customer-side) | B27: 3835336.4 | C27: flow
A28: Q_Khc (matched consumption, settled) | B28: 3291057.8 | C28: flow
A29: EVN retail shortfall | B29: 6049033.8 | C29: flow

Sheet Monthly Settlement
A1: Month | B1: C_DN (VND) | C1: C_DPPA (VND) | D1: C_CL (VND) | E1: C_BL (VND) | F1: CfD Net (VND) | G1: Generator Revenue (VND) | H1: Customer Total (VND)
A2: 1 | B2: 4.1585873e+08 | C2: 1.0029314e+08 | D2: 45494082 | E2: 1.1153492e+09 | F2: 1.6161029e+08 | G2: 6.5467987e+08 | H2: 1.8386054e+09
A3: 2 | B3: 3.9481248e+08 | C3: 99983603 | D3: 45353673 | E3: 8.8231664e+08 | F3: 1.8370192e+08 | G3: 6.6263063e+08 | H3: 1.6061683e+09
A4: 3 | B4: 5.571889e+08 | C4: 1.1772203e+08 | D4: 53400019 | E4: 1.0643384e+09 | F4: 1.264479e+08 | G4: 7.8000366e+08 | H4: 1.9190973e+09
A5: 4 | B5: 5.2231761e+08 | C5: 1.0579069e+08 | D5: 47987831 | E5: 9.6371624e+08 | F5: 91883386 | G5: 7.0105064e+08 | H5: 1.7316957e+09
A6: 5 | B6: 4.5246465e+08 | C6: 1.0853491e+08 | D6: 49232642 | E6: 9.4969746e+08 | F6: 1.7213905e+08 | G6: 6.4954105e+08 | H6: 1.7320687e+09
A7: 6 | B7: 2.3684934e+08 | C7: 94265223 | D7: 42759753 | E7: 9.9730623e+08 | F7: 2.9680835e+08 | G7: 5.4156712e+08 | H7: 1.6679889e+09
A8: 7 | B8: 2.7098089e+08 | C8: 93609029 | D8: 42462096 | E8: 9.4407446e+08 | F8: 2.6384374e+08 | G8: 5.6933761e+08 | H8: 1.6149702e+09
A9: 8 | B9: 3.4791895e+08 | C9: 91341226 | D9: 41433395 | E9: 1.1120928e+09 | F9: 1.7474373e+08 | G9: 6.1159068e+08 | H9: 1.7675301e+09
A10: 9 | B10: 2.2021947e+08 | C10: 92288055 | D10: 41862887 | E10: 1.1232787e+09 | F10: 2.9537383e+08 | G10: 5.3531953e+08 | H10: 1.7730229e+09
A11: 10 | B11: 3.2655165e+08 | C11: 83797639 | D11: 38011540 | E11: 1.24967e+09 | F11: 1.4892044e+08 | G11: 5.0819804e+08 | H11: 1.8469513e+09
A12: 11 | B12: 4.122607e+08 | C12: 99009137 | D12: 44911645 | E12: 1.1441923e+09 | F12: 1.5726568e+08 | G12: 5.8573842e+08 | H12: 1.8576395e+09
A13: 12 | B13: 4.3859491e+08 | C13: 98146136 | D13: 44520178 | E13: 1.1271544e+09 | F13: 1.2531931e+08 | G13: 5.9554877e+08 | H13: 1.833735e+09

Sheet Hourly Settlement
A1: Hour | B1: Load (kW) | C1: Q_re_meter (kW) | D1: Q_re_delivered (kW) | E1: Q_adj (kW) | F1: Q_Khc (kW) | G1: FMP (VND/kWh) | H1: C_DN (VND) | I1: C_DPPA (VND) | J1: C_CL (VND) | K1: C_BL (VND) | L1: CfD Payment (VND)
A2: 1 | B2: 1020 | C2: 0 | D2: 0 | E2: 0 | F2: 0 | G2: 1377.55 | H2: 0 | I2: 0 | J2: 0 | K2: 1213800 | L2: 0
A3: 2 | B3: 1078.4 | C3: 0 | D3: 0 | E3: 0 | F3: 0 | G3: 1316 | H3: 0 | I3: 0 | J3: 0 | K3: 1283296 | L3: 0
A4: 3 | B4: 906.4 | C4: 0 | D4: 0 | E4: 0 | F4: 0 | G4: 1367.3 | H4: 0 | I4: 0 | J4: 0 | K4: 1078616 | L4: 0
A5: 4 | B5: 860.8 | C5: 0 | D5: 0 | E5: 0 | F5: 0 | G5: 1420.5 | H5: 0 | I5: 0 | J5: 0 | K5: 1024352 | L5: 0
A6: 5 | B6: 996.8 | C6: 0 | D6: 0 | E6: 0 | F6: 0 | G6: 1423.7 | H6: 0 | I6: 0 | J6: 0 | K6: 1186192 | L6: 0
A7: 6 | B7: 983.2 | C7: 110.59946 | D7: 110.59946 | E7: 107.66421 | F7: 107.66421 | G7: 1433.15 | H7: 164130.33 | I7: 38759.117 | J7: 17581.566 | K7: 1041887.6 | L7: 61029.46
A8: 7 | B8: 586.4 | C8: 326.25845 | D8: 326.25845 | E8: 317.59973 | F8: 317.59973 | G8: 1460.05 | H8: 491831.89 | I8: 114335.9 | J8: 51864.035 | K8: 492710.9 | L8: 171487.97
A9: 8 | B9: 104.269 | C9: 108.31513 | D9: 108.31513 | E9: 105.44051 | F9: 104.269 | G9: 1481.35 | H9: 163091.23 | I9: 37536.84 | J9: 17027.128 | K9: 0 | L9: 54079.117
A10: 9 | B10: 89.172 | C10: 282.87692 | D10: 92.632297 | E10: 275.36952 | F10: 89.172 | G10: 1273.8 | H10: 119873.54 | I10: 32101.92 | J10: 14561.788 | K10: 0 | L10: 64756.706
A11: 10 | B11: 105.232 | C11: 796.75078 | D11: 109.3155 | E11: 775.60545 | F11: 105.232 | G11: 1251.7 | H11: 139185.26 | I11: 37883.52 | J11: 17184.386 | K11: 0 | L11: 78745.106
A12: 11 | B12: 89.626 | C12: 925.93342 | D12: 93.103914 | E12: 901.35965 | F12: 89.626 | G12: 1237.2 | H12: 117193.73 | I12: 32265.36 | J12: 14635.926 | K12: 0 | L12: 68366.713
A13: 12 | B13: 119.641 | C13: 857.55825 | D13: 124.28468 | E13: 834.79912 | F13: 119.641 | G13: 1241.95 | H13: 156736.63 | I13: 43070.76 | J13: 19537.375 | K13: 0 | L13: 90693.86
... A8761: 8760 | B8761: 1216 | C8761: 0 | D8761: 0 | E8761: 0 | F8761: 0 | G8761: 1658.6 | H8761: 0 | I8761: 0 | J8761: 0 | K8761: 2228928 | L8761: 0
