Workbook
Name PROJECT_YEARS: 'Assumptions'!$C$9
Name FX_VND_PER_USD: 'Assumptions'!$C$47
Name PV_CAPEX: 'Assumptions'!$C$50
Name BESS_CAPEX: 'Assumptions'!$C$51
Name OTHER_CAPEX: 'Assumptions'!$C$52
Name TOTAL_CAPEX: 'Assumptions'!$C$53
Name OM_YEAR1: 'Assumptions'!$C$55
Name ESC_OM: 'Assumptions'!$C$56
Name ESC_ENERGY: 'Assumptions'!$C$59
Name ESC_CAPACITY: 'Assumptions'!$C$60
Name PV_DEGRADATION: 'Assumptions'!$C$61
Name ESCO_DISCOUNT: 'Assumptions'!$C$65
Name DEMAND_SHARE: 'Assumptions'!$C$66
Name DEBT_FRACTION: 'Assumptions'!$C$69
Name DEBT_RATE: 'Assumptions'!$C$70
Name DEBT_TERM_YEARS: 'Assumptions'!$C$71
Name DEBT_PRINCIPAL: 'Assumptions'!$C$72
Name EQUITY_INVESTMENT: 'Assumptions'!$C$73
Name DEBT_PAYMENT: 'Assumptions'!$C$74
Name DISC_RATE: 'Assumptions'!$C$75
Name CIT_RATE: 'Assumptions'!$C$78
Name CIT_HOLIDAY_YEARS: 'Assumptions'!$C$79
Name CIT_REDUCED_YEARS: 'Assumptions'!$C$80
Name CIT_REDUCED_FRACTION: 'Assumptions'!$C$81
Name CIT_LOSS_CF_YEARS: 'Assumptions'!$C$82
Name CIT_CLOCK_CAP_YEAR: 'Assumptions'!$C$83
Name PV_DEP_YEARS: 'Assumptions'!$C$84
Name BESS_DEP_YEARS: 'Assumptions'!$C$85
Name BAU_BILL_Y1: 'Assumptions'!$C$87
Name OPT_BILL_Y1: 'Assumptions'!$C$88
Name BAU_DEMAND_Y1: 'Assumptions'!$C$89
Name OPT_DEMAND_Y1: 'Assumptions'!$C$90
Name BASE_DEMAND_SAVINGS: 'Assumptions'!$C$91
Name BASE_SERVED_RETAIL: 'Assumptions'!$C$92
Name BASE_ENERGY_REV: 'Assumptions'!$C$93
Name BASE_GRID_ARB: 'Assumptions'!$C$94

Sheet Cover
B2: Investment Case Workbook - Factory A Vietnam ESCO E2E
B3: ESCO discount-to-EVN tariff (behind-the-meter) · prepared 2026-09-11 · REopt dispatch + proforma_vietnam financial engine
B4: REopt run UUID: 554ee85a-6f3c-4077-8dcb-0145406d4e6e
B6: Model validation status | C6: =IF(COUNTIF('Pro Forma (Audit)'!F86:F94,"REVIEW")+COUNTIF('FX Sensitivity'!F5:F8,"REVIEW")=0,"ALL CHECKS PASS","REVIEW REQUIRED") | D6: Live tie-out of every Excel-derived metric against the engine
B8: Colour legend
B9: Hardcoded input / engine output | C9: Case file terms, REopt dispatch results, 8760-h settlement totals, tie-out references
B10: Live Excel formula (white) | C10: Everything derivable is a formula - trace with Excel's formula auditing tools
B11: PASS / REVIEW check cell | C11: Excel-vs-engine tie-out at stated tolerances
B13: Contents
B14: Executive Summary | C14: Headline KPIs for both counterparties
B15: Assumptions | C15: Every case input & contract term with unit, source and named cell
B16: Model Basis | C16: Methodology, settlement math, simplifications register
B17: Pro Forma (Audit) | C17: Full cash flow rebuilt with live formulas + engine tie-out
B18: FX Sensitivity | C18: USD returns under VND depreciation (editable)
B19: Buyer Analysis | C19: Offtaker savings vs business-as-usual
B20: Developer Returns | C20: Sources & uses, coverage, equity cash flow
B21: Technical Results | C21: System sizing, year-1 energy balance, bill comparison
B22: Dispatch Profile | C22: 8760-h dispatch incl. original PV generation; chart shows the peak-load week
B23: Load Duration | C23: Load and net-load duration curves
B25: Prepared for investment and lending review. Figures are model outputs, not offers; REopt sizing is optimizer output and may shift with solver versions.
B26: Regenerate offline anytime: python -m proforma_vietnam.rebuild_report --case-dir <case>.

Sheet Executive Summary
B1: Investment & PPA Negotiation Summary - Factory A Vietnam ESCO E2E
B2: ESCO discount-to-EVN tariff (behind-the-meter) · prepared 2026-09-11 · REopt dispatch + proforma_vietnam financial model
B4: Project & System
B5: PV Size (kW) | C5: 5943.6183
B6: Battery Power (kW) | C6: 1799.38
B7: Battery Energy (kWh) | C7: 10823.88
B8: Total Investment (USD) | C8: 4295752.8
B10: Contract Terms
B11: ESCO Energy Price (fraction of EVN tariff) | C11: 0.9
B12: Demand Savings Share to ESCO | C12: 0.8
B13: Analysis Period (Years) | C13: 25
B15: Developer (Seller) Returns
B16: Equity IRR | C16: 0.14647206
B17: Project IRR | C17: 0.12229483
B18: NPV (USD) | C18: 1032757.9 | D18: At owner discount rate
B19: Minimum DSCR (debt years) | C19: 1.067649 | D19: Lender covenant view
B20: Average DSCR | C20: 1.2295962
B21: Simple Payback (Years) | C21: 12.195007
B22: Equity Investment (USD) | C22: 1288725.8
B23: Debt Principal (USD) | C23: 3007026.9
B25: Buyer (Offtaker) Outcome
B26: Year 1 BAU Cost (USD) | C26: 769044.53
B27: Year 1 Cost With Project (USD) | C27: 709112.62
B28: Year 1 Buyer Savings (USD) | C28: 59931.914
B29: Year 1 Savings (% of BAU) | C29: 0.077930356
B30: First 10 Years Buyer Savings (USD) | C30: 702435.33 | D30: Cumulative, years 1-10
B31: First 10 Years Savings (% of BAU) | C31: 0.076076872
B32: Lifetime Buyer Savings (USD) | C32: 2328139.2 | D32: Sum over analysis period
B33: Lifetime Savings (% of BAU) | C33: 0.07269175
B35: Model Basis & Conventions
B36: • ESCO is paid a discount to the time-specific EVN tariff for project-served energy.
B37: • PV degradation, O&M escalation and battery replacement (REopt schedule) are applied across the analysis period.
B38: • PV straight-line depreciation over 20 years (Circular 45/2013/TT-BTC permits 7-20 years for generating equipment).
B39: • Vietnam CIT: 4-year exemption + 9-year 50% reduction from first profitable year; 5-year tax-loss carryforward.
B40: • All USD figures at the fixed contract exchange rate (see Assumptions); FX drift between VND revenue and USD reporting is quantified on the FX Sensitivity sheet.

Sheet Assumptions
B1: Assumptions & Model Inputs
B2: Shaded cells are hardcoded inputs (case file or engine output); named cells drive every formula on the Pro Forma (Audit) sheet.
B4: Project & Run
B5: Case name | C5: Factory A Vietnam ESCO E2E | E5: case.json
B6: Financing structure | C6: ESCO discount-to-EVN (behind-the-meter) | E6: proforma_vietnam.structures
B7: REopt run UUID | C7: 554ee85a-6f3c-4077-8dcb-0145406d4e6e | E7: REopt API
B8: Report prepared | C8: 2026-09-11
B9: Analysis period | C9: 25 | D9: years | E9: case.json financial.analysis_years
B10: Tariff year | C10: 2025 | E10: case.json tariff.year
B11: Voltage level | C11: 22-110kV | E11: case.json tariff.voltage_level
B12: TOU schedule | C12: decision_963 | E12: case.json tariff.tou_schedule
B13: Site & Load Profile (case.json)
B14: Latitude | C14: 10.8231 | D14: deg | E14: case.json site.latitude
B15: Longitude | C15: 106.6297 | D15: deg | E15: case.json site.longitude
B16: Load profile file | C16: Sample Load Profile/Emivest_clean.csv | E16: case.json load_profile.path (8760 hourly kW)
B17: Load year | C17: 2025 | E17: case.json load_profile.year
B18: PV Technology (case.json)
B19: PV minimum size | C19: 0 | D19: kW | E19: case.json technologies.pv.min_kw
B20: PV maximum size | C20: 10000 | D20: kW | E20: case.json technologies.pv.max_kw
B21: PV installed cost | C21: 480 | D21: USD/kW | E21: case.json technologies.pv.installed_cost_per_kw
B22: PV O&M cost | C22: 6 | D22: USD/kW/yr | E22: case.json technologies.pv.om_cost_per_kw
B23: PV degradation (case input) | C23: 0.005 | D23: per year | E23: case.json technologies.pv.degradation_fraction
B24: PVWatts tilt | C24: 10 | E24: case.json technologies.pv.pvwatts (production factor inputs)
B25: PVWatts azimuth | C25: 180 | E25: case.json technologies.pv.pvwatts (production factor inputs)
B26: PVWatts array_type | C26: 1 | E26: case.json technologies.pv.pvwatts (production factor inputs)
B27: PVWatts module_type | C27: 0 | E27: case.json technologies.pv.pvwatts (production factor inputs)
B28: PVWatts losses | C28: 14 | E28: case.json technologies.pv.pvwatts (production factor inputs)
B29: PVWatts dc_ac_ratio | C29: 1.2 | E29: case.json technologies.pv.pvwatts (production factor inputs)
B30: Storage Technology (case.json)
B31: Storage minimum power | C31: 0 | D31: kW | E31: case.json technologies.storage.min_kw
B32: Storage maximum power | C32: 5000 | D32: kW | E32: case.json technologies.storage.max_kw
B33: Storage minimum energy | C33: 0 | D33: kWh | E33: case.json technologies.storage.min_kwh
B34: Storage maximum energy | C34: 20000 | D34: kWh | E34: case.json technologies.storage.max_kwh
B35: Storage cost per kW | C35: 80 | D35: USD/kW | E35: case.json technologies.storage.installed_cost_per_kw
B36: Storage cost per kWh | C36: 120 | D36: USD/kWh | E36: case.json technologies.storage.installed_cost_per_kwh
B37: Storage fixed cost | C37: 0 | D37: USD | E37: case.json technologies.storage.installed_cost_constant
B38: Replacement cost per kW | C38: 80 | D38: USD/kW | E38: case.json technologies.storage.replace_cost_per_kw
B39: Replacement cost per kWh | C39: 100 | D39: USD/kWh | E39: case.json technologies.storage.replace_cost_per_kwh
B40: Replacement fixed cost | C40: 0 | D40: USD | E40: case.json technologies.storage.replace_cost_constant
B41: Inverter replacement year | C41: 10 | D41: year | E41: case.json technologies.storage.inverter_replacement_year
B42: Battery replacement year | C42: 11 | D42: year | E42: case.json technologies.storage.battery_replacement_year
... B44: O&M (fraction of installed cost) | C44: 0.01 | D44: per year | E44: case.json technologies.storage.om_cost_fraction_of_installed_cost
B45: Currency & FX
B46: Model currency | C46: USD | E46: EVN tariff converted VND→USD before REopt; see Model Basis
B47: Contract exchange rate | C47: 26300 | D47: VND per USD | E47: case.json tariff.exchange_rate_vnd_per_usd
B48: FX treatment | C48: Held flat over the analysis period | E48: Simplification - see FX Sensitivity sheet
B49: Capital Costs
B50: PV capex | C50: 2852936.8 | D50: USD | E50: REopt PV size_kw × installed_cost_per_kw
B51: BESS capex | C51: 1442816 | D51: USD | E51: REopt ElectricStorage initial_capital_cost
B52: Other capex | C52: 0 | D52: USD | E52: case.json (developer overrides)
B53: Total investment | C53: =PV_CAPEX+BESS_CAPEX+OTHER_CAPEX | D53: USD | E53: Formula: PV + BESS + Other
B54: Operating Costs
B55: Year-1 O&M | C55: 50089.873 | D55: USD/yr | E55: REopt Financial.year_one_om_costs_before_tax
B56: O&M escalation | C56: 0.03 | D56: per year | E56: vietnam_defaults.json / case.json financial.om_escalation_rate
B57: Battery replacement year | C57: 11 | D57: year | E57: case.json technologies.storage.battery_replacement_year
B58: Tariff & Escalation
B59: EVN energy escalation | C59: 0.04 | D59: per year | E59: case.json tariff.evn_energy_escalation_rate
B60: EVN capacity (demand) escalation | C60: 0.04 | D60: per year | E60: case.json tariff.evn_capacity_escalation_rate
B61: PV degradation | C61: 0.005 | D61: per year | E61: REopt PV.degradation_fraction
B62: Tariff currency fed to REopt | C62: USD | E62: case.json tariff.currency
B63: Two-component tariff pilot | C63: FALSE | D63: yes/no | E63: case.json tariff.two_component_pilot_enabled
B64: Contract Terms
B65: ESCO energy price (fraction of EVN tariff) | C65: 0.9 | D65: fraction | E65: case.json esco_contract.esco_energy_discount_fraction
B66: Demand savings share to ESCO | C66: 0.8 | D66: fraction | E66: case.json esco_contract.demand_savings_esco_share
B67: Grid charging enabled | C67: FALSE | D67: yes/no | E67: case.json esco_contract.grid_charging_enabled
B68: Financing
B69: Debt fraction | C69: 0.7 | D69: of total capex | E69: vietnam_defaults.json / case.json financial.debt_fraction
B70: Debt interest rate | C70: 0.085 | D70: per year | E70: vietnam_defaults.json / case.json financial.debt_interest_rate_fraction
B71: Debt term | C71: 10 | D71: years | E71: vietnam_defaults.json / case.json financial.debt_term_years
B72: Debt principal | C72: =TOTAL_CAPEX*DEBT_FRACTION | D72: USD | E72: Formula: total investment × debt fraction
B73: Equity investment | C73: =TOTAL_CAPEX-DEBT_PRINCIPAL | D73: USD | E73: Formula: total investment − debt
B74: Annual debt payment (level) | C74: =IF(OR(DEBT_PRINCIPAL<=0,DEBT_TERM_YEARS<=0),0,IF(DEBT_RATE=0,DEBT_PRINCIPAL/DEBT_TERM_YEARS,DEBT_PRINCIPAL*(DEBT_RATE*(1+DEBT_RATE)^DEBT_TERM_YEARS)/((1+DEBT_RATE)^DEBT_TERM_YEARS-1))) | D74: USD/yr | E74: Standard annuity over the debt term
B75: Owner discount rate | C75: 0.1 | D75: per year | E75: case.json financial.owner_discount_rate_fraction
B76: Tax & Depreciation (Vietnam)
B77: CIT regime | C77: Standard + holiday (conservative ESCO default) | E77: proforma_vietnam.cash_flow (structure-dependent; explicit override wins)
B78: CIT standard rate | C78: 0.2 | D78: of taxable income | E78: Law 67/2025/QH15; vietnam_defaults.json
B79: CIT holiday | C79: 4 | D79: years | E79: Law 67/2025 (from first profitable year); Circular 78/2014 Art. 18 shape
B80: CIT reduced-rate period | C80: 9 | D80: years | E80: Law 67/2025; Circular 78/2014 Art. 18 shape
B81: CIT reduction during period | C81: 0.5 | D81: of applicable base rate | E81: Law 67/2025 (50% of base rate)
B82: Tax-loss carryforward limit | C82: 5 | D82: years | E82: Law 67/2025; Circular 78/2014 Art. 9 shape
B83: Incentive clock cap | C83: 4 | D83: year (latest start) | E83: Law 67/2025; Circular 78/2014 Art. 18 shape
B84: PV depreciation (straight-line) | C84: 20 | D84: years | E84: Circular 45/2013/TT-BTC (7–20 yr band)
B85: BESS depreciation (straight-line) | C85: 8 | D85: years | E85: Circular 45/2013/TT-BTC
B86: Year-1 Engine Outputs (hardcoded - dispatch × tariff, not derivable in-sheet)
B87: Year-1 BAU EVN bill | C87: 769044.53 | D87: USD | E87: REopt ElectricTariff.year_one_bill_before_tax_bau
B88: Year-1 optimized EVN bill | C88: 169725.54 | D88: USD | E88: REopt ElectricTariff.year_one_bill_before_tax
B89: Year-1 BAU demand charge | C89: 0 | D89: USD | E89: REopt year_one_demand_cost_before_tax_bau
B90: Year-1 optimized demand charge | C90: 0 | D90: USD | E90: REopt year_one_demand_cost_before_tax
B91: Year-1 demand savings base | C91: 0 | D91: USD | E91: max(BAU − optimized demand charge, 0)
B92: Year-1 served-energy retail value | C92: 599318.97 | D92: USD | E92: Σ project-served kWh × EVN TOU rate (8760 h)
B93: Year-1 ESCO energy revenue base | C93: 539387.07 | D93: USD | E93: Σ served kWh × EVN TOU rate × ESCO discount
B94: Year-1 grid arbitrage base | C94: 0 | D94: USD | E94: REopt net grid arbitrage × ESCO share
B95: Other Assumptions (assumptions.json echo)
B96: rate_vintage_source | C96: EVN retail electricity tariff, Decision 1279/QD-BCT dated 2025-05-09 | E96: assumptions.json
B97: rate_vintage_year | C97: 2025 | E97: assumptions.json

Sheet Model Basis
B1: Model Basis, Conventions & Simplifications
B3: 1. Model architecture
B4: • REopt (NLR optimization engine) selects PV/BESS sizing and hourly dispatch against the EVN time-of-use tariff over an 8760-hour year.
B5: • proforma_vietnam post-processes the REopt run: an hourly ND57/2025 DPPA settlement layer (when applicable) and a 25-year developer cash flow with Vietnam tax and debt.
B6: • This workbook is generated from that engine. The Pro Forma (Audit) sheet re-derives the full cash flow with live Excel formulas from the named inputs on the Assumptions sheet; the Checks block ties every metric back to the engine (PASS/REVIEW).
B8: 2. Currency & FX
B9: • All money flows are computed in USD at the fixed contract rate (26,300 VND/USD).
B10: • Underlying revenue is VND-denominated (EVN tariff, FMP market, DPPA fees). Holding FX flat for the analysis period is a simplification: the FX Sensitivity sheet quantifies USD-reported returns under 0-3%/yr VND depreciation.
B11: • Sheets that show VND amounts (Hourly/Monthly Settlement, DPPA fee inputs) are VND-native regulatory quantities, not conversions.
B12: • Debt is assumed VND-denominated (local bank), so DSCR is FX-neutral.
B14: 3. Settlement math - ESCO discount-to-EVN
B15: • The ESCO is paid a contracted fraction of the time-specific EVN tariff for project-served energy (PV→load, plus battery→load when the battery cannot grid-charge).
... B47: • EVN retail tariff (current & QĐ963 TOU structures) as configured in the case file.

Sheet Pro Forma (Audit)
A1: Pro Forma (Audit) - every white cell is a live Excel formula
A2: Shaded cells are hardcoded engine outputs (REopt dispatch / 8760-h settlement / tie-out reference). All other cells derive from the named cells on the Assumptions sheet. Currency: USD at the fixed contract FX rate.
A4: TIMELINE & INDEXATION
A5: Year | B5: index | C5: 0 | D5: 1 | E5: 2 | F5: 3 | G5: 4 | H5: 5 | I5: 6 | J5: 7 | K5: 8 | L5: 9 | M5: 10 | N5: 11 | O5: 12 | P5: 13 | Q5: 14 | R5: 15 | S5: 16 | T5: 17 | U5: 18 | V5: 19 | W5: 20 | X5: 21 | Y5: 22 | Z5: 23 | AA5: 24 | AB5: 25
A6: EVN energy escalation factor | B6: index | D6: =(1+ESC_ENERGY)^(D$5-1) | E6: =(1+ESC_ENERGY)^(E$5-1) | F6: =(1+ESC_ENERGY)^(F$5-1) | G6: =(1+ESC_ENERGY)^(G$5-1) | H6: =(1+ESC_ENERGY)^(H$5-1) | I6: =(1+ESC_ENERGY)^(I$5-1) | J6: =(1+ESC_ENERGY)^(J$5-1) | K6: =(1+ESC_ENERGY)^(K$5-1) | ... AB6: =(1+ESC_ENERGY)^(AB$5-1)
A7: EVN capacity escalation factor | B7: index | D7: =(1+ESC_CAPACITY)^(D$5-1) | E7: =(1+ESC_CAPACITY)^(E$5-1) | F7: =(1+ESC_CAPACITY)^(F$5-1) | G7: =(1+ESC_CAPACITY)^(G$5-1) | H7: =(1+ESC_CAPACITY)^(H$5-1) | I7: =(1+ESC_CAPACITY)^(I$5-1) | J7: =(1+ESC_CAPACITY)^(J$5-1) | K7: =(1+ESC_CAPACITY)^(K$5-1) | ... AB7: =(1+ESC_CAPACITY)^(AB$5-1)
A8: O&M escalation factor | B8: index | D8: =(1+ESC_OM)^(D$5-1) | E8: =(1+ESC_OM)^(E$5-1) | F8: =(1+ESC_OM)^(F$5-1) | G8: =(1+ESC_OM)^(G$5-1) | H8: =(1+ESC_OM)^(H$5-1) | I8: =(1+ESC_OM)^(I$5-1) | J8: =(1+ESC_OM)^(J$5-1) | K8: =(1+ESC_OM)^(K$5-1) | ... AB8: =(1+ESC_OM)^(AB$5-1)
A9: PV degradation factor | B9: index | D9: =(1-PV_DEGRADATION)^(D$5-1) | E9: =(1-PV_DEGRADATION)^(E$5-1) | F9: =(1-PV_DEGRADATION)^(F$5-1) | G9: =(1-PV_DEGRADATION)^(G$5-1) | H9: =(1-PV_DEGRADATION)^(H$5-1) | I9: =(1-PV_DEGRADATION)^(I$5-1) | J9: =(1-PV_DEGRADATION)^(J$5-1) | K9: =(1-PV_DEGRADATION)^(K$5-1) | ... AB9: =(1-PV_DEGRADATION)^(AB$5-1)
A11: REVENUE (USD)
A12: ESCO energy revenue (discount-to-EVN) | B12: USD | D12: =BASE_ENERGY_REV*D6*D9 | E12: =BASE_ENERGY_REV*E6*E9 | F12: =BASE_ENERGY_REV*F6*F9 | G12: =BASE_ENERGY_REV*G6*G9 | H12: =BASE_ENERGY_REV*H6*H9 | I12: =BASE_ENERGY_REV*I6*I9 | J12: =BASE_ENERGY_REV*J6*J9 | K12: =BASE_ENERGY_REV*K6*K9 | ... AB12: =BASE_ENERGY_REV*AB6*AB9
A13: Demand charge savings (total) | B13: USD | D13: =BASE_DEMAND_SAVINGS*D7 | E13: =BASE_DEMAND_SAVINGS*E7 | F13: =BASE_DEMAND_SAVINGS*F7 | G13: =BASE_DEMAND_SAVINGS*G7 | H13: =BASE_DEMAND_SAVINGS*H7 | I13: =BASE_DEMAND_SAVINGS*I7 | J13: =BASE_DEMAND_SAVINGS*J7 | K13: =BASE_DEMAND_SAVINGS*K7 | ... AB13: =BASE_DEMAND_SAVINGS*AB7
A14: ESCO share of demand savings | B14: USD | D14: =D13*DEMAND_SHARE | E14: =E13*DEMAND_SHARE | F14: =F13*DEMAND_SHARE | G14: =G13*DEMAND_SHARE | H14: =H13*DEMAND_SHARE | I14: =I13*DEMAND_SHARE | J14: =J13*DEMAND_SHARE | K14: =K13*DEMAND_SHARE | ... AB14: =AB13*DEMAND_SHARE
A15: Grid arbitrage revenue | B15: USD | D15: =BASE_GRID_ARB*D6 | E15: =BASE_GRID_ARB*E6 | F15: =BASE_GRID_ARB*F6 | G15: =BASE_GRID_ARB*G6 | H15: =BASE_GRID_ARB*H6 | I15: =BASE_GRID_ARB*I6 | J15: =BASE_GRID_ARB*J6 | K15: =BASE_GRID_ARB*K6 | ... AB15: =BASE_GRID_ARB*AB6
A16: Total developer revenue | B16: USD | D16: =D12+D14+D15 | E16: =E12+E14+E15 | F16: =F12+F14+F15 | G16: =G12+G14+G15 | H16: =H12+H14+H15 | I16: =I12+I14+I15 | J16: =J12+J14+J15 | K16: =K12+K14+K15 | ... AB16: =AB12+AB14+AB15
A18: OPERATING COSTS (USD)
A19: O&M | B19: USD | D19: =OM_YEAR1*D8 | E19: =OM_YEAR1*E8 | F19: =OM_YEAR1*F8 | G19: =OM_YEAR1*G8 | H19: =OM_YEAR1*H8 | I19: =OM_YEAR1*I8 | J19: =OM_YEAR1*J8 | K19: =OM_YEAR1*K8 | ... AB19: =OM_YEAR1*AB8
A20: Battery replacement (engine schedule) | B20: USD | D20: 0 | E20: 0 | F20: 0 | G20: 0 | H20: 0 | I20: 0 | J20: 0 | K20: 0 | L20: 0 | M20: 0 | N20: 1226338.4 | O20: 0 | P20: 0 | Q20: 0 | R20: 0 | S20: 0 | T20: 0 | U20: 0 | V20: 0 | W20: 0 | X20: 0 | Y20: 0 | Z20: 0 | AA20: 0 | AB20: 0
A21: EBITDA | B21: USD | D21: =D16-D19-D20 | E21: =E16-E19-E20 | F21: =F16-F19-F20 | G21: =G16-G19-G20 | H21: =H16-H19-H20 | I21: =I16-I19-I20 | J21: =J16-J19-J20 | K21: =K16-K19-K20 | ... AB21: =AB16-AB19-AB20
A23: DEBT SCHEDULE (USD)
A24: Opening debt balance | B24: USD | D24: =DEBT_PRINCIPAL | E24: =D28 | F24: =E28 | G24: =F28 | H24: =G28 | I24: =H28 | J24: =I28 | K24: =J28 | L24: =K28 | ... AB24: =AA28
A25: Interest | B25: USD | D25: =IF(D$5<=DEBT_TERM_YEARS,D24*DEBT_RATE,0) | E25: =IF(E$5<=DEBT_TERM_YEARS,E24*DEBT_RATE,0) | F25: =IF(F$5<=DEBT_TERM_YEARS,F24*DEBT_RATE,0) | G25: =IF(G$5<=DEBT_TERM_YEARS,G24*DEBT_RATE,0) | H25: =IF(H$5<=DEBT_TERM_YEARS,H24*DEBT_RATE,0) | I25: =IF(I$5<=DEBT_TERM_YEARS,I24*DEBT_RATE,0) | J25: =IF(J$5<=DEBT_TERM_YEARS,J24*DEBT_RATE,0) | K25: =IF(K$5<=DEBT_TERM_YEARS,K24*DEBT_RATE,0) | ... AB25: =IF(AB$5<=DEBT_TERM_YEARS,AB24*DEBT_RATE,0)
A26: Principal repayment | B26: USD | D26: =IF(D$5<=DEBT_TERM_YEARS,MIN(MAX(DEBT_PAYMENT-D25,0),D24),0) | E26: =IF(E$5<=DEBT_TERM_YEARS,MIN(MAX(DEBT_PAYMENT-E25,0),E24),0) | F26: =IF(F$5<=DEBT_TERM_YEARS,MIN(MAX(DEBT_PAYMENT-F25,0),F24),0) | G26: =IF(G$5<=DEBT_TERM_YEARS,MIN(MAX(DEBT_PAYMENT-G25,0),G24),0) | H26: =IF(H$5<=DEBT_TERM_YEARS,MIN(MAX(DEBT_PAYMENT-H25,0),H24),0) | I26: =IF(I$5<=DEBT_TERM_YEARS,MIN(MAX(DEBT_PAYMENT-I25,0),I24),0) | J26: =IF(J$5<=DEBT_TERM_YEARS,MIN(MAX(DEBT_PAYMENT-J25,0),J24),0) | K26: =IF(K$5<=DEBT_TERM_YEARS,MIN(MAX(DEBT_PAYMENT-K25,0),K24),0) | ... AB26: =IF(AB$5<=DEBT_TERM_YEARS,MIN(MAX(DEBT_PAYMENT-AB25,0),AB24),0)
A27: Debt service | B27: USD | D27: =D25+D26 | E27: =E25+E26 | F27: =F25+F26 | G27: =G25+G26 | H27: =H25+H26 | I27: =I25+I26 | J27: =J25+J26 | K27: =K25+K26 | ... AB27: =AB25+AB26
A28: Closing debt balance | B28: USD | D28: =D24-D26 | E28: =E24-E26 | F28: =F24-F26 | G28: =G24-G26 | H28: =H24-H26 | I28: =I24-I26 | J28: =J24-J26 | K28: =K24-K26 | ... AB28: =AB24-AB26
A30: DEPRECIATION & VIETNAM CIT (USD)
A31: PV depreciation (straight-line) | B31: USD | D31: =IF(D$5<=PV_DEP_YEARS,PV_CAPEX/PV_DEP_YEARS,0) | E31: =IF(E$5<=PV_DEP_YEARS,PV_CAPEX/PV_DEP_YEARS,0) | F31: =IF(F$5<=PV_DEP_YEARS,PV_CAPEX/PV_DEP_YEARS,0) | G31: =IF(G$5<=PV_DEP_YEARS,PV_CAPEX/PV_DEP_YEARS,0) | H31: =IF(H$5<=PV_DEP_YEARS,PV_CAPEX/PV_DEP_YEARS,0) | I31: =IF(I$5<=PV_DEP_YEARS,PV_CAPEX/PV_DEP_YEARS,0) | J31: =IF(J$5<=PV_DEP_YEARS,PV_CAPEX/PV_DEP_YEARS,0) | K31: =IF(K$5<=PV_DEP_YEARS,PV_CAPEX/PV_DEP_YEARS,0) | ... AB31: =IF(AB$5<=PV_DEP_YEARS,PV_CAPEX/PV_DEP_YEARS,0)
A32: BESS depreciation (straight-line) | B32: USD | D32: =IF(D$5<=BESS_DEP_YEARS,BESS_CAPEX/BESS_DEP_YEARS,0) | E32: =IF(E$5<=BESS_DEP_YEARS,BESS_CAPEX/BESS_DEP_YEARS,0) | F32: =IF(F$5<=BESS_DEP_YEARS,BESS_CAPEX/BESS_DEP_YEARS,0) | G32: =IF(G$5<=BESS_DEP_YEARS,BESS_CAPEX/BESS_DEP_YEARS,0) | H32: =IF(H$5<=BESS_DEP_YEARS,BESS_CAPEX/BESS_DEP_YEARS,0) | I32: =IF(I$5<=BESS_DEP_YEARS,BESS_CAPEX/BESS_DEP_YEARS,0) | J32: =IF(J$5<=BESS_DEP_YEARS,BESS_CAPEX/BESS_DEP_YEARS,0) | K32: =IF(K$5<=BESS_DEP_YEARS,BESS_CAPEX/BESS_DEP_YEARS,0) | ... AB32: =IF(AB$5<=BESS_DEP_YEARS,BESS_CAPEX/BESS_DEP_YEARS,0)
A33: Replacement depreciation (in-service yr 11) | B33: USD | D33: =IF(AND(D$5>=11,D$5<=11+BESS_DEP_YEARS-1),$N$20/BESS_DEP_YEARS,0) | E33: =IF(AND(E$5>=11,E$5<=11+BESS_DEP_YEARS-1),$N$20/BESS_DEP_YEARS,0) | F33: =IF(AND(F$5>=11,F$5<=11+BESS_DEP_YEARS-1),$N$20/BESS_DEP_YEARS,0) | G33: =IF(AND(G$5>=11,G$5<=11+BESS_DEP_YEARS-1),$N$20/BESS_DEP_YEARS,0) | H33: =IF(AND(H$5>=11,H$5<=11+BESS_DEP_YEARS-1),$N$20/BESS_DEP_YEARS,0) | I33: =IF(AND(I$5>=11,I$5<=11+BESS_DEP_YEARS-1),$N$20/BESS_DEP_YEARS,0) | J33: =IF(AND(J$5>=11,J$5<=11+BESS_DEP_YEARS-1),$N$20/BESS_DEP_YEARS,0) | K33: =IF(AND(K$5>=11,K$5<=11+BESS_DEP_YEARS-1),$N$20/BESS_DEP_YEARS,0) | ... AB33: =IF(AND(AB$5>=11,AB$5<=11+BESS_DEP_YEARS-1),$N$20/BESS_DEP_YEARS,0)
A34: Total depreciation | B34: USD | D34: =D31+D32+D33 | E34: =E31+E32+E33 | F34: =F31+F32+F33 | G34: =G31+G32+G33 | H34: =H31+H32+H33 | I34: =I31+I32+I33 | J34: =J31+J32+J33 | K34: =K31+K32+K33 | ... AB34: =AB31+AB32+AB33
A35: Taxable income before loss relief (EBT) | B35: USD | D35: =D21+D20-D34-D25 | E35: =E21+E20-E34-E25 | F35: =F21+F20-F34-F25 | G35: =G21+G20-G34-G25 | H35: =H21+H20-H34-H25 | I35: =I21+I20-I34-I25 | J35: =J21+J20-J34-J25 | K35: =K21+K20-K34-K25 | ... AB35: =AB21+AB20-AB34-AB25
A36: New tax loss arising | B36: USD | D36: =MAX(-D35,0) | E36: =MAX(-E35,0) | F36: =MAX(-F35,0) | G36: =MAX(-G35,0) | H36: =MAX(-H35,0) | I36: =MAX(-I35,0) | J36: =MAX(-J35,0) | K36: =MAX(-K35,0) | ... AB36: =MAX(-AB35,0)
A37: Assessable income (pre-relief) | B37: USD | D37: =MAX(D35,0) | E37: =MAX(E35,0) | F37: =MAX(F35,0) | G37: =MAX(G35,0) | H37: =MAX(H35,0) | I37: =MAX(I35,0) | J37: =MAX(J35,0) | K37: =MAX(K35,0) | ... AB37: =MAX(AB35,0)
A38: Loss vintage aged 1y - available | B38: USD | D38: 0 | E38: =D36 | F38: =E36 | G38: =F36 | H38: =G36 | I38: =H36 | J38: =I36 | K38: =J36 | L38: =K36 | ... AB38: =AA36
A39: Loss vintage aged 2y - available | B39: USD | D39: 0 | E39: =MAX(D38-D47,0) | F39: =MAX(E38-E47,0) | G39: =MAX(F38-F47,0) | H39: =MAX(G38-G47,0) | I39: =MAX(H38-H47,0) | J39: =MAX(I38-I47,0) | K39: =MAX(J38-J47,0) | L39: =MAX(K38-K47,0) | ... AB39: =MAX(AA38-AA47,0)
A40: Loss vintage aged 3y - available | B40: USD | D40: 0 | E40: =MAX(D39-D46,0) | F40: =MAX(E39-E46,0) | G40: =MAX(F39-F46,0) | H40: =MAX(G39-G46,0) | I40: =MAX(H39-H46,0) | J40: =MAX(I39-I46,0) | K40: =MAX(J39-J46,0) | L40: =MAX(K39-K46,0) | ... AB40: =MAX(AA39-AA46,0)
A41: Loss vintage aged 4y - available | B41: USD | D41: 0 | E41: =MAX(D40-D45,0) | F41: =MAX(E40-E45,0) | G41: =MAX(F40-F45,0) | H41: =MAX(G40-G45,0) | I41: =MAX(H40-H45,0) | J41: =MAX(I40-I45,0) | K41: =MAX(J40-J45,0) | L41: =MAX(K40-K45,0) | ... AB41: =MAX(AA40-AA45,0)
A42: Loss vintage aged 5y - available | B42: USD | D42: 0 | E42: =MAX(D41-D44,0) | F42: =MAX(E41-E44,0) | G42: =MAX(F41-F44,0) | H42: =MAX(G41-G44,0) | I42: =MAX(H41-H44,0) | J42: =MAX(I41-I44,0) | K42: =MAX(J41-J44,0) | L42: =MAX(K41-K44,0) | ... AB42: =MAX(AA41-AA44,0)
A43: Loss vintage aged 5y - utilised | B43: USD | D43: =MIN(D42,MAX(D37,0)) | E43: =MIN(E42,MAX(E37,0)) | F43: =MIN(F42,MAX(F37,0)) | G43: =MIN(G42,MAX(G37,0)) | H43: =MIN(H42,MAX(H37,0)) | I43: =MIN(I42,MAX(I37,0)) | J43: =MIN(J42,MAX(J37,0)) | K43: =MIN(K42,MAX(K37,0)) | ... AB43: =MIN(AB42,MAX(AB37,0))
A44: Loss vintage aged 4y - utilised | B44: USD | D44: =MIN(D41,MAX(D37-D43,0)) | E44: =MIN(E41,MAX(E37-E43,0)) | F44: =MIN(F41,MAX(F37-F43,0)) | G44: =MIN(G41,MAX(G37-G43,0)) | H44: =MIN(H41,MAX(H37-H43,0)) | I44: =MIN(I41,MAX(I37-I43,0)) | J44: =MIN(J41,MAX(J37-J43,0)) | K44: =MIN(K41,MAX(K37-K43,0)) | ... AB44: =MIN(AB41,MAX(AB37-AB43,0))
A45: Loss vintage aged 3y - utilised | B45: USD | D45: =MIN(D40,MAX(D37-D43-D44,0)) | E45: =MIN(E40,MAX(E37-E43-E44,0)) | F45: =MIN(F40,MAX(F37-F43-F44,0)) | G45: =MIN(G40,MAX(G37-G43-G44,0)) | H45: =MIN(H40,MAX(H37-H43-H44,0)) | I45: =MIN(I40,MAX(I37-I43-I44,0)) | J45: =MIN(J40,MAX(J37-J43-J44,0)) | K45: =MIN(K40,MAX(K37-K43-K44,0)) | ... AB45: =MIN(AB40,MAX(AB37-AB43-AB44,0))
A46: Loss vintage aged 2y - utilised | B46: USD | D46: =MIN(D39,MAX(D37-D43-D44-D45,0)) | E46: =MIN(E39,MAX(E37-E43-E44-E45,0)) | F46: =MIN(F39,MAX(F37-F43-F44-F45,0)) | G46: =MIN(G39,MAX(G37-G43-G44-G45,0)) | H46: =MIN(H39,MAX(H37-H43-H44-H45,0)) | I46: =MIN(I39,MAX(I37-I43-I44-I45,0)) | J46: =MIN(J39,MAX(J37-J43-J44-J45,0)) | K46: =MIN(K39,MAX(K37-K43-K44-K45,0)) | ... AB46: =MIN(AB39,MAX(AB37-AB43-AB44-AB45,0))
A47: Loss vintage aged 1y - utilised | B47: USD | D47: =MIN(D38,MAX(D37-D43-D44-D45-D46,0)) | E47: =MIN(E38,MAX(E37-E43-E44-E45-E46,0)) | F47: =MIN(F38,MAX(F37-F43-F44-F45-F46,0)) | G47: =MIN(G38,MAX(G37-G43-G44-G45-G46,0)) | H47: =MIN(H38,MAX(H37-H43-H44-H45-H46,0)) | I47: =MIN(I38,MAX(I37-I43-I44-I45-I46,0)) | J47: =MIN(J38,MAX(J37-J43-J44-J45-J46,0)) | K47: =MIN(K38,MAX(K37-K43-K44-K45-K46,0)) | ... AB47: =MIN(AB38,MAX(AB37-AB43-AB44-AB45-AB46,0))
A48: Loss relief utilised (FIFO, ≤5y old) | B48: USD | D48: =D43+D44+D45+D46+D47 | E48: =E43+E44+E45+E46+E47 | F48: =F43+F44+F45+F46+F47 | G48: =G43+G44+G45+G46+G47 | H48: =H43+H44+H45+H46+H47 | I48: =I43+I44+I45+I46+I47 | J48: =J43+J44+J45+J46+J47 | K48: =K43+K44+K45+K46+K47 | ... AB48: =AB43+AB44+AB45+AB46+AB47
A49: Taxable income after loss relief | B49: USD | D49: =D37-D48 | E49: =E37-E48 | F49: =F37-F48 | G49: =G37-G48 | H49: =H37-H48 | I49: =I37-I48 | J49: =J37-J48 | K49: =K37-K48 | ... AB49: =AB37-AB48
A50: Profitable-to-date flag (starts CIT clock) | B50: 0/1 | D50: =IF(D35>0,1,0) | E50: =IF(OR(D50=1,E35>0),1,0) | F50: =IF(OR(E50=1,F35>0),1,0) | G50: =IF(OR(F50=1,G35>0),1,0) | H50: =IF(OR(G50=1,H35>0),1,0) | I50: =IF(OR(H50=1,I35>0),1,0) | J50: =IF(OR(I50=1,J35>0),1,0) | K50: =IF(OR(J50=1,K35>0),1,0) | L50: =IF(OR(K50=1,L35>0),1,0) | ... AB50: =IF(OR(AA50=1,AB35>0),1,0)
A51: CIT clock start year (first profit, capped) | C51: =MIN(IFERROR(MATCH(1,D50:AB50,0),CIT_CLOCK_CAP_YEAR),CIT_CLOCK_CAP_YEAR) | D51: Circular 78/2014 Art. 18
A52: Applicable CIT rate | B52: % | D52: =IF(D$5<$C$51+CIT_HOLIDAY_YEARS,0,IF(D$5<$C$51+CIT_HOLIDAY_YEARS+CIT_REDUCED_YEARS,CIT_RATE*CIT_REDUCED_FRACTION,CIT_RATE)) | E52: =IF(E$5<$C$51+CIT_HOLIDAY_YEARS,0,IF(E$5<$C$51+CIT_HOLIDAY_YEARS+CIT_REDUCED_YEARS,CIT_RATE*CIT_REDUCED_FRACTION,CIT_RATE)) | F52: =IF(F$5<$C$51+CIT_HOLIDAY_YEARS,0,IF(F$5<$C$51+CIT_HOLIDAY_YEARS+CIT_REDUCED_YEARS,CIT_RATE*CIT_REDUCED_FRACTION,CIT_RATE)) | G52: =IF(G$5<$C$51+CIT_HOLIDAY_YEARS,0,IF(G$5<$C$51+CIT_HOLIDAY_YEARS+CIT_REDUCED_YEARS,CIT_RATE*CIT_REDUCED_FRACTION,CIT_RATE)) | H52: =IF(H$5<$C$51+CIT_HOLIDAY_YEARS,0,IF(H$5<$C$51+CIT_HOLIDAY_YEARS+CIT_REDUCED_YEARS,CIT_RATE*CIT_REDUCED_FRACTION,CIT_RATE)) | I52: =IF(I$5<$C$51+CIT_HOLIDAY_YEARS,0,IF(I$5<$C$51+CIT_HOLIDAY_YEARS+CIT_REDUCED_YEARS,CIT_RATE*CIT_REDUCED_FRACTION,CIT_RATE)) | J52: =IF(J$5<$C$51+CIT_HOLIDAY_YEARS,0,IF(J$5<$C$51+CIT_HOLIDAY_YEARS+CIT_REDUCED_YEARS,CIT_RATE*CIT_REDUCED_FRACTION,CIT_RATE)) | K52: =IF(K$5<$C$51+CIT_HOLIDAY_YEARS,0,IF(K$5<$C$51+CIT_HOLIDAY_YEARS+CIT_REDUCED_YEARS,CIT_RATE*CIT_REDUCED_FRACTION,CIT_RATE)) | ... AB52: =IF(AB$5<$C$51+CIT_HOLIDAY_YEARS,0,IF(AB$5<$C$51+CIT_HOLIDAY_YEARS+CIT_REDUCED_YEARS,CIT_RATE*CIT_REDUCED_FRACTION,CIT_RATE))
A53: CIT payable | B53: USD | D53: =D49*D52 | E53: =E49*E52 | F53: =F49*F52 | G53: =G49*G52 | H53: =H49*H52 | I53: =I49*I52 | J53: =J49*J52 | K53: =K49*K52 | ... AB53: =AB49*AB52
A55: CASH FLOW & COVERAGE (USD)
A56: Cash available for debt service (CFADS) | B56: USD | D56: =D21-D53 | E56: =E21-E53 | F56: =F21-F53 | G56: =G21-G53 | H56: =H21-H53 | I56: =I21-I53 | J56: =J21-J53 | K56: =K21-K53 | ... AB56: =AB21-AB53
A57: Project cash flow (unlevered, post-tax) | B57: USD | C57: =-TOTAL_CAPEX | D57: =D56 | E57: =E56 | F57: =F56 | G57: =G56 | H57: =H56 | I57: =I56 | J57: =J56 | K57: =K56 | ... AB57: =AB56
A58: Equity cash flow | B58: USD | C58: =-EQUITY_INVESTMENT | D58: =D56-D27 | E58: =E56-E27 | F58: =F56-F27 | G58: =G56-G27 | H58: =H56-H27 | I58: =I56-I27 | J58: =J56-J27 | K58: =K56-K27 | ... AB58: =AB56-AB27
A59: Cumulative equity cash flow | B59: USD | C59: =C58 | D59: =C59+D58 | E59: =D59+E58 | F59: =E59+F58 | G59: =F59+G58 | H59: =G59+H58 | I59: =H59+I58 | J59: =I59+J58 | K59: =J59+K58 | ... AB59: =AA59+AB58
A60: DSCR (debt years) | B60: x | D60: =IF(D27>0,D56/D27,"") | E60: =IF(E27>0,E56/E27,"") | F60: =IF(F27>0,F56/F27,"") | G60: =IF(G27>0,G56/G27,"") | H60: =IF(H27>0,H56/H27,"") | I60: =IF(I27>0,I56/I27,"") | J60: =IF(J27>0,J56/J27,"") | K60: =IF(K27>0,K56/K27,"") | ... AB60: =IF(AB27>0,AB56/AB27,"")
A62: OFFTAKER (BUYER) POSITION (USD)
A63: BAU EVN bill (energy + demand) | B63: USD | D63: =BAU_BILL_Y1*D6 | E63: =BAU_BILL_Y1*E6 | F63: =BAU_BILL_Y1*F6 | G63: =BAU_BILL_Y1*G6 | H63: =BAU_BILL_Y1*H6 | I63: =BAU_BILL_Y1*I6 | J63: =BAU_BILL_Y1*J6 | K63: =BAU_BILL_Y1*K6 | ... AB63: =BAU_BILL_Y1*AB6
A64: Buyer cost with project | B64: USD | D64: =(OPT_BILL_Y1+BASE_SERVED_RETAIL*(1-D9))*D6+D12+D14+D15 | E64: =(OPT_BILL_Y1+BASE_SERVED_RETAIL*(1-E9))*E6+E12+E14+E15 | F64: =(OPT_BILL_Y1+BASE_SERVED_RETAIL*(1-F9))*F6+F12+F14+F15 | G64: =(OPT_BILL_Y1+BASE_SERVED_RETAIL*(1-G9))*G6+G12+G14+G15 | H64: =(OPT_BILL_Y1+BASE_SERVED_RETAIL*(1-H9))*H6+H12+H14+H15 | I64: =(OPT_BILL_Y1+BASE_SERVED_RETAIL*(1-I9))*I6+I12+I14+I15 | J64: =(OPT_BILL_Y1+BASE_SERVED_RETAIL*(1-J9))*J6+J12+J14+J15 | K64: =(OPT_BILL_Y1+BASE_SERVED_RETAIL*(1-K9))*K6+K12+K14+K15 | ... AB64: =(OPT_BILL_Y1+BASE_SERVED_RETAIL*(1-AB9))*AB6+AB12+AB14+AB15
A65: Buyer savings vs BAU | B65: USD | D65: =D63-D64 | E65: =E63-E64 | F65: =F63-F64 | G65: =G63-G64 | H65: =H63-H64 | I65: =I63-I64 | J65: =J63-J64 | K65: =K63-K64 | ... AB65: =AB63-AB64
A66: Buyer savings (% of BAU) | B66: % | D66: =IF(D63=0,"",D65/D63) | E66: =IF(E63=0,"",E65/E63) | F66: =IF(F63=0,"",F65/F63) | G66: =IF(G63=0,"",G65/G63) | H66: =IF(H63=0,"",H65/H63) | I66: =IF(I63=0,"",I65/I63) | J66: =IF(J63=0,"",J65/J63) | K66: =IF(K63=0,"",K65/K63) | ... AB66: =IF(AB63=0,"",AB65/AB63)
A68: RETURN METRICS (Excel formulas)
A69: Equity IRR | C69: =IRR(C58:AB58)
A70: Project IRR (unlevered) | C70: =IRR(C57:AB57)
A71: Equity NPV @ owner discount rate | C71: =NPV(DISC_RATE,D58:AB58)+C58
A72: Minimum DSCR (debt years) | C72: =MIN(D60:AB60) | D72: MIN ignores the blank non-debt years
A73: Average DSCR (debt years) | C73: =AVERAGE(D60:AB60)
A74: First year cumulative equity CF ≥ 0 | C74: =MATCH(TRUE,INDEX(D59:AB59>=0,0),0)
A75: Simple equity payback | C75: =IF(ISNA($C$74),"n/a",$C$74-1+IFERROR(-INDEX(C59:AB59,$C$74)/INDEX(D58:AB58,$C$74),0)) | D75: years
A76: ROI (cumulative equity CF / equity) | C76: =SUM(D58:AB58)/EQUITY_INVESTMENT
A77: Buyer savings, years 1-10 (% of BAU) | C77: =SUM(D65:M65)/SUM(D63:M63)
A79: CHECKS - EXCEL vs ENGINE (per-year tie-out)
A80: Equity cash flow (engine) | B80: USD | C80: -1288725.8 | D80: 31003.122 | E80: 48271.096 | F80: 66147.208 | G80: 84652.839 | H80: 103810.12 | I80: 123641.95 | J80: 144172.05 | K80: 145302.13 | L80: 144018.12 | M80: 161207.14 | N80: -573878.65 | O80: 674426.29 | P80: 697165.99 | Q80: 720706.02 | R80: 745074.49 | S80: 770300.52 | T80: 740805.89 | U80: 764834.86 | V80: 759050.83 | W80: 784800.43 | X80: 782926.58 | Y80: 810519.82 | Z80: 839083.73 | AA80: 868652.39 | AB80: 899261.11
A81: CFADS (engine) | B81: USD | D81: 489297.2 | E81: 506565.17 | F81: 524441.28 | G81: 542946.92 | H81: 562104.19 | I81: 581936.03 | J81: 602466.13 | K81: 603596.21 | L81: 602312.2 | M81: 619501.22 | N81: -573878.65 | O81: 674426.29 | P81: 697165.99 | Q81: 720706.02 | R81: 745074.49 | S81: 770300.52 | T81: 740805.89 | U81: 764834.86 | V81: 759050.83 | W81: 784800.43 | X81: 782926.58 | Y81: 810519.82 | Z81: 839083.73 | AA81: 868652.39 | AB81: 899261.11
A82: CIT (engine) | B82: USD | D82: 0 | E82: 0 | F82: 0 | G82: 0 | H82: 0 | I82: 0 | J82: 0 | K82: 20122.826 | L82: 43407.957 | M82: 48994.573 | N82: 39613.401 | O82: 42054.128 | P82: 44580.761 | Q82: 47196.32 | R82: 49903.928 | S82: 52706.82 | T82: 111216.69 | U82: 117223.93 | V82: 154101 | W82: 160538.4 | X82: 195731.64 | Y82: 202629.95 | Z82: 209770.93 | AA82: 217163.1 | AB82: 224815.28
A83: Max |Excel − engine| this year | B83: USD | C83: =ABS(C58-C80) | D83: =MAX(ABS(D58-D80),ABS(D56-D81),ABS(D53-D82)) | E83: =MAX(ABS(E58-E80),ABS(E56-E81),ABS(E53-E82)) | F83: =MAX(ABS(F58-F80),ABS(F56-F81),ABS(F53-F82)) | G83: =MAX(ABS(G58-G80),ABS(G56-G81),ABS(G53-G82)) | H83: =MAX(ABS(H58-H80),ABS(H56-H81),ABS(H53-H82)) | I83: =MAX(ABS(I58-I80),ABS(I56-I81),ABS(I53-I82)) | J83: =MAX(ABS(J58-J80),ABS(J56-J81),ABS(J53-J82)) | K83: =MAX(ABS(K58-K80),ABS(K56-K81),ABS(K53-K82)) | ... AB83: =MAX(ABS(AB58-AB80),ABS(AB56-AB81),ABS(AB53-AB82))
A85: Check | C85: Excel | D85: Engine | E85: Delta | F85: Status
A86: Per-year cash flow tie-out (max delta, all years) | C86: =MAX(C83:AB83) | D86: 0 | E86: =ABS(C86-D86) | F86: =IF(ABS(C86-D86)<=1.0,"PASS","REVIEW")
A87: Equity IRR | C87: =$C$69 | D87: 0.14647206 | E87: =ABS(C87-D87) | F87: =IF(ABS(C87-D87)<=0.0005,"PASS","REVIEW")
A88: Project IRR | C88: =$C$70 | D88: 0.12229483 | E88: =ABS(C88-D88) | F88: =IF(ABS(C88-D88)<=0.0005,"PASS","REVIEW")
A89: Equity NPV | C89: =$C$71 | D89: 1032757.9 | E89: =ABS(C89-D89) | F89: =IF(ABS(C89-D89)<=1.0,"PASS","REVIEW")
A90: Minimum DSCR | C90: =$C$72 | D90: 1.067649 | E90: =ABS(C90-D90) | F90: =IF(ABS(C90-D90)<=0.005,"PASS","REVIEW")
A91: Average DSCR | C91: =$C$73 | D91: 1.2295962 | E91: =ABS(C91-D91) | F91: =IF(ABS(C91-D91)<=0.005,"PASS","REVIEW")
A92: Simple equity payback | C92: =$C$75 | D92: 12.195007 | E92: =ABS(C92-D92) | F92: =IF(ABS(C92-D92)<=0.05,"PASS","REVIEW")
A93: ROI | C93: =$C$76 | D93: 8.7962511 | E93: =ABS(C93-D93) | F93: =IF(ABS(C93-D93)<=0.0005,"PASS","REVIEW")
A94: Buyer savings, years 1-10 (% of BAU) | C94: =$C$77 | D94: 0.076076872 | E94: =ABS(C94-D94) | F94: =IF(ABS(C94-D94)<=0.0005,"PASS","REVIEW")

Sheet FX Sensitivity
A1: FX Sensitivity - VND depreciation vs USD returns
A2: Cash flows are VND-denominated (EVN tariff / DPPA settlement) but reported in USD at the fixed contract rate. Each scenario deflates the year-t USD equity cash flow by (1+d)^t. Debt is assumed VND-denominated, so DSCR is unchanged. The rate cells are editable; engine columns validate the default scenarios.
A4: VND depreciation (per year) | B4: Equity IRR (USD) | C4: Equity NPV (USD) | D4: Equity IRR (engine) | E4: Equity NPV (engine) | F4: Status
A5: 0 | B5: =IRR(B12:AA12) | C5: =NPV(DISC_RATE,C12:AA12)+B12 | D5: 0.14647206 | E5: 1032757.9 | F5: =IF(AND(ABS(B5-D5)<=0.0005,ABS(C5-E5)<=1.0),"PASS","REVIEW")
A6: 0.01 | B6: =IRR(B13:AA13) | C6: =NPV(DISC_RATE,C13:AA13)+B13 | D6: 0.13512085 | E6: 714095.34 | F6: =IF(AND(ABS(B6-D6)<=0.0005,ABS(C6-E6)<=1.0),"PASS","REVIEW")
A7: 0.02 | B7: =IRR(B14:AA14) | C7: =NPV(DISC_RATE,C14:AA14)+B14 | D7: 0.12399222 | E7: 448202.92 | F7: =IF(AND(ABS(B7-D7)<=0.0005,ABS(C7-E7)<=1.0),"PASS","REVIEW")
A8: 0.03 | B8: =IRR(B15:AA15) | C8: =NPV(DISC_RATE,C15:AA15)+B15 | D8: 0.11307967 | E8: 225404.37 | F8: =IF(AND(ABS(B8-D8)<=0.0005,ABS(C8-E8)<=1.0),"PASS","REVIEW")
A10: Helper - FX-adjusted equity cash flow per scenario (USD): CF_t / (1 + d)^t
B11: 0 | C11: 1 | D11: 2 | E11: 3 | F11: 4 | G11: 5 | H11: 6 | I11: 7 | J11: 8 | K11: 9 | L11: 10 | M11: 11 | N11: 12 | O11: 13 | P11: 14 | Q11: 15 | R11: 16 | S11: 17 | T11: 18 | U11: 19 | V11: 20 | W11: 21 | X11: 22 | Y11: 23 | Z11: 24 | AA11: 25
A12: =A5 | B12: ='Pro Forma (Audit)'!C58/(1+$A5)^B$11 | C12: ='Pro Forma (Audit)'!D58/(1+$A5)^C$11 | D12: ='Pro Forma (Audit)'!E58/(1+$A5)^D$11 | E12: ='Pro Forma (Audit)'!F58/(1+$A5)^E$11 | F12: ='Pro Forma (Audit)'!G58/(1+$A5)^F$11 | G12: ='Pro Forma (Audit)'!H58/(1+$A5)^G$11 | H12: ='Pro Forma (Audit)'!I58/(1+$A5)^H$11 | I12: ='Pro Forma (Audit)'!J58/(1+$A5)^I$11 | ... AA12: ='Pro Forma (Audit)'!AB58/(1+$A5)^AA$11
A13: =A6 | B13: ='Pro Forma (Audit)'!C58/(1+$A6)^B$11 | C13: ='Pro Forma (Audit)'!D58/(1+$A6)^C$11 | D13: ='Pro Forma (Audit)'!E58/(1+$A6)^D$11 | E13: ='Pro Forma (Audit)'!F58/(1+$A6)^E$11 | F13: ='Pro Forma (Audit)'!G58/(1+$A6)^F$11 | G13: ='Pro Forma (Audit)'!H58/(1+$A6)^G$11 | H13: ='Pro Forma (Audit)'!I58/(1+$A6)^H$11 | I13: ='Pro Forma (Audit)'!J58/(1+$A6)^I$11 | ... AA13: ='Pro Forma (Audit)'!AB58/(1+$A6)^AA$11
A14: =A7 | B14: ='Pro Forma (Audit)'!C58/(1+$A7)^B$11 | C14: ='Pro Forma (Audit)'!D58/(1+$A7)^C$11 | D14: ='Pro Forma (Audit)'!E58/(1+$A7)^D$11 | E14: ='Pro Forma (Audit)'!F58/(1+$A7)^E$11 | F14: ='Pro Forma (Audit)'!G58/(1+$A7)^F$11 | G14: ='Pro Forma (Audit)'!H58/(1+$A7)^G$11 | H14: ='Pro Forma (Audit)'!I58/(1+$A7)^H$11 | I14: ='Pro Forma (Audit)'!J58/(1+$A7)^I$11 | ... AA14: ='Pro Forma (Audit)'!AB58/(1+$A7)^AA$11
A15: =A8 | B15: ='Pro Forma (Audit)'!C58/(1+$A8)^B$11 | C15: ='Pro Forma (Audit)'!D58/(1+$A8)^C$11 | D15: ='Pro Forma (Audit)'!E58/(1+$A8)^D$11 | E15: ='Pro Forma (Audit)'!F58/(1+$A8)^E$11 | F15: ='Pro Forma (Audit)'!G58/(1+$A8)^F$11 | G15: ='Pro Forma (Audit)'!H58/(1+$A8)^G$11 | H15: ='Pro Forma (Audit)'!I58/(1+$A8)^H$11 | I15: ='Pro Forma (Audit)'!J58/(1+$A8)^I$11 | ... AA15: ='Pro Forma (Audit)'!AB58/(1+$A8)^AA$11

Sheet Buyer Analysis
B1: Buyer Analysis - Cost vs Business-As-Usual
B2: Annual electricity cost with the project compared against the EVN-only baseline (USD)
B4: Year 1 Snapshot
B5: Year 1 BAU Cost (USD) | C5: 769044.53
B6: Year 1 Cost With Project (USD) | C6: 709112.62
B7: Year 1 Savings (USD) | C7: 59931.914
B8: Year 1 Savings (% of BAU) | C8: 0.077930356
B9: First 10 Years Savings (USD) | C9: 702435.33 | D9: Cumulative, years 1-10
B10: First 10 Years Savings (% of BAU) | C10: 0.076076872
B11: Lifetime Savings (USD) | C11: 2328139.2 | D11: Cumulative over analysis period
B12: Lifetime Savings (% of BAU) | C12: 0.07269175
A14: Year | B14: BAU Cost (USD) | C14: Cost With Project (USD) | D14: Savings (USD) | E14: Savings (% of BAU) | F14: Cumulative Savings (USD)
A15: 1 | B15: 769044.53 | C15: 709112.62 | D15: 59931.914 | E15: 0.077930356 | F15: 59931.914
A16: 2 | B16: 799806.31 | C16: 737788.77 | D16: 62017.545 | E16: 0.077540704 | F16: 121949.46
A17: 3 | B17: 831798.56 | C17: 767622.81 | D17: 64175.755 | E17: 0.077153001 | F17: 186125.21
A18: 4 | B18: 865070.51 | C18: 798661.43 | D18: 66409.072 | E18: 0.076767236 | F18: 252534.29
A19: 5 | B19: 899673.33 | C19: 830953.22 | D19: 68720.107 | E19: 0.0763834 | F19: 321254.39
A20: 6 | B20: 935660.26 | C20: 864548.69 | D20: 71111.567 | E20: 0.076001483 | F20: 392365.96
A21: 7 | B21: 973086.67 | C21: 899500.42 | D21: 73586.25 | E21: 0.075621476 | F21: 465952.21
A22: 8 | B22: 1012010.1 | C22: 935863.09 | D22: 76147.051 | E22: 0.075243368 | F22: 542099.26
A23: 9 | B23: 1052490.5 | C23: 973693.57 | D23: 78796.969 | E23: 0.074867152 | F23: 620896.23
A24: 10 | B24: 1094590.2 | C24: 1013051.1 | D24: 81539.104 | E24: 0.074492816 | F24: 702435.33
A25: 11 | B25: 1138373.8 | C25: 1053997.1 | D25: 84376.665 | E25: 0.074120352 | F25: 786812
A26: 12 | B26: 1183908.7 | C26: 1096595.7 | D26: 87312.973 | E26: 0.07374975 | F26: 874124.97
... A39: 25 | B39: 1971295 | C39: 1835084 | D39: 136211.02 | E39: 0.069097226 | F39: 2328139.2

Sheet Developer Returns
B1: Developer Returns - Financing & Cash Flow
B2: Seller/ESCO investment case: sources & uses, return metrics and annual equity cash flow (USD)
B4: Sources & Uses
B5: Total Investment (USD) | C5: 4295752.8
B6: Debt Principal (USD) | C6: 3007026.9
B7: Equity Investment (USD) | C7: 1288725.8
B9: Return Metrics
B10: Equity IRR | C10: 0.14647206
B11: Project IRR | C11: 0.12229483
B12: NPV (USD) | C12: 1032757.9 | D12: At owner discount rate
B13: Minimum DSCR (debt years) | C13: 1.067649
B14: Average DSCR | C14: 1.2295962
B15: Simple Payback (Years) | C15: 12.195007
B16: ROI (cumulative equity CF / equity) | C16: 8.7962511
A18: Year | B18: Revenue (USD) | C18: O&M + Replacement (USD) | D18: CIT (USD) | E18: CFADS (USD) | F18: Debt Service (USD) | G18: DSCR | H18: Equity Cash Flow (USD) | I18: Cumulative Equity CF (USD)
A19: 1 | B19: 539387.07 | C19: 50089.873 | D19: 0 | E19: 489297.2 | F19: 458294.08 | G19: 1.067649 | H19: 31003.122 | I19: -1257722.7
A20: 2 | B20: 558157.74 | C20: 51592.569 | D20: 0 | E20: 506565.17 | F20: 458294.08 | G20: 1.1053278 | H20: 48271.096 | I20: -1209451.6
A21: 3 | B21: 577581.63 | C21: 53140.346 | D21: 0 | E21: 524441.28 | F21: 458294.08 | G21: 1.1443335 | H21: 66147.208 | I21: -1143304.4
A22: 4 | B22: 597681.47 | C22: 54734.557 | D22: 0 | E22: 542946.92 | F22: 458294.08 | G22: 1.1847129 | H22: 84652.839 | I22: -1058651.6
A23: 5 | B23: 618480.79 | C23: 56376.593 | D23: 0 | E23: 562104.19 | F23: 458294.08 | G23: 1.2265142 | H23: 103810.12 | I23: -954841.45
A24: 6 | B24: 640003.92 | C24: 58067.891 | D24: 0 | E24: 581936.03 | F24: 458294.08 | G24: 1.2697874 | H24: 123641.95 | I24: -831199.5
A25: 7 | B25: 662276.05 | C25: 59809.928 | D25: 0 | E25: 602466.13 | F25: 458294.08 | G25: 1.3145841 | H25: 144172.05 | I25: -687027.45
A26: 8 | B26: 685323.26 | C26: 61604.226 | D26: 20122.826 | E26: 603596.21 | F26: 458294.08 | G26: 1.31705 | H26: 145302.13 | I26: -541725.32
A27: 9 | B27: 709172.51 | C27: 63452.353 | D27: 43407.957 | E27: 602312.2 | F27: 458294.08 | G27: 1.3142483 | H27: 144018.12 | I27: -397707.2
A28: 10 | B28: 733851.71 | C28: 65355.923 | D28: 48994.573 | E28: 619501.22 | F28: 458294.08 | G28: 1.3517548 | H28: 161207.14 | I28: -236500.05
A29: 11 | B29: 759389.75 | C29: 1293655 | D29: 39613.401 | E29: -573878.65 | F29: 0 | H29: -573878.65 | I29: -810378.7
A30: 12 | B30: 785816.52 | C30: 69336.099 | D30: 42054.128 | E30: 674426.29 | F30: 0 | H30: 674426.29 | I30: -135952.41
A31: 13 | B31: 813162.93 | C31: 71416.182 | D31: 44580.761 | E31: 697165.99 | F31: 0 | H31: 697165.99 | I31: 561213.58
A32: 14 | B32: 841461 | C32: 73558.667 | D32: 47196.32 | E32: 720706.02 | F32: 0 | H32: 720706.02 | I32: 1281919.6
A33: 15 | B33: 870743.85 | C33: 75765.427 | D33: 49903.928 | E33: 745074.49 | F33: 0 | H33: 745074.49 | I33: 2026994.1
A34: 16 | B34: 901045.73 | C34: 78038.39 | D34: 52706.82 | E34: 770300.52 | F34: 0 | H34: 770300.52 | I34: 2797294.6
A35: 17 | B35: 932402.12 | C35: 80379.542 | D35: 111216.69 | E35: 740805.89 | F35: 0 | H35: 740805.89 | I35: 3538100.5
A36: 18 | B36: 964849.72 | C36: 82790.928 | D36: 117223.93 | E36: 764834.86 | F36: 0 | H36: 764834.86 | I36: 4302935.4
A37: 19 | B37: 998426.49 | C37: 85274.656 | D37: 154101 | E37: 759050.83 | F37: 0 | H37: 759050.83 | I37: 5061986.2
A38: 20 | B38: 1033171.7 | C38: 87832.896 | D38: 160538.4 | E38: 784800.43 | F38: 0 | H38: 784800.43 | I38: 5846786.6
A39: 21 | B39: 1069126.1 | C39: 90467.883 | D39: 195731.64 | E39: 782926.58 | F39: 0 | H39: 782926.58 | I39: 6629713.2
A40: 22 | B40: 1106331.7 | C40: 93181.919 | D40: 202629.95 | E40: 810519.82 | F40: 0 | H40: 810519.82 | I40: 7440233
... A43: 25 | B43: 1225898.8 | C43: 101822.4 | D43: 224815.28 | E43: 899261.11 | F43: 0 | H43: 899261.11 | I43: 10047230

Sheet Technical Results
A1: Metric | B1: Value
A2: System Sizing
A3: PV Size (kW) | B3: 5943.6183
A4: Battery Power (kW) | B4: 1799.38
A5: Battery Energy (kWh) | B5: 10823.88
A7: Annual Energy Balance (Year 1)
A8: PV to Load (kWh) | B8: 3893817.6
A9: PV to Storage (kWh) | B9: 2838149.6
A10: PV to Grid (kWh) | B10: 0
A11: Storage to Load (kWh) | B11: 2553477.8
A12: Grid to Load (kWh) | B12: 3196666.3
A13: PV Curtailed (kWh) | B13: 1636900.4
A14: Grid to Storage (kWh) | B14: 0
A16: Year-1 Utility Bill Comparison
A17: BAU Utility Bill (USD) | B17: 769044.53
A18: Optimized Utility Bill (USD) | B18: 169725.54
A19: Utility Bill Savings (USD) | B19: 599318.99
A20: BAU Demand Charge (USD) | B20: 0
A21: Optimized Demand Charge (USD) | B21: 0
A22: Demand Charge Savings (USD) | B22: 0

Sheet Dispatch Profile
A1: Hour | B1: Load (kW) | C1: PV Irradiation (W/m²) | D1: PV Generation Total (kW) | E1: PV to Load (kW) | F1: PV to Storage (kW) | G1: PV to Grid (kW) | H1: PV Curtailed (kW) | I1: Grid to Load (kW) | J1: Grid to Storage (kW) | K1: Storage to Load (kW)
A2: 1 | B2: 1020 | C2: 0 | D2: 0 | E2: 0 | F2: 0 | G2: 0 | H2: 0 | I2: 1020 | J2: 0 | K2: 0
A3: 2 | B3: 1078.4 | C3: 0 | D3: 0 | E3: 0 | F3: 0 | G3: 0 | H3: 0 | I3: 1078.4 | J3: 0 | K3: 0
A4: 3 | B4: 906.4 | C4: 0 | D4: 0 | E4: 0 | F4: 0 | G4: 0 | H4: 0 | I4: 906.4 | J4: 0 | K4: 0
A5: 4 | B5: 860.8 | C5: 0 | D5: 0 | E5: 0 | F5: 0 | G5: 0 | H5: 0 | I5: 332.523 | J5: 0 | K5: 554.40701
A6: 5 | B6: 996.8 | C6: 0 | D6: 0 | E6: 0 | F6: 0 | G6: 0 | H6: 0 | I6: 0 | J6: 0 | K6: 1046.1044
A7: 6 | B7: 983.2 | C7: 0 | D7: 0 | E7: 0 | F7: 0 | G7: 0 | H7: 0 | I7: 0 | J7: 0 | K7: 1031.8317
A8: 7 | B8: 586.4 | C8: 0 | D8: 17.432625 | E8: 17.432625 | F8: 0 | G8: 0 | H8: 0 | I8: 0 | J8: 0 | K8: 597.9723
A9: 8 | B9: 104.269 | C9: 0 | D9: 539.40704 | E9: 109.42643 | F9: -429.98061 | G9: 0 | H9: 0 | I9: 0 | J9: 0 | K9: 0
A10: 9 | B10: 89.172 | C10: 0 | D10: 1262.2644 | E10: 93.582688 | F10: -1168.6817 | G10: 0 | H10: 0 | I10: 0 | J10: 0 | K10: 0
A11: 10 | B11: 105.232 | C11: 0 | D11: 2341.833 | E11: 110.43601 | F11: -1888.3791 | G11: 0 | H11: 343.01793 | I11: 0 | J11: 0 | K11: 0
A12: 11 | B12: 89.626 | C12: 0 | D12: 2613.2251 | E12: 94.059144 | F12: -1888.3791 | G12: 0 | H12: 630.7869 | I12: 0 | J12: 0 | K12: 0
A13: 12 | B13: 119.641 | C13: 0 | D13: 2157.7237 | E13: 125.55877 | F13: -1888.3791 | G13: 0 | H13: 143.78584 | I13: 0 | J13: 0 | K13: 0
... A8761: 8760 | B8761: 1216 | C8761: 0 | D8761: 0 | E8761: 0 | F8761: 0 | G8761: 0 | H8761: 0 | I8761: 0 | J8761: 0 | K8761: 1276.1466

Sheet Load Duration
A1: Rank | B1: Load (kW) | C1: Net Load (kW)
A2: 1 | B2: 2428 | C2: 2428
A3: 2 | B3: 2418.5558 | C3: 2418.556
A4: 3 | B4: 2414.4 | C4: 2379.2
A5: 4 | B5: 2405.0087 | C5: 2369.946
A6: 5 | B6: 2390.381 | C6: 2342.123
A7: 6 | B7: 2389.6 | C7: 2330.4
A8: 7 | B8: 2387.844 | C8: 2321.335
A9: 8 | B9: 2381.0831 | C9: 2228.07
A10: 9 | B10: 2380.3051 | C10: 2208.8
A11: 10 | B11: 2379.2 | C11: 2200.208
A12: 11 | B12: 2378.556 | C12: 2156.8
A13: 12 | B13: 2369.9456 | C13: 2148.411
... A8761: 8760 | B8761: 0 | C8761: 0
